Workbook

Sheet Datos
A1: Código AC | B1: Fecha de inicio | C1: Comentarios | D1: Repuesto | E1: Equipo | F1: Activo | G1: Serie
A2: BDG-EQUIO-00015284 | B2: 41942 | C2: -NO_DEFINIDO - se realiza cambio de bombillo de otoscopio equipo queda en correcto funcionamiento | D2: Bombillo | E2: =VLOOKUP(A2,Equipos!$1:$1048576,2,0) -> Equipo Organos De Los Sentidos | F2: 15284 | G2: =VLOOKUP(A2,Equipos!$A$2:$H$16545,4,FALSE) -> N/A
A3: BAN-LARIN-00006779 | B3: 41942 | C3: -NO_DEFINIDO - CREADA DESDE AMsi&#x0D; &#x0D; Se realiza cambio de bombillo de mango de laringoscopio. &#x0D; Se realizan pruebas de funcionamiento &#x0D; Equipo funcionando correctamente | D3: Bombillo | E3: =VLOOKUP(A3,Equipos!$1:$1048576,2,0) -> Laringoscopio | F3: 6779 | G3: =VLOOKUP(A3,Equipos!$A$2:$H$16545,4,FALSE) -> N/A
A4: BAN-LARIN-00015725 | B4: 41942 | C4: -NO_DEFINIDO - CREADA DESDE AMsi&#x0D; &#x0D; Se realiza cambio de bombillo de mango de laringo de la sala 1, se realizan pruebas y equipo queda funcionando | D4: Bombillo | E4: =VLOOKUP(A4,Equipos!$1:$1048576,2,0) -> Laringoscopio | F4: 15725 | G4: =VLOOKUP(A4,Equipos!$A$2:$H$16545,4,FALSE) -> N/A
A5: BMO-TRMOH-00009050 | B5: 41942 | C5: 14/07/2022-NO_DEFINIDO - Solicitud de Servico Creada desde AMSi, 14/07/2022-Novatecnica - la sonda del termohigrometro se encuentra cortada, por lo que se procede a soldar a la tarjeta y se cambia la bateria. Se realizan pruebas y funciona correctamente. | D5: Bateria | E5: =VLOOKUP(A5,Equipos!$1:$1048576,2,0) -> Termohigrometro Digital | F5: 9050 | G5: =VLOOKUP(A5,Equipos!$A$2:$H$16545,4,FALSE) -> N/A
A6: BAN-LARIN-00012366 | B6: 41942 | C6: 21/07/2022-NO_DEFINIDO - Solicitud de Servico Creada desde AMSi, 21/07/2022-Biomedico2 - Se realiza verificación de laringoscopio y se evidencia bombillo dañado Se realiza cambio de bombillo Se entrega al servicio sin novedad | D6: Bombillo | E6: =VLOOKUP(A6,Equipos!$1:$1048576,2,0) -> Laringoscopio | F6: 12366 | G6: =VLOOKUP(A6,Equipos!$A$2:$H$16545,4,FALSE) -> N/A
A7: BMO-TRMOH-00015064 | B7: 41942 | C7: 21/07/2022-NO_DEFINIDO - Solicitud de Servico Creada desde AMSi, 26/07/2022-Biomedico1 - Se realiza reemplazo de pantalla la cual se encontro partida se intala pantalla equipo funciona correctamente | D7: Pantalla | E7: =VLOOKUP(A7,Equipos!$1:$1048576,2,0) -> Termohigrometro Digital | F7: 15064 | G7: =VLOOKUP(A7,Equipos!$A$2:$H$16545,4,FALSE) -> N/A
A8: BDG-EQUIO-00007377 | B8: 41942 | C8: 01/08/2022-NO_DEFINIDO - Solicitud de Servico Creada desde AMSi, 02/08/2022-Biomedico1 - se realiza cambio de bombillo de equipo de órganos se realizan pruebas de funcionamiento equipo funciona correctamente | D8: Bombillo | E8: =VLOOKUP(A8,Equipos!$1:$1048576,2,0) -> Equipo De Organos Portatil | F8: 7377 | G8: =VLOOKUP(A8,Equipos!$A$2:$H$16545,4,FALSE) -> N/A
A9: BDG-EQUIO-00013803 | B9: 41942 | C9: 03/08/2022-NO_DEFINIDO - Solicitud de Servico Creada desde AMSi, 04/08/2022-Senior - Se cambia el bombillo del otoscopio del equipo de órganos, se realiza pruebas de funcionamiento y queda OK. | D9: Bombillo | E9: =VLOOKUP(A9,Equipos!$1:$1048576,2,0) -> Equipo Organos De Los Sentidos | F9: 13803 | G9: =VLOOKUP(A9,Equipos!$A$2:$H$16545,4,FALSE) -> N/A
A10: BDG-TENAT-00012867 | B10: 41942 | C10: 17/08/2022-NO_DEFINIDO - Solicitud de Servico Creada desde AMSi, 31/08/2022-Biomedico1 - Se realiza cambios de brazalete ya que presenta desgaste se realizan pruebas de funcionamiento equipo funciona correctamente | D10: Brazalete | E10: =VLOOKUP(A10,Equipos!$1:$1048576,2,0) -> Tensiometro De Atril | F10: 12867 | G10: =VLOOKUP(A10,Equipos!$A$2:$H$16545,4,FALSE) -> N/A
A11: OTP-CAMIL-00009406 | B11: 41942 | C11: 08/11/2022-NO_DEFINIDO - Solicitud de Servico Creada desde AMSi, 09/12/2022-Senior - Equipo se da de baja, ya que presenta deterioro en su estructura que no pudo ser reparada | D11: Baja | E11: =VLOOKUP(A11,Equipos!$1:$1048576,2,0) -> Camilla Fija-Divan | F11: 9406 | G11: =VLOOKUP(A11,Equipos!$A$2:$H$16545,4,FALSE) -> N/A
A12: OTP-CAMIL-00010629 | B12: 41942 | C12: 10/11/2022-NO_DEFINIDO - Solicitud de Servico Creada desde AMSi, 01/12/2022-Senior - Se realiza reemplazo de rueda por una de back up, pruebas de funcionamiento ok. Se adjunta reporte. | D12: Ruedas | E12: =VLOOKUP(A12,Equipos!$1:$1048576,2,0) -> Camilla De Transporte | F12: 10629 | G12: =VLOOKUP(A12,Equipos!$A$2:$H$16545,4,FALSE) -> N/A
A13: BDG-EQUIO-00016126 | B13: 41942 | C13: 30/11/2022-NO_DEFINIDO - Solicitud de Servico Creada desde AMSi, 25/01/2023-Senior - Se realiza ajuste en switch de encendido del equipo y se realiza el cambio de baterías | D13: Bateria | E13: =VLOOKUP(A13,Equipos!$1:$1048576,2,0) -> Equipo De Organos Portatil | F13: 16126/16127 | G13: =VLOOKUP(A13,Equipos!$A$2:$H$16545,4,FALSE) -> N/A
A14: OTP-CAMIL-00008945 | B14: 41942 | C14: 08/02/2023-NO_DEFINIDO - Solicitud de Servico Creada desde AMSi, 01/03/2023-Senior - Se realiza cambio de rueda. | D14: Ruedas | E14: =VLOOKUP(A14,Equipos!$1:$1048576,2,0) -> Camilla De Transporte | F14: 8945 | G14: =VLOOKUP(A14,Equipos!$A$2:$H$16545,4,FALSE) -> N/A
A15: BFE-LAMAU-00005914 | B15: 41942 | C15: 17/04/2023-NO_DEFINIDO - Solicitud de Servico Creada desde AMSi, 24/04/2023-Biomedico2 - Se realiza verificación de lámparas pieliticas, se realiza ajuste de soket y manilar ,se realiza cambio de bombillo, Se entrega sin novedad | D15: Bombillo | E15: =VLOOKUP(A15,Equipos!$1:$1048576,2,0) -> Lampara Auxiliar De Procedimientos | F15: 5914 | G15: =VLOOKUP(A15,Equipos!$A$2:$H$16545,4,FALSE) -> N/A
A16: BDG-TENPO-00005909 | B16: 41942 | C16: 10/01/2024-NO_DEFINIDO - Solicitud de Servico Creada desde AMSi, 11/01/2024-Biomedico1 - Se realiza ajuste de soporte de tensiómetro se realiza cambio de brazalete se realizan pruebas de funcionamiento equipo funciona correctamente | D16: Brazalete | E16: =VLOOKUP(A16,Equipos!$1:$1048576,2,0) -> Tensiometro Portatil | F16: 5909 | G16: =VLOOKUP(A16,Equipos!$A$2:$H$16545,4,FALSE) -> N/A
A17: BMO-TRMOH-00003811 | B17: 41942 | C17: 18/01/2024-NO_DEFINIDO - Solicitud de Servico Creada desde AMSi, 19/01/2024-Biomedico1 - Se realiza ajuste de conexión de batería se realizan pruebas equipo funciona correctamente | D17: Bateria | E17: =VLOOKUP(A17,Equipos!$1:$1048576,2,0) -> Termometro Digital | F17: 3811 | G17: =VLOOKUP(A17,Equipos!$A$2:$H$16545,4,FALSE) -> N/A
A18: BMO-TRMOH-00014155 | B18: 41942 | C18: 06/02/2024-NO_DEFINIDO - Solicitud de Servico Creada desde AMSi, 06/02/2024-Biomedico1 - Se realiza reemplazo de batería se evidencia leve aberturas en una esquina se realiza ajuste se realizan pruebas equipo funciona correctamente | D18: Bateria | E18: =VLOOKUP(A18,Equipos!$1:$1048576,2,0) -> Termohigrometro Digital | F18: 14155 | G18: =VLOOKUP(A18,Equipos!$A$2:$H$16545,4,FALSE) -> N/A
A19: BAN-LARIN-00015725 | B19: 41942 | C19: 26/02/2024-NO_DEFINIDO - Solicitud de Servico Creada desde AMSi, 10/03/2024-Biomedico2 - Se realiza cambio de bombillo por desgaste, se entrega sin novedad | D19: Bombillo | E19: =VLOOKUP(A19,Equipos!$1:$1048576,2,0) -> Laringoscopio | F19: 15725 | G19: =VLOOKUP(A19,Equipos!$A$2:$H$16545,4,FALSE) -> N/A
A20: BDG-EQUIO-00018895 | B20: 41942 | C20: 29/02/2024-NO_DEFINIDO - Solicitud de Servico Creada desde AMSi, 29/02/2024-Biomedico1 - Se realiza instalación de baterías nuevas equipo funciona correctamente | D20: Bateria | E20: =VLOOKUP(A20,Equipos!$1:$1048576,2,0) -> Equipo De Organos Portatil | F20: 18895/18896 | G20: =VLOOKUP(A20,Equipos!$A$2:$H$16545,4,FALSE) -> N/A
A21: BDG-BASME-00006049 | B21: 41942 | C21: 02/05/2024-NO_DEFINIDO - Solicitud de Servico Creada desde AMSi, 24/05/2024-Biomedico2 - Se realiza verificación con masas patrón y no se evidencia desajuste, se recomienda el cambio de las baterías | D21: Bateria | E21: =VLOOKUP(A21,Equipos!$1:$1048576,2,0) -> Bascula Mecanica | F21: 6049 | G21: =VLOOKUP(A21,Equipos!$A$2:$H$16545,4,FALSE) -> N/A
A22: BDG-TENAT-00012864 | B22: 41942 | C22: 06/05/2024-NO_DEFINIDO - Solicitud de Servico Creada desde AMSi, 29/05/2024-Biomedico2 - Se realiza ajustte de brazalete y regulador de pera ,se entrega sin novedad | D22: Brazalete | E22: =VLOOKUP(A22,Equipos!$1:$1048576,2,0) -> Tensiometro De Atril | F22: 12864 | G22: =VLOOKUP(A22,Equipos!$A$2:$H$16545,4,FALSE) -> N/A
A23: BAN-LARIN-00014221 | B23: 41942 | C23: 08/05/2024-NO_DEFINIDO - Solicitud de Servico Creada desde AMSi, 28/05/2024-Biomedico2 - Se realiza cambio de bombillo y se entrega sin novedad | D23: Bombillo | E23: =VLOOKUP(A23,Equipos!$1:$1048576,2,0) -> Laringoscopio | F23: 14221 | G23: =VLOOKUP(A23,Equipos!$A$2:$H$16545,4,FALSE) -> N/A
A24: BDG-EQUIO-00001076 | B24: 41942 | C24: 19/06/2024-NO_DEFINIDO - Solicitud de Servico Creada desde AMSi, 26/06/2024-Biomedico1 - Se retira equipo del servicio ya que llegó el equipo de reposición eeste equipo se encontraba en proceso de renovación y ya contaba con acta de baja | D24: Baja | E24: =VLOOKUP(A24,Equipos!$1:$1048576,2,0) -> Equipo Organos De Los Sentidos | F24: 1076 | G24: =VLOOKUP(A24,Equipos!$A$2:$H$16545,4,FALSE) -> N/A
A25: BAN-LARIN-00013920 | B25: 41942 | C25: 18/07/2024-NO_DEFINIDO - Solicitud de Servico Creada desde AMSi, 22/07/2024-Biomedico1 - Se realiza cambio de baterías de mango de laringo se realizan pruebas de funcionamiento equipo funciona correctamente | D25: Bateria | E25: =VLOOKUP(A25,Equipos!$1:$1048576,2,0) -> Laringoscopio | F25: 13920 | G25: =VLOOKUP(A25,Equipos!$A$2:$H$16545,4,FALSE) -> N/A
A26: BDG-TENAT-00012867 | B26: 41942 | C26: 29/08/2024-NO_DEFINIDO - Solicitud de Servico Creada desde AMSi, 03/09/2024-Biomedico1 - Se realiza cambio de brazalete de tensiómetro el cual se encuentra con desgaste se realizan prubas de funcionamiento equipo funciona correctamente | D26: Brazalete | E26: =VLOOKUP(A26,Equipos!$1:$1048576,2,0) -> Tensiometro De Atril | F26: 12867 | G26: =VLOOKUP(A26,Equipos!$A$2:$H$16545,4,FALSE) -> N/A
A27: BAN-LARIN-00015724 | B27: 41942 | C27: 01/09/2024-NO_DEFINIDO - Solicitud de Servico Creada desde AMSi, 07/10/2024-Biomedico2 - Se realiza verificación de mango de laringo y no se encuentra novedad, se realiza verificación de hojas de laringo y se evidencia bombillo suelto ,se realiza ajuste y se entrega sin novedad | D27: Bombillo | E27: =VLOOKUP(A27,Equipos!$1:$1048576,2,0) -> Laringoscopio | F27: 15724 | G27: =VLOOKUP(A27,Equipos!$A$2:$H$16545,4,FALSE) -> N/A
A28: BDG-TENAT-00012865 | B28: 41942 | C28: 05/09/2024-NO_DEFINIDO - Solicitud de Servico Creada desde AMSi, 10/09/2024-Biomedico1 - Se realiza cambio de brazalete y pers ya que presentan fuga se instala uno nuevo equipo funciona correctamente | D28: Brazalete | E28: =VLOOKUP(A28,Equipos!$1:$1048576,2,0) -> Tensiometro De Atril | F28: 12865 | G28: =VLOOKUP(A28,Equipos!$A$2:$H$16545,4,FALSE) -> N/A
A29: BAN-LARIN-00014222 | B29: 41942 | C29: 08/11/2024-NO_DEFINIDO - Solicitud de Servico Creada desde AMSi, 08/11/2024-Biomedico1 - Se realiza cambio de bombillo de laringoscopio ya que se encontraba fundido se instala uno nuevo se realizan pruebas equipo funciona correctamente | D29: Bombillo | E29: =VLOOKUP(A29,Equipos!$1:$1048576,2,0) -> Laringoscopio | F29: 14222 | G29: =VLOOKUP(A29,Equipos!$A$2:$H$16545,4,FALSE) -> N/A
A30: BAN-LARIN-00014221 | B30: 41942 | C30: 08/11/2024-NO_DEFINIDO - Solicitud de Servico Creada desde AMSi, 08/11/2024-Biomedico1 - Se realiza limpieza y cambio de baterías | D30: Bateria | E30: =VLOOKUP(A30,Equipos!$1:$1048576,2,0) -> Laringoscopio | F30: 14221 | G30: =VLOOKUP(A30,Equipos!$A$2:$H$16545,4,FALSE) -> N/A
A31: OTP-CAMIL-00009652 | B31: 41942 | C31: 26/12/2024-NO_DEFINIDO - Solicitud de Servico Creada desde AMSi, 24/01/2025-Senior - Faltaban cinturones y ruedas cristalizada, se instala una pareja de cinturón y se cambia una rueda por back up, debido a que se encontraba cristalizada, se recomienda cambio de ruedas. | D31: Ruedas | E31: =VLOOKUP(A31,Equipos!$1:$1048576,2,0) -> Camilla De Transporte | F31: 9652 | G31: =VLOOKUP(A31,Equipos!$A$2:$H$16545,4,FALSE) -> N/A
A32: BAN-LARIN-00012366 | B32: 41942 | C32: 27/01/2025-NO_DEFINIDO - Solicitud de Servico Creada desde AMSi, 29/01/2025-Biomedico1 - Se realiza verificación de mango d larin se realiza cambio de bombillo se realizan prubas de funcionamiento equipo funcionando correctamente | D32: Bombillo | E32: =VLOOKUP(A32,Equipos!$1:$1048576,2,0) -> Laringoscopio | F32: 12366 | G32: =VLOOKUP(A32,Equipos!$A$2:$H$16545,4,FALSE) -> N/A
... A63: BDG-EQUIO-00013153 | B63: 41942 | C63: -NO_DEFINIDO - Se realiza cambio de bombillo de oftalmoscopio. Equipo funciona correctamente. | D63: Bombillo | E63: =VLOOKUP(A63,Equipos!$1:$1048576,2,0) -> Equipo Organos De Los Sentidos | F63: 13153 | G63: =VLOOKUP(A63,Equipos!$A$2:$H$16545,4,FALSE) -> N/A
A64: BDG-EQUIO-00005986 | B64: 41942 | C64: -NO_DEFINIDO - Se realiza verificación inicial se realizan mediciones de voltaje en los puntos de conexión con los cabezales en el punto de conexión del otoscopio se evidencia que el voltaje no es el adecuado y mínimo requerido para que funcione el bombillo, se realiza inspección del punto de conexión de oftalmoscopio se evidencia que este se encuentra en las mininas condiciones, no cumple con el voltaje mínimo requerido para el funcionamiento del bombillo, se realiza inspección de la fuente en donde se evidencia componentes con fallas electrónicas, se realiza un testeo de la tarjeta y s evidencia afectación en gran parte de la tarjeta en la etapa de filtrado y regulación de voltaje de a tarjeta. Se realiza respectiva cotización de componentes pero estos no son comerciales por tal motivo se sugiere dar de baja el equipo ya que no es posible realizar la reparación. | D64: Bombillo | E64: =VLOOKUP(A64,Equipos!$1:$1048576,2,0) -> Equipo Organos De Los Sentidos | F64: 5986/10127 | G64: =VLOOKUP(A64,Equipos!$A$2:$H$16545,4,FALSE) -> N/A
A65: BAN-LARIN-00013553 | B65: 41942 | C65: -NO_DEFINIDO - Se realiza limpieza del mango de laringoscopio el cual se encontraba con abundante sulfatación en el socket, adicionalmente se realiza cambio a hoja de laringoscopio #3. Equipo funciona correctamente. | D65: Hoja de laringoscopio | E65: =VLOOKUP(A65,Equipos!$1:$1048576,2,0) -> Laringoscopio | F65: 13553 | G65: =VLOOKUP(A65,Equipos!$A$2:$H$16545,4,FALSE) -> N/A
A66: BAN-LARIN-00012077 | B66: 41942 | C66: -NO_DEFINIDO - e realiza cambio de bombillo se realizan pruebas de funcionamiento el equipo funciona correctamente | D66: Bombillo | E66: =VLOOKUP(A66,Equipos!$1:$1048576,2,0) -> Laringoscopio | F66: 12077 | G66: =VLOOKUP(A66,Equipos!$A$2:$H$16545,4,FALSE) -> N/A
A67: BAN-LARIN-00012075 | B67: 41942 | C67: -NO_DEFINIDO - Se realiza ajuste de bombillo de laringo. equipo queda funcionando correctamente | D67: Bombillo | E67: =VLOOKUP(A67,Equipos!$1:$1048576,2,0) -> Laringoscopio | F67: 12075 | G67: =VLOOKUP(A67,Equipos!$A$2:$H$16545,4,FALSE) -> N/A
A68: BDG-TENAT-00012867 | B68: 41942 | C68: -NO_DEFINIDO - Se realiza entrega de tensiómetro al servicio de consulta externa en perfectas condiciones de funcionamiento con brazalete nuevo y pera nueva.&#x0D; &#x0D; se adjunta reporte de entrega | D68: Brazalete | E68: =VLOOKUP(A68,Equipos!$1:$1048576,2,0) -> Tensiometro De Atril | F68: 12867 | G68: =VLOOKUP(A68,Equipos!$A$2:$H$16545,4,FALSE) -> N/A
A69: BAN-LARIN-00001387 | B69: 41942 | C69: -NO_DEFINIDO - Se realiza mantenimiento preventivo según cronograma.&#x0D; Se realiza revision del mango, bombillo, portabombillo, hojas de laringoscopio, verificacion de carga de las baterias, se entrega el equipo al servicio en funcionamiento, para su respectiva limpieza y desinfeccion. | D69: Bombillo | E69: =VLOOKUP(A69,Equipos!$1:$1048576,2,0) -> Laringoscopio | F69: 1387 | G69: =VLOOKUP(A69,Equipos!$A$2:$H$16545,4,FALSE) -> N/A
A70: BAN-LARIN-00006707 | B70: 41942 | C70: -NO_DEFINIDO - se realiza mantenimiento preventivo según cronograma&#x0D; Se realiza revision del mango, bombillo, portabombillo, hojas de laringoscopio, verificacion de carga de las baterias, se entrega el equipo al servicio en funcionamiento, para su respectiva limpieza y desinfeccion. | D70: Bombillo | E70: =VLOOKUP(A70,Equipos!$1:$1048576,2,0) -> Laringoscopio | F70: 6707 | G70: =VLOOKUP(A70,Equipos!$A$2:$H$16545,4,FALSE) -> N/A
A71: BAN-LARIN-00014221 | B71: 41942 | C71: -NO_DEFINIDO - Se realiza revision del mango, bombillo, portabombillo, hojas de laringoscopio, verificacion de carga de las baterias, se entrega el equipo al servicio en funcionamiento, para su respectiva limpieza y desinfeccion. | D71: Bombillo | E71: =VLOOKUP(A71,Equipos!$1:$1048576,2,0) -> Laringoscopio | F71: 14221 | G71: =VLOOKUP(A71,Equipos!$A$2:$H$16545,4,FALSE) -> N/A
A72: BAN-LARIN-00014222 | B72: 41942 | C72: -NO_DEFINIDO - Se realiza revision del mango, bombillo, portabombillo, hojas de laringoscopio, verificacion de carga de las baterias, se entrega el equipo al servicio en funcionamiento, para su respectiva limpieza y desinfeccion. | D72: Bombillo | E72: =VLOOKUP(A72,Equipos!$1:$1048576,2,0) -> Laringoscopio | F72: 14222 | G72: =VLOOKUP(A72,Equipos!$A$2:$H$16545,4,FALSE) -> N/A
A73: BAN-LARIN-00013553 | B73: 41942 | C73: -NO_DEFINIDO - Se realiza Revisión del mango, bombillo, porta bombillo, hojas de laringoscopio, verificación de carga de las baterias, se evidencia que el equipo presenta desgaste en el eje Pasante de enganche de la hoja se evidencia que las hojas presentan desgaste esto ocasiona que el equipo no funcione correctamente por tal motivo se sugiere que se de baja el equipo ya que se encuentra desgastado | D73: Bombillo | E73: =VLOOKUP(A73,Equipos!$1:$1048576,2,0) -> Laringoscopio | F73: 13553 | G73: =VLOOKUP(A73,Equipos!$A$2:$H$16545,4,FALSE) -> N/A
A74: BAN-LARIN-00013554 | B74: 41942 | C74: -NO_DEFINIDO - Se realiza revision del mango, bombillo, portabombillo, hojas de laringoscopio, verificacion de carga de las baterias, se entrega el equipo al servicio en funcionamiento, para su respectiva limpieza y desinfeccion. | D74: Bombillo | E74: =VLOOKUP(A74,Equipos!$1:$1048576,2,0) -> Laringoscopio | F74: 13554 | G74: =VLOOKUP(A74,Equipos!$A$2:$H$16545,4,FALSE) -> N/A
A75: BAN-LARIN-00013555 | B75: 41942 | C75: -NO_DEFINIDO - Se realiza revision del mango, bombillo, portabombillo, hojas de laringoscopio, verificacion de carga de las baterias, se entrega el equipo al servicio en funcionamiento, para su respectiva limpieza y desinfeccion. | D75: Bombillo | E75: =VLOOKUP(A75,Equipos!$1:$1048576,2,0) -> Laringoscopio | F75: 13555 | G75: =VLOOKUP(A75,Equipos!$A$2:$H$16545,4,FALSE) -> N/A
A76: BAN-LARIN-00013556 | B76: 41942 | C76: -NO_DEFINIDO - Se realiza revision del mango, bombillo, portabombillo, hojas de laringoscopio, verificacion de carga de las baterias, se entrega el equipo al servicio en funcionamiento, para su respectiva limpieza y desinfeccion. | D76: Bombillo | E76: =VLOOKUP(A76,Equipos!$1:$1048576,2,0) -> Laringoscopio | F76: 13556 | G76: =VLOOKUP(A76,Equipos!$A$2:$H$16545,4,FALSE) -> N/A
A77: BAN-LARIN-00013557 | B77: 41942 | C77: -NO_DEFINIDO - Se realiza revision del mango, bombillo, portabombillo, hojas de laringoscopio, verificacion de carga de las baterias, se realiza cambio de soket ya que se encontraba desgastado, se entrega el equipo al servicio en funcionamiento, para su respectiva limpieza y desinfeccion. | D77: Bombillo | E77: =VLOOKUP(A77,Equipos!$1:$1048576,2,0) -> Laringoscopio | F77: 13557 | G77: =VLOOKUP(A77,Equipos!$A$2:$H$16545,4,FALSE) -> N/A
A78: BAN-LARIN-00012962 | B78: 41942 | C78: -NO_DEFINIDO - Se realiza revision del mango, bombillo, portabombillo, hojas de laringoscopio, verificacion de carga de las baterias, se entrega el equipo al servicio en funcionamiento, para su respectiva limpieza y desinfeccion. | D78: Bombillo | E78: =VLOOKUP(A78,Equipos!$1:$1048576,2,0) -> Laringoscopio | F78: 1349/12962 | G78: =VLOOKUP(A78,Equipos!$A$2:$H$16545,4,FALSE) -> N/A
A79: BAN-LARIN-00010005 | B79: 41942 | C79: -NO_DEFINIDO - Se realiza mantenimiento preventivo según cronograma revision del mango, bombillo, portabombillo, hojas de laringoscopio, verificacion de carga de las baterias. equipo operativo &#x0D; | D79: Bombillo | E79: =VLOOKUP(A79,Equipos!$1:$1048576,2,0) -> Laringoscopio | F79: 10005 | G79: =VLOOKUP(A79,Equipos!$A$2:$H$16545,4,FALSE) -> N/A
A80: BAN-LARIN-00015726 | B80: 41942 | C80: -NO_DEFINIDO - Se realiza Mantenimiento preventivo según cronograma, revision del mango, bombillo, portabombillo, hojas de laringoscopio, verificacion de carga de las baterias, se entrega el equipo al servicio en funcionamiento, para su respectiva limpieza y desinfeccion. | D80: Bombillo | E80: =VLOOKUP(A80,Equipos!$1:$1048576,2,0) -> Laringoscopio | F80: 15726 | G80: =VLOOKUP(A80,Equipos!$A$2:$H$16545,4,FALSE) -> N/A
A81: BAN-LARIN-00015264 | B81: 41942 | C81: -NO_DEFINIDO - Se realiza revision del mango, bombillo, portabombillo, hojas de laringoscopio, verificacion de carga de las baterias, se entrega el equipo al servicio en funcionamiento, para su respectiva limpieza y desinfeccion. | D81: Bombillo | E81: =VLOOKUP(A81,Equipos!$1:$1048576,2,0) -> Laringoscopio | F81: 15264 | G81: =VLOOKUP(A81,Equipos!$A$2:$H$16545,4,FALSE) -> N/A
A82: BAN-LARIN-00015728 | B82: 41942 | C82: -NO_DEFINIDO - se realiza mantenimiento preventivo según cronograma.&#x0D; Se realiza revision del mango, bombillo, portabombillo, hojas de laringoscopio, verificacion de carga de las baterias, se entrega el equipo al servicio en funcionamiento, para su respectiva limpieza y desinfeccion. | D82: Bombillo | E82: =VLOOKUP(A82,Equipos!$1:$1048576,2,0) -> Laringoscopio | F82: 15728/9841 | G82: =VLOOKUP(A82,Equipos!$A$2:$H$16545,4,FALSE) -> N/A
A83: BAN-LARIN-00015724 | B83: 41942 | C83: -NO_DEFINIDO - Se verifica y bombillo se encuentra fundido. Se realiza cambio de este y equipo queda funcionando correctamente. | D83: Bombillo | E83: =VLOOKUP(A83,Equipos!$1:$1048576,2,0) -> Laringoscopio | F83: 15724 | G83: =VLOOKUP(A83,Equipos!$A$2:$H$16545,4,FALSE) -> N/A
A84: BAN-LARIN-00012888 | B84: 41942 | C84: -NO_DEFINIDO - Se realiza mantenimiento preventivo según cronograma&#x0D; Se realiza revision del mango, bombillo, portabombillo, hojas de laringoscopio, verificacion de carga de las baterias, se entrega el equipo al servicio en funcionamiento, para su respectiva limpieza y desinfeccion. | D84: Bombillo | E84: =VLOOKUP(A84,Equipos!$1:$1048576,2,0) -> Laringoscopio | F84: 12888 | G84: =VLOOKUP(A84,Equipos!$A$2:$H$16545,4,FALSE) -> N/A
A85: BAN-LARIN-00013553 | B85: 41942 | C85: -NO_DEFINIDO - se realiza cambio de bombillo del laringoscopio entregándolo en optimo estado. | D85: Bombillo | E85: =VLOOKUP(A85,Equipos!$1:$1048576,2,0) -> Laringoscopio | F85: 13553 | G85: =VLOOKUP(A85,Equipos!$A$2:$H$16545,4,FALSE) -> N/A
A86: BDG-EQUIO-00015284 | B86: 41942 | C86: -NO_DEFINIDO - Se realiza cambio de bombillo a equipo de órganos equipo queda operativo | D86: Bombillo | E86: =VLOOKUP(A86,Equipos!$1:$1048576,2,0) -> Equipo Organos De Los Sentidos | F86: 15284 | G86: =VLOOKUP(A86,Equipos!$A$2:$H$16545,4,FALSE) -> N/A
A87: BAN-LARIN-00001349 | B87: 41942 | C87: -NO_DEFINIDO - Se realiza revisión del mango, bombillo, hojas de laringoscopio, verificación de carga de las baterías. | D87: Bombillo | E87: =VLOOKUP(A87,Equipos!$1:$1048576,2,0) -> Laringoscopio | F87: 1349 | G87: =VLOOKUP(A87,Equipos!$A$2:$H$16545,4,FALSE) -> N/A
A88: BAN-LARIN-00001387 | B88: 41942 | C88: -NO_DEFINIDO - Se realiza revisión del mango, bombillo, hojas de laringoscopio, verificación de carga de las baterías. | D88: Bombillo | E88: =VLOOKUP(A88,Equipos!$1:$1048576,2,0) -> Laringoscopio | F88: 1387 | G88: =VLOOKUP(A88,Equipos!$A$2:$H$16545,4,FALSE) -> N/A
A89: BFE-FOTOF-00015810 | B89: 41942 | C89: -NO_DEFINIDO - se evidencia equipo roto y sin el cargador&#x0D; se realiza revisión de equipo, encontrando daño en el brazo adicionalmente el adaptador no se encontró en el servicio equipo temporalmente fuera de servicio ya que la batería del equipo se agoto y no funciona adecuadamente. | D89: Cargador | E89: =VLOOKUP(A89,Equipos!$1:$1048576,2,0) -> Fotoforo | F89: 15810 | G89: =VLOOKUP(A89,Equipos!$A$2:$H$16545,4,FALSE) -> N/A
A90: BAN-LARIN-00006707 | B90: 41942 | C90: -NO_DEFINIDO - Se realiza revisión del mango, bombillo, hoja de laringo, verificación de carga de las baterías, se entrega el equipo al servicio en funcionamiento, para su respectiva limpieza y desinfección.&#x0D; &#x0D; Se adjunta reporte de servicio | D90: Bombillo | E90: =VLOOKUP(A90,Equipos!$1:$1048576,2,0) -> Laringoscopio | F90: 6707 | G90: =VLOOKUP(A90,Equipos!$A$2:$H$16545,4,FALSE) -> N/A
A91: BAN-LARIN-00014221 | B91: 41942 | C91: -NO_DEFINIDO - Se realiza revisión del mango, bombillo, hojas de laringoscopio, verificación de carga de las baterías. | D91: Bombillo | E91: =VLOOKUP(A91,Equipos!$1:$1048576,2,0) -> Laringoscopio | F91: 14221 | G91: =VLOOKUP(A91,Equipos!$A$2:$H$16545,4,FALSE) -> N/A
A92: BAN-LARIN-00014222 | B92: 41942 | C92: -NO_DEFINIDO - Se realiza revisión del mango, bombillo, hojas de laringoscopio, verificación de carga de las baterías. | D92: Bombillo | E92: =VLOOKUP(A92,Equipos!$1:$1048576,2,0) -> Laringoscopio | F92: 14222 | G92: =VLOOKUP(A92,Equipos!$A$2:$H$16545,4,FALSE) -> N/A
A93: BAN-LARIN-00000768 | B93: 41942 | C93: -NO_DEFINIDO - Se realiza revisión del mango, bombillo, hojas de laringoscopio, verificación de carga de las baterías. | D93: Bombillo | E93: =VLOOKUP(A93,Equipos!$1:$1048576,2,0) -> Laringoscopio | F93: 768 | G93: =VLOOKUP(A93,Equipos!$A$2:$H$16545,4,FALSE) -> N/A
A94: BAN-LARIN-00011656 | B94: 41942 | C94: -NO_DEFINIDO - Se realiza revisión del mango, bombillo, hojas de laringoscopio, verificación de carga de las baterías. | D94: Bombillo | E94: =VLOOKUP(A94,Equipos!$1:$1048576,2,0) -> Laringoscopio | F94: 11656 | G94: =VLOOKUP(A94,Equipos!$A$2:$H$16545,4,FALSE) -> N/A
... A112: BDG-BASME-00010028 | B112: 41942 | C112: -NO_DEFINIDO - Se realiza revisión general del equipo, verificación de funcionamiento se evidencia que las mediciones están fuer del rango permitido, se realiza despiece del equipo se evidencia celdas dobladas, se realiza ajuste se lubrican partes se ensambla se realizan pruebas nuevamente y se observa que la bascula no cumple con los estándares de funcionamiento por tal motivo se recomienda dar de baja. | D112: Baja | E112: =VLOOKUP(A112,Equipos!$1:$1048576,2,0) -> Bascula Mecanica | F112: 10028 | G112: =VLOOKUP(A112,Equipos!$A$2:$H$16545,4,FALSE) -> N/A
A113: BAN-LARIN-00012962 | B113: 41942 | C113: -NO_DEFINIDO - Se realiza revisión del mango, bombillo, hojas de laringoscopio, verificación de carga de las baterías. | D113: Bombillo | E113: =VLOOKUP(A113,Equipos!$1:$1048576,2,0) -> Laringoscopio | F113: 1349/12962 | G113: =VLOOKUP(A113,Equipos!$A$2:$H$16545,4,FALSE) -> N/A
A114: BAN-LARIN-00010005 | B114: 41942 | C114: -NO_DEFINIDO - Se realiza revisión del mango, bombillo, hoja de laringo, verificación de carga de las baterías, se entrega el equipo al servicio en funcionamiento, para su respectiva limpieza y desinfección.&#x0D; &#x0D; Se adjunta reporte de servicio | D114: Bombillo | E114: =VLOOKUP(A114,Equipos!$1:$1048576,2,0) -> Laringoscopio | F114: 10005 | G114: =VLOOKUP(A114,Equipos!$A$2:$H$16545,4,FALSE) -> N/A
A115: BAN-LARIN-00006779 | B115: 41942 | C115: -NO_DEFINIDO - &#x0D; Se realiza revisión del mango, bombillo, hojas de laringoscopio, verificación de carga de las baterías. | D115: Bombillo | E115: =VLOOKUP(A115,Equipos!$1:$1048576,2,0) -> Laringoscopio | F115: 6779 | G115: =VLOOKUP(A115,Equipos!$A$2:$H$16545,4,FALSE) -> N/A
A116: BAN-LARIN-00005347 | B116: 41942 | C116: -NO_DEFINIDO - Se realiza revisión del mango, bombillo, hojas de laringoscopio, verificación de carga de las baterías. | D116: Bombillo | E116: =VLOOKUP(A116,Equipos!$1:$1048576,2,0) -> Laringoscopio | F116: 5347 | G116: =VLOOKUP(A116,Equipos!$A$2:$H$16545,4,FALSE) -> N/A
A117: BAN-LARIN-00000778 | B117: 41942 | C117: -NO_DEFINIDO - Se realiza revisión del mango, bombillo, hojas de laringoscopio, verificación de carga de las baterías. | D117: Bombillo | E117: =VLOOKUP(A117,Equipos!$1:$1048576,2,0) -> Laringoscopio | F117: 778 | G117: =VLOOKUP(A117,Equipos!$A$2:$H$16545,4,FALSE) -> N/A
A118: BAN-LARIN-00015725 | B118: 41942 | C118: -NO_DEFINIDO - Se revisa equipo y se evidencia falla en el bombillo por lo cual se realiza cambio de este y se instala uno nuevo dejando equipo funcionando correctamente | D118: Bombillo | E118: =VLOOKUP(A118,Equipos!$1:$1048576,2,0) -> Laringoscopio | F118: 15725 | G118: =VLOOKUP(A118,Equipos!$A$2:$H$16545,4,FALSE) -> N/A
A119: BAN-LARIN-00013920 | B119: 41942 | C119: -NO_DEFINIDO - Se revisa equipo y se evidencia falla en el bombillo por lo cual se realiza cambio de este y se instala uno nuevo dejando equipo funcionando correctamente | D119: Bombillo | E119: =VLOOKUP(A119,Equipos!$1:$1048576,2,0) -> Laringoscopio | F119: 13920 | G119: =VLOOKUP(A119,Equipos!$A$2:$H$16545,4,FALSE) -> N/A
A120: BAN-LARIN-00012077 | B120: 41942 | C120: -NO_DEFINIDO - Se revisa y se evidencia que el bombillo esta fundido por lo que se realiza el cambio de este, se instala un bombillo nuevo, se hacen pruebas y equipo queda funcionado correctamente | D120: Bombillo | E120: =VLOOKUP(A120,Equipos!$1:$1048576,2,0) -> Laringoscopio | F120: 12077 | G120: =VLOOKUP(A120,Equipos!$A$2:$H$16545,4,FALSE) -> N/A
A121: BAN-LARIN-00012076 | B121: 41942 | C121: -NO_DEFINIDO - Se revisa y se evidencia que el bombillo esta fundido por lo que se realiza el cambio de este, se instala un bombillo nuevo, se hacen pruebas y equipo queda funcionado correctamente | D121: Bombillo | E121: =VLOOKUP(A121,Equipos!$1:$1048576,2,0) -> Laringoscopio | F121: 12076 | G121: =VLOOKUP(A121,Equipos!$A$2:$H$16545,4,FALSE) -> N/A
A122: BDG-TENAT-00012867 | B122: 41942 | C122: 14/06/2023-NO_DEFINIDO - Solicitud de Servico Creada desde AMSi, 15/06/2023-Biomedico2 - Se realiza verificaión de tensiometro y se evidencia pera con válvula desgastada,se realiza cambio de pera con válvula totalmente nueva | D122: Válvula | E122: =VLOOKUP(A122,Equipos!$1:$1048576,2,0) -> Tensiometro De Atril | F122: 12867 | G122: =VLOOKUP(A122,Equipos!$A$2:$H$16545,4,FALSE) -> N/A
A123: BDG-TERMO-00014954 | B123: 41942 | C123: -NO_DEFINIDO - Se revisa equipo evidenciando pantalla con múltiples fracturas por lo cual se sugiere dar de baja.&#x0D; &#x0D; Se adjunta reporte de servicio | D123: Baja | E123: =VLOOKUP(A123,Equipos!$1:$1048576,2,0) -> Termohigrometro Digital | F123: 14954 | G123: =VLOOKUP(A123,Equipos!$A$2:$H$16545,4,FALSE) -> N/A
A124: BAN-LARIN-00015724 | B124: 41942 | C124: -NO_DEFINIDO - Se realiza revisión del mango, bombillo, hojas de laringoscopio, verificación de carga de las baterías. | D124: Bombillo | E124: =VLOOKUP(A124,Equipos!$1:$1048576,2,0) -> Laringoscopio | F124: 15724 | G124: =VLOOKUP(A124,Equipos!$A$2:$H$16545,4,FALSE) -> N/A
A125: BAN-LARIN-00015725 | B125: 41942 | C125: -NO_DEFINIDO - Se realiza revisión del mango, bombillo, hojas de laringoscopio, verificación de carga de las baterías. | D125: Bombillo | E125: =VLOOKUP(A125,Equipos!$1:$1048576,2,0) -> Laringoscopio | F125: 15725 | G125: =VLOOKUP(A125,Equipos!$A$2:$H$16545,4,FALSE) -> N/A
... A127: BFE-FOTOF-00015810 | B127: 41942 | C127: -NO_DEFINIDO - Se realiza verificación de equipo en el servicio se observa que el equipo se encuentra roto, motivo por el cual se atiende llamado. Se informa a la jefe del servicio que el equipo va a ser retirado ya que no cumple con las condiciones adecuadas para el uso en el servicio. &#x0D; &#x0D; Equipo se trata de pegar, pero se fractura por el mismo punto a la hora de realizar pruebas funcionales. &#x0D; &#x0D; Se recomienda dar de baja el equipo ya que su estructura esta rota y en mal estado de funcionamiento&#x0D; Fecha de compra 12 Sept 2019- costo 856742 | D127: Baja | E127: =VLOOKUP(A127,Equipos!$1:$1048576,2,0) -> Fotoforo | F127: 15810 | G127: =VLOOKUP(A127,Equipos!$A$2:$H$16545,4,FALSE) -> N/A
A128: BAN-LARIN-00012962 | B128: 41942 | C128: -NO_DEFINIDO - Se realiza revisión de laringoscopio, se encuentra bombillo fundido. &#x0D; &#x0D; Se realiza cambio del bombillo y pruebas funcionales satisfactorias | D128: Bombillo | E128: =VLOOKUP(A128,Equipos!$1:$1048576,2,0) -> Laringoscopio | F128: 1349/12962 | G128: =VLOOKUP(A128,Equipos!$A$2:$H$16545,4,FALSE) -> N/A
A129: BFE-FOTOF-00000625 | B129: 41942 | C129: -NO_DEFINIDO - se realiza verificación de equipo, se observa que el equipo se encuentra bastante deteriorado, el servicio informa que el equipo se encontraba en un mueble bajo llave y que se encontraba fuera de servicio desde hace muchos años. se recomienda dar de baja el equipo ya que su estructura está rota y en mal estado de funcionamiento | D129: Baja | E129: =VLOOKUP(A129,Equipos!$1:$1048576,2,0) -> Fotoforo | F129: 625 | G129: =VLOOKUP(A129,Equipos!$A$2:$H$16545,4,FALSE) -> N/A
A130: BFE-FOTOF-00015060 | B130: 41942 | C130: -NO_DEFINIDO - Se realiza revisión del equipo, encontrando daño en el brazo del fotóforo lo cual ocasionó exposición de los cables y daño del equipo dejándolo fuera de servicio, se realiza cambio de carcaza para extender su vida útil. se entrega equipo al servicio en funcionamiento, se recomienda realizar el uso adecuado del equipo para garantizar su correcto funcionamiento, se adjunta registro fotográfico del daño encontrado. se entrega para su respectiva limpieza y desinfección. | D130: Carcasa | E130: =VLOOKUP(A130,Equipos!$1:$1048576,2,0) -> Fotoforo | F130: 15060 | G130: =VLOOKUP(A130,Equipos!$A$2:$H$16545,4,FALSE) -> N/A
A131: BFE-LAMAU-00000179 | B131: 41942 | C131: -NO_DEFINIDO - Se realiza revisión del equipo encontrando daño general en la carcaza, se encuentra cables expuestos e interruptor de encendido en corto circuito, por los daños presentados en la lampara, en estado de la carcaza y el corto circuito presentado en el interruptor, no es posible la reparación de la misma por tal motivo se recomienda dar de baja. | D131: Baja | E131: =VLOOKUP(A131,Equipos!$1:$1048576,2,0) -> Lampara Auxiliar De Procedimientos | F131: 179 | G131: =VLOOKUP(A131,Equipos!$A$2:$H$16545,4,FALSE) -> N/A
A132: BDG-TENPA-00006745 | B132: 41942 | C132: -NO_DEFINIDO - Se realiza cambio de brazalete de 2 vías por desgaste. Equipo queda funcionando correctamente. | D132: Brazalete | E132: =VLOOKUP(A132,Equipos!$1:$1048576,2,0) -> Tensiometro De Pared | F132: 6745 | G132: =VLOOKUP(A132,Equipos!$A$2:$H$16545,4,FALSE) -> N/A
A133: BAN-LARIN-00015264 | B133: 41942 | C133: -NO_DEFINIDO - Se realiza revisión del mango, bombillo, hojas de laringoscopio, verificación de carga de las baterías. | D133: Bombillo | E133: =VLOOKUP(A133,Equipos!$1:$1048576,2,0) -> Laringoscopio | F133: 15264 | G133: =VLOOKUP(A133,Equipos!$A$2:$H$16545,4,FALSE) -> N/A
A134: BDG-EQUIO-00005986 | B134: 41942 | C134: -NO_DEFINIDO - Se realiza cambio de bombillo a equipo de órganos ref: 3000 equipo queda funcionando | D134: Bombillo | E134: =VLOOKUP(A134,Equipos!$1:$1048576,2,0) -> Equipo Organos De Los Sentidos | F134: 5986/10127 | G134: =VLOOKUP(A134,Equipos!$A$2:$H$16545,4,FALSE) -> N/A
A135: BAN-LARIN-00012367 | B135: 41942 | C135: -NO_DEFINIDO - Se realiza por parte de Miguel Hernández de Novatécnica revisión de laringoscopio, equipo requiere cambio de bombillo, se realiza cambio por uno nuevo, se efectúan pruebas de funcionamiento. &#x0D; &#x0D; Equipo funcional. Recibe a satisfacción Jefe Alberto Almanza. | D135: Bombillo | E135: =VLOOKUP(A135,Equipos!$1:$1048576,2,0) -> Laringoscopio | F135: 12367 | G135: =VLOOKUP(A135,Equipos!$A$2:$H$16545,4,FALSE) -> N/A
A136: BDG-TENSI-00015257 | B136: 41942 | C136: -NO_DEFINIDO - Se realiza revisión general del equipo, estado físico de pera y brazalete, se realiza limpieza, se realizan pruebas de funcionamiento con simulador y se entrega al servicio para su respectiva desinfección. Equipo funciona correctamente.&#x0D; &#x0D; Se adjunta reporte de mantenimiento. | D136: Brazalete | E136: =VLOOKUP(A136,Equipos!$1:$1048576,2,0) -> Tensiometro Portatil | F136: 15257 | G136: =VLOOKUP(A136,Equipos!$A$2:$H$16545,4,FALSE) -> N/A
A137: BDG-EQUIO-00007377 | B137: 41942 | C137: -NO_DEFINIDO - Se realiza revisión general del equipo, estado físico de pera y brazalete, se realiza limpieza, se realizan pruebas de funcionamiento y se entrega al servicio para su respectiva desinfección. Equipo funciona correctamente.&#x0D; &#x0D; Se adjunta reporte de mantenimiento. | D137: Brazalete | E137: =VLOOKUP(A137,Equipos!$1:$1048576,2,0) -> Equipo De Organos Portatil | F137: 7377 | G137: =VLOOKUP(A137,Equipos!$A$2:$H$16545,4,FALSE) -> N/A
A138: BDG-EQUIO-00013803 | B138: 41942 | C138: -NO_DEFINIDO - Se realiza revisión general del equipo, estado físico de pera y brazalete, se realiza limpieza, se realizan pruebas de funcionamiento con simulador y se entrega al servicio para su respectiva desinfección. Equipo funciona correctamente.&#x0D; &#x0D; Se adjunta reporte de mantenimiento. | D138: Brazalete | E138: =VLOOKUP(A138,Equipos!$1:$1048576,2,0) -> Equipo Organos De Los Sentidos | F138: 13803 | G138: =VLOOKUP(A138,Equipos!$A$2:$H$16545,4,FALSE) -> N/A
A139: BDG-TENAT-00012861 | B139: 41942 | C139: -NO_DEFINIDO - Se realiza revisión general del equipo, pera, brazalete, se realiza limpieza, se realizan pruebas de funcionamiento y se entrega al servicio para su respectiva desinfección. Equipo funciona correctamente.&#x0D; &#x0D; Se adjunta reporte de mantenimiento. | D139: Brazalete | E139: =VLOOKUP(A139,Equipos!$1:$1048576,2,0) -> Tensiometro De Atril | F139: 12861 | G139: =VLOOKUP(A139,Equipos!$A$2:$H$16545,4,FALSE) -> N/A
A140: BAN-LARIN-00013920 | B140: 41942 | C140: -NO_DEFINIDO - Se realiza revisión del equipo, se evidencian baterías desgastadas.&#x0D; Se realiza cambio de las mismas y pruebas de funcionamiento satisfactorias &#x0D; Equipo operativo en el servicio | D140: Bateria | E140: =VLOOKUP(A140,Equipos!$1:$1048576,2,0) -> Laringoscopio | F140: 13920 | G140: =VLOOKUP(A140,Equipos!$A$2:$H$16545,4,FALSE) -> N/A
A141: BAN-LARIN-00014221 | B141: 41942 | C141: -NO_DEFINIDO - Se realiza revisión general del equipo, se evidencia bombillo fundido. &#x0D; Se realiza cambio del mismo y pruebas de funcionamiento satisfactorias&#x0D; Equipo operativo en el servicio | D141: Bombillo | E141: =VLOOKUP(A141,Equipos!$1:$1048576,2,0) -> Laringoscopio | F141: 14221 | G141: =VLOOKUP(A141,Equipos!$A$2:$H$16545,4,FALSE) -> N/A
A142: BMO-TERDI-00018470 | B142: 41942 | C142: -NO_DEFINIDO - Se realiza verificación del equipo, evidenciando que el display no enciende se realiza pruebas de funcionamiento el equipo no da respuesta satisfactoria. se realiza proceso de verificación interna evidenciando componentes sueltos en su interior y presenta múltiples fracturas en su estructura, estas partes no son reparables por tal motivo se recomienda dar de baja | D142: Baja | E142: =VLOOKUP(A142,Equipos!$1:$1048576,2,0) -> Termometro Digital | F142: 18470 | G142: =VLOOKUP(A142,Equipos!$A$2:$H$16545,4,FALSE) -> N/A
A143: BDG-EQUIO-00013153 | B143: 41942 | C143: -NO_DEFINIDO - Se realiza instalación de aros de seguridad a equipo de órganos . &#x0D; Pruebas de funcionamiento satisfactorias | D143: Cable AC | E143: =VLOOKUP(A143,Equipos!$1:$1048576,2,0) -> Equipo Organos De Los Sentidos | F143: 13153 | G143: =VLOOKUP(A143,Equipos!$A$2:$H$16545,4,FALSE) -> N/A
A144: BMO-TERDI-00018924 | B144: 41942 | C144: -NO_DEFINIDO - Se envía termómetro con CC 262949 a calibración el cual el proveedor indica que el equipo no cumple con los parámetros establecidos para su calibración, se realizan múltiples pruebas y el quipo no presenta mejoría; por tanto no pasa la calibración.&#x0D; Por lo descrito anteriormente se recomienda dar de baja el equipo. &#x0D; | D144: Baja | E144: =VLOOKUP(A144,Equipos!$1:$1048576,2,0) -> Termometro Digital | F144: 18924 | G144: =VLOOKUP(A144,Equipos!$A$2:$H$16545,4,FALSE) -> N/A
A145: BDG-TENPA-00006749 | B145: 41942 | C145: -NO_DEFINIDO - Se realiza revisión general de equipo, se evidencia manguera de conexión de brazalete suelto.&#x0D; Se realiza ajuste de manguera y realizan pruebas de funcionamiento satisfactorias. Equipo queda operativo | D145: Brazalete | E145: =VLOOKUP(A145,Equipos!$1:$1048576,2,0) -> Tensiometro De Pared | F145: 6749 | G145: =VLOOKUP(A145,Equipos!$A$2:$H$16545,4,FALSE) -> N/A
A146: BAN-LARIN-00012078 | B146: 41942 | C146: -NO_DEFINIDO - Se realiza revisión general del mango de laringoscopio, se evidencia bombillo fundido.&#x0D; Se realiza cambio de bombillo y pruebas de funcionamiento satisfactorias. &#x0D; Equipo operativo en el servicio | D146: Bombillo | E146: =VLOOKUP(A146,Equipos!$1:$1048576,2,0) -> Laringoscopio | F146: 12078 | G146: =VLOOKUP(A146,Equipos!$A$2:$H$16545,4,FALSE) -> N/A
... A150: BAN-LARIN-00012075 | B150: 41942 | C150: -NO_DEFINIDO - Se realiza revisión general del equipo, se evidencia bombillo fundido, se realiza cambio del mismo y pruebas de funcionamiento satisfactorias. &#x0D; Equipo operativo en el servicio | D150: Bombillo | E150: =VLOOKUP(A150,Equipos!$1:$1048576,2,0) -> Laringoscopio | F150: 12075 | G150: =VLOOKUP(A150,Equipos!$A$2:$H$16545,4,FALSE) -> N/A
A151: BAN-LARIN-00012962 | B151: 41942 | C151: -NO_DEFINIDO - Se realiza revisión general del equipo, se evidencia que la tapa del deposito de baterías no realiza el cierre adecuado ya que se encuentra desgastada la rosca que cumple esta función debido a esto el equipo no es funcional en el estado que se encuentra, se recomienda dar de baja | D151: Bateria | E151: =VLOOKUP(A151,Equipos!$1:$1048576,2,0) -> Laringoscopio | F151: 1349/12962 | G151: =VLOOKUP(A151,Equipos!$A$2:$H$16545,4,FALSE) -> N/A
...

Sheet Equipos
A1: Código AC | B1: Descripción | C1: Activo Fijo | D1: Serial | E1: Centro de Costo | F1: Marca | G1: Modelo | H1: Estado | I1: DIAS NO DISPO | K1: UBICACIÓN | L1: EQUIPO | M1: MARCA | N1: MODELO | O1: SERIE | P1: ACTIVO FIJO | Q1: FECHA DE ADQUISICION | R1: COSTO DE ADQUISICION | S1: EVALUACION ECONOMICA | V1: REMPLAZO | W1: TIEMPO DE FALLA
A2: BMO-MOSIV-00010553 | B2: Monitor De Signos Vitales | C2: 10553 | D2: CC22121790 | E2: Ginecologia | F2: Mindray | G2: Mec 1200 | H2: A - En Operación | I2: =VLOOKUP(C1,Datos!$F:$G,6,0) -> #REF! | S2: costo de mnto correctivo | T2: Costo Anual de mnto | U2: Subtotal de evaluación económica
A3: BMO-MOSIV-00000297 | B3: Monitor De Signos Vitales | C3: 297 | D3: AAW08310023SA | E3: QX Medicina General | F3: General Electric | G3: Procare 300 | H3: I - Dado de baja | I3: =VLOOKUP(C2,Datos!$F:$G,6,0) -> #REF! | K3: BANCO DE SANGRE | L3: AGITADOR DE PLAQUETAS | M3: HELMER | N3: PF15I | O3: 1017681 | P3: 13550 | Q3: 42195 | R3: 6237320 | S3: 458600 | T3: 870000 | U3: 4 | V3: No requiere renovación | W3: =VLOOKUP(P3,Datos!$F:$G,6,0) -> #REF!
A4: BMO-MOSIV-00009874 | B4: Monitor De Signos Vitales | C4: 9874 | D4: EX24001257 | E4: Urgencias Adulto | F4: Mindray | G4: Imec10 | H4: A - En Operación | I4: =VLOOKUP(C3,Datos!$F:$G,6,0) -> #REF! | K4: UNIDAD QUIRURGICA | L4: ARCO EN C | M4: SIEMENS | N4: SIREMOBIL | O4: 31192 | P4: 10109 | Q4: 41438 | R4: 325000000 | S4: 0 | T4: 16143000 | U4: 5 | V4: Evaluar tecnología en un año | W4: =VLOOKUP(P4,Datos!$F:$G,6,0) -> #REF!
A5: BEF-NEVER-00002694 | B5: Nevera | C5: 2694 | D5: 8012300602 | E5: Hospitalización | F5: Challenger | G5: Cr233 | H5: I - Dado de Baja | I5: =VLOOKUP(C4,Datos!$F:$G,6,0) -> #REF! | K5: UNIDAD QUIRURGICA | L5: ARCO EN C | M5: SIEMENS | N5: SIREMOBIL COMPACT L | O5: 9857-4429 | P5: 265 | Q5: 39560 | R5: 165297251 | S5: 2050000 | T5: 15838000 | U5: 4 | V5: Reemplazo inmmediato | W5: =VLOOKUP(P5,Datos!$F:$G,6,0) -> #REF!
A6: BMO-MONFE-00007841 | B6: Monitor Fetal | C6: 7841 | D6: SAS10024555PA | E6: Ginecologia | F6: General Electric | G6: Corometrics 170 | H6: A - En Operación | I6: =VLOOKUP(C5,Datos!$F:$G,6,0) -> #REF! | K6: UNIDAD QUIRURGICA | L6: ARCO EN C | M6: SIEMENS | N6: CIOS SELECT | O6: 12793 | P6: 16700 | Q6: 44146 | R6: 213006671 | S6: 0 | T6: 19250000 | U6: 4 | V6: No requiere renovación | W6: =VLOOKUP(P6,Datos!$F:$G,6,0) -> #REF!
A7: BLP-FUENL-00010233 | B7: Fuente de Luz (Torre Wolf) | C7: 10233 | D7: 1100151942 | E7: Salas De Cirugia | F7: Richard Wolf | G7: 5132002 | H7: A - En Operación | I7: =VLOOKUP(C6,Datos!$F:$G,6,0) -> #REF! | K7: CONSULTA EXTERNA | L7: AUDIOMETRO | M7: MAICO | N7: MA42 | O7: 23322 | P7: 13008 | Q7: 39855 | R7: 15000000 | S7: 0 | T7: 946050 | U7: 5 | V7: Funcionamiento aprox 1 año | W7: =VLOOKUP(P7,Datos!$F:$G,6,0) -> #REF!
A8: BMP-MESAC-00015729 | B8: Mesa De Procedimientos Quirurgicos | C8: 15729 | D8: G9-94007284 | E8: Salas De Cirugia | F8: Mindray | G8: Hybase 6100 | H8: A - En Operación | I8: =VLOOKUP(C7,Datos!$F:$G,6,0) -> #REF! | K8: TERAPIA FISICA | L8: BANDA TROTADORA | M8: SPORTFITNESS | N8: NIMES | O8: B170520029 | P8: 15249 | Q8: 43181 | R8: 6637750 | S8: 110000 | T8: 600000 | U8: 4 | V8: No requiere renovación | W8: =VLOOKUP(P8,Datos!$F:$G,6,0) -> #REF!
A9: BMO-MONFE-00007841 | B9: Monitor Fetal | C9: 7841 | D9: SAS10024555PA | E9: Ginecologia | F9: General Electric | G9: Corometrics 170 | H9: A - En Operación | I9: =VLOOKUP(C8,Datos!$F:$G,6,0) -> #REF! | K9: TERAPIA FISICA | L9: BANDA TROTADORA | M9: SPORTFITNESS | N9: NIMES | O9: B170820030 | P9: 15250 | Q9: 43181 | R9: 6637750 | S9: 0 | T9: 600000 | U9: 5 | V9: No requiere renovación | W9: =VLOOKUP(P9,Datos!$F:$G,6,0) -> #REF!
A10: BDG-MOSIV-00117728 | B10: Monitor De Signos Vitales | C10: Alquiler | D10: 117728 | E10: Biomedica | F10: Nihon kohden | G10: PVM-2701 | H10: A - En Operación | I10: =VLOOKUP(C9,Datos!$F:$G,6,0) -> #REF! | K10: UNIDAD QUIRURGICA | L10: BAÑO SEROLOGICO | M10: MEMMERT | N10: WNE 10 | O10: 13080690 | P10: 7526 | Q10: 40305 | R10: 3405099 | S10: 0 | T10: 600000 | U10: 4 | V10: Evaluar tecnología en un año | W10: =VLOOKUP(P10,Datos!$F:$G,6,0) -> #REF!
A11: BDG-MOSIV-00117728 | B11: Monitor De Signos Vitales | C11: Alquiler | D11: 117728 | E11: Biomedica | F11: Nihon kohden | G11: PVM-2701 | H11: A - En Operación | I11: =VLOOKUP(C10,Datos!$F:$G,6,0) -> #REF! | K11: BIOMEDICA | L11: BAÑO SEROLOGICO | M11: MEMMERT | N11: W270 | O11: 800890 | P11: 5644 | Q11: 38930 | R11: 1000000 | S11: 0 | T11: 600000 | U11: 2 | V11: Funcionamiento aprox 1 año | W11: =VLOOKUP(P11,Datos!$F:$G,6,0) -> #REF!
A12: BDG-MOSIV-00117728 | B12: Monitor De Signos Vitales | C12: Alquiler | D12: 117728 | E12: Biomedica | F12: Nihon kohden | G12: PVM-2701 | H12: A - En Operación | I12: =VLOOKUP(C11,Datos!$F:$G,6,0) -> #REF! | K12: HOSPITALIZACION | L12: BASCULA DIGITAL | M12: KENWELL | N12: EB9003 | O12: 5348 | P12: 15753 | Q12: 43676 | R12: 275842 | S12: 0 | T12: 600000 | U12: FALSE | V12: No requiere renovación | W12: =VLOOKUP(P12,Datos!$F:$G,6,0) -> #REF!
A13: BID-ARCON-00000265 | B13: Arco en C | C13: 265 | D13: 4429 | E13: Salas De Cirugia | F13: Siemens | G13: Multimobil Compact 1 | H13: A - En Operación | I13: =VLOOKUP(C12,Datos!$F:$G,6,0) -> #REF! | K13: BANCO DE SANGRE | L13: BASCULA DIGITAL | M13: AND | N13: SK100 | O13: h6081039 | P13: 5621 | Q13: 38930 | R13: 500000 | S13: 0 | T13: 600000 | U13: FALSE | V13: Funcionamiento aprox 1 año | W13: =VLOOKUP(P13,Datos!$F:$G,6,0) -> #REF!
A14: BDG-BASTA-00007156 | B14: Bascula Con Tallimetro | C14: 19426 | D14: N/A | E14: Consulta Externa | F14: Health O Meter | G14: 220 KG | H14: A - En Operación | I14: =VLOOKUP(C13,Datos!$F:$G,6,0) -> #REF! | K14: BANCO DE SANGRE | L14: BASCULA DIGITAL | M14: AND | N14: SK100 | O14: H6081051 | P14: 5620 | Q14: 38930 | R14: 500000 | S14: 0 | T14: 600000 | U14: FALSE | V14: Funcionamiento aprox 1 año | W14: =VLOOKUP(P14,Datos!$F:$G,6,0) -> #REF!
A15: BMO-MONFE-00007841 | B15: Monitor Fetal | C15: 7841 | D15: SAS10024555PA | E15: Ginecologia | F15: General Electric | G15: Corometrics 170 | H15: A - En Operación | I15: =VLOOKUP(C14,Datos!$F:$G,6,0) -> #REF! | K15: CENTRO MEDICO | L15: BASCULA DIGITAL | M15: SECA | N15: 874DR | O15: 10000000293657 | P15: 16863 | Q15: 44293 | R15: 1925518 | S15: 0 | T15: 600000 | U15: 4 | V15: No requiere renovación | W15: =VLOOKUP(P15,Datos!$F:$G,6,0) -> #REF!
A16: BEF-NEVER-00006630 | B16: Nevera | C16: 6630 | D16: 080123-00602 | E16: Urgencias Adulto | F16: Challenger | G16: Arezzo | H16: I - Dado de baja | I16: =VLOOKUP(C15,Datos!$F:$G,6,0) -> #REF! | K16: NUTRICIÓN | L16: BASCULA DIGITAL | M16: SECA | N16: 874DR | O16: 10000000371735 | P16: 17795 | Q16: 44533 | R16: 1925518 | S16: 0 | T16: 400000 | U16: 4 | V16: No requiere renovación | W16: =VLOOKUP(P16,Datos!$F:$G,6,0) -> #REF!
A17: BMO-MOSIV-00009874 | B17: Monitor De Signos Vitales | C17: 9874 | D17: EX24001257 | E17: Urgencias Adulto | F17: Mindray | G17: Imec10 | H17: A - En Operación | I17: =VLOOKUP(C16,Datos!$F:$G,6,0) -> #REF! | K17: CONSULTA EXTERNA | L17: BASCULA DIGITAL | M17: SECA | N17: 813 | O17: 8813038202248 | P17: 16809 | Q17: 44237 | R17: 842520 | S17: 0 | T17: 600000 | U17: 2 | V17: No requiere renovación | W17: =VLOOKUP(P17,Datos!$F:$G,6,0) -> #REF!
A18: BMO-MOSIV-00015789 | B18: Monitor De Signos Vitales | C18: 15789 | D18: KN-94041489 | E18: Salas De Cirugia | F18: Mindray | G18: uMEC 10 | H18: A - En Operación | I18: =VLOOKUP(C17,Datos!$F:$G,6,0) -> #REF! | K18: URGENCIAS | L18: BASCULA DIGITAL | M18: HEALTH O METER | N18: 880KL | O18: 88042210000017 | P18: 18237 | Q18: 44813 | R18: 492443 | S18: 0 | T18: 600000 | U18: FALSE | V18: Evaluar tecnología en un año | W18: =VLOOKUP(P18,Datos!$F:$G,6,0) -> #REF!
A19: BMO-MOSIV-00010013 | B19: Monitor De Signos Vitales | C19: 10013 | D19: CC28123455 | E19: Ginecologia | F19: Mindray | G19: Mec1200 | H19: A - En Operación | I19: =VLOOKUP(C18,Datos!$F:$G,6,0) -> #REF! | K19: CONSULTA EXTERNA | L19: BASCULA DIGITAL | M19: SECA | N19: 813 | O19: 8813038201992 | P19: 16830 | Q19: 44235 | R19: 842520 | S19: 0 | T19: 600000 | U19: 2 | V19: No requiere renovación | W19: =VLOOKUP(P19,Datos!$F:$G,6,0) -> #REF!
A20: BMO-MOSIV-00008129 | B20: Monitor De Signos Vitales | C20: 8129 | D20: AA11134646 | E20: Hospitalización | F20: Mindray | G20: Pm8000 | H20: A - En Operación | I20: =VLOOKUP(C19,Datos!$F:$G,6,0) -> #REF! | K20: CUARTO DE RESIDUOS | L20: BASCULA ELECTRONICA INDUSTRIAL | M20: BBG | N20: R5232 | O20: 12E161231004 | P20: 14348 | Q20: 42795 | R20: 1500000 | S20: 0 | T20: 600000 | U20: 3 | V20: No requiere renovación | W20: =VLOOKUP(P20,Datos!$F:$G,6,0) -> #REF!
A21: BMO-MOSIV-00008129 | B21: Monitor De Signos Vitales | C21: 8129 | D21: AA11134646 | E21: Hospitalización | F21: Mindray | G21: Pm8000 | H21: A - En Operación | I21: =VLOOKUP(C20,Datos!$F:$G,6,0) -> #REF! | K21: CUARTO DE RESIDUOS | L21: BASCULA ELECTRONICA INDUSTRIAL | M21: BBG | N21: INDUSTRY20 | O21: 12E181227104 | P21: 16105 | Q21: 44063 | R21: 1500000 | S21: 0 | T21: 600000 | U21: 3 | V21: No requiere renovación | W21: =VLOOKUP(P21,Datos!$F:$G,6,0) -> #REF!
A22: BMO-MOSIV-00000294 | B22: Monitor De Signos Vitales | C22: 294 | D22: AAW07240072SA | E22: Biomedica | F22: General Electric | G22: Procare 300 | H22: I - Dado de baja | I22: =VLOOKUP(C21,Datos!$F:$G,6,0) -> #REF! | K22: URGENCIAS ADULTOS | L22: BASCULA MECANICA | M22: NEWMED | N22: DT05 | O22: BANM2015749 | P22: 14293 | Q22: 42769 | R22: 174000 | S22: 0 | T22: 600000 | U22: FALSE | V22: No requiere renovación | W22: =VLOOKUP(P22,Datos!$F:$G,6,0) -> #REF!
A23: BMO-MOSIV-00014803 | B23: Monitor De Signos Vitales | C23: 14803 | D23: KN73006796 | E23: Ginecologia | F23: Mindray | G23: Umec 10 | H23: A - En Operación | I23: =VLOOKUP(C22,Datos!$F:$G,6,0) -> #REF! | K23: URGENCIAS PEDIATRIA | L23: BASCULA CON TALLIMETRO | M23: DETECTO | N23: 200KG | O23: SIN | P23: 7507 | Q23: 39778 | R23: 794600 | S23: 0 | T23: 600000 | U23: 2 | V23: Funcionamiento aprox 1 año | W23: =VLOOKUP(P23,Datos!$F:$G,6,0) -> #REF!
A24: B | B24: #N/A | C24: #N/A | D24: #N/A | E24: #N/A | F24: #N/A | G24: #N/A | H24: #N/A | I24: =VLOOKUP(C23,Datos!$F:$G,6,0) -> #REF! | K24: URGENCIAS PEDIATRIA | L24: BASCULA CON TALLIMETRO | M24: HEALTH O METER | N24: 200KG | O24: SIN | P24: 9742/17108 | Q24: 40304 | R24: 174000 | S24: 0 | T24: 600000 | U24: FALSE | V24: Funcionamiento aprox 1 año | W24: =VLOOKUP(P24,Datos!$F:$G,6,0) -> #REF!
A25: BMO-MOSIV-00013491 | B25: Monitor De Signos Vitales | C25: 13491 | D25: CC53131303 | E25: Salas De Cirugia | F25: Mindray | G25: Mec 1200 | H25: A - En Operación | I25: =VLOOKUP(C24,Datos!$F:$G,6,0) -> #N/A | K25: URGENCIAS ADULTOS | L25: BASCULA CON TALLIMETRO | M25: DETECTO | N25: 200KG | O25: 173140090076 | P25: 14292 | Q25: 42769 | R25: 457272 | S25: 0 | T25: 600000 | U25: FALSE | V25: No requiere renovación | W25: =VLOOKUP(P25,Datos!$F:$G,6,0) -> #REF!
A26: BMO-MOSIV-00010013 | B26: Monitor De Signos Vitales | C26: 10013 | D26: CC28123455 | E26: Ginecologia | F26: Mindray | G26: Mec1200 | H26: A - En Operación | I26: =VLOOKUP(C25,Datos!$F:$G,6,0) -> #REF! | K26: CONSULTA EXTERNA | L26: BASCULA CON TALLIMETRO | M26: DETECTO | N26: 220KG | O26: SIN | P26: 13704 | Q26: 42319 | R26: 457272 | S26: 0 | T26: 600000 | U26: FALSE | V26: Evaluar tecnología en un año | W26: =VLOOKUP(P26,Datos!$F:$G,6,0) -> #REF!
A27: BMO-MONFE-00007841 | B27: Monitor Fetal | C27: 7841 | D27: SAS10024555PA | E27: Ginecologia | F27: General Electric | G27: Corometrics 170 | H27: A - En Operación | I27: =VLOOKUP(C26,Datos!$F:$G,6,0) -> #REF! | K27: CONSULTA EXTERNA | L27: BASCULA CON TALLIMETRO | M27: SECA | N27: 220KG | O27: SIN | P27: 13245 | Q27: 42122 | R27: 1469720 | S27: 0 | T27: 600000 | U27: 3 | V27: Evaluar tecnología en un año | W27: =VLOOKUP(P27,Datos!$F:$G,6,0) -> #REF!
A28: B | B28: #N/A | C28: #N/A | D28: #N/A | E28: #N/A | F28: #N/A | G28: #N/A | H28: #N/A | I28: =VLOOKUP(C27,Datos!$F:$G,6,0) -> #REF! | K28: CONSULTA EXTERNA | L28: BASCULA CON TALLIMETRO | M28: WELCH ALLYN | N28: 402KL | O28: 402WA03066 | P28: 12878 | Q28: 41982 | R28: 533600 | S28: 0 | T28: 600000 | U28: FALSE | V28: Evaluar tecnología en un año | W28: =VLOOKUP(P28,Datos!$F:$G,6,0) -> #REF!
A29: BMO-MOSIV-00015588 | B29: Monitor De Signos Vitales | C29: 15588 | D29: 6009532669 | E29: Salas De Cirugia | F29: Drager | G29: Infinity Del | H29: A - En Operación | I29: =VLOOKUP(C28,Datos!$F:$G,6,0) -> #N/A | K29: HOSPITALIZACION | L29: BASCULA CON TALLIMETRO | M29: DETECTO | N29: 125KG | O29: SIN | P29: 8079 | Q29: 38930 | R29: 500000 | S29: 0 | T29: 600000 | U29: FALSE | V29: Funcionamiento aprox 1 año | W29: =VLOOKUP(P29,Datos!$F:$G,6,0) -> #REF!
A30: BMO-MOSIV-00015467 | B30: Monitor De Signos Vitales | C30: 15467 | D30: 6009570075 | E30: Salas De Cirugia | F30: Drager | G30: Infinity Del | H30: A - En Operación | I30: =VLOOKUP(C29,Datos!$F:$G,6,0) -> #REF! | K30: CONSULTA EXTERNA | L30: BASCULA CON TALLIMETRO | M30: HEALTH O METER | N30: 220KG | O30: SIN | P30: 7156 | Q30: 38930 | R30: 600000 | S30: 0 | T30: 600000 | U30: 1 | V30: Funcionamiento aprox 1 año | W30: =VLOOKUP(P30,Datos!$F:$G,6,0) -> #REF!
A31: BCC-ELCBI-00015082 | B31: Electrobisturi | C31: 15082 | D31: S7F26607AX | E31: Salas De Cirugia | F31: Valleylab | G31: Force Fx-C | H31: A - En Operación | I31: =VLOOKUP(C30,Datos!$F:$G,6,0) -> #REF! | K31: CONSULTA EXTERNA | L31: BASCULA CON TALLIMETRO | M31: HEALTH O METER | N31: 1160 KG | O31: SIN | P31: 6143 | Q31: 39780 | R31: 794600 | S31: 0 | T31: 600000 | U31: 2 | V31: Evaluar tecnología en un año | W31: =VLOOKUP(P31,Datos!$F:$G,6,0) -> #REF!
A32: BMO-MOSIV-00005329 | B32: Monitor De Signos Vitales | C32: 5329 | D32: CE8B110447 | E32: Salas De Cirugia | F32: Mindray | G32: Pm7000 | H32: I - Dado de baja | I32: =VLOOKUP(C31,Datos!$F:$G,6,0) -> #REF! | K32: CONSULTA EXTERNA | L32: BASCULA CON TALLIMETRO | M32: DETECTO | N32: SIN | O32: SIN | P32: 5941 | Q32: 38930 | R32: 500000 | S32: 0 | T32: 600000 | U32: FALSE | V32: Funcionamiento aprox 1 año | W32: =VLOOKUP(P32,Datos!$F:$G,6,0) -> #REF!
A33: BMO-MOSIV-00010048 | B33: Monitor De Signos Vitales | C33: 10048 | D33: EX-31004634 | E33: Salas De Cirugia | F33: Mindray | G33: Imec10 | H33: I - Dado de baja | I33: =VLOOKUP(C32,Datos!$F:$G,6,0) -> #REF! | K33: CONSULTA EXTERNA | L33: BASCULA CON TALLIMETRO | M33: DETECTO | N33: 220KG | O33: 1731410090316 | P33: 14289 | Q33: 42769 | R33: 547000 | S33: 0 | T33: 600000 | U33: FALSE | V33: No requiere renovación | W33: =VLOOKUP(P33,Datos!$F:$G,6,0) -> #REF!
A34: BMO-MOSIV-00010013 | B34: Monitor De Signos Vitales | C34: 10013 | D34: CC28123455 | E34: Ginecologia | F34: Mindray | G34: Mec1200 | H34: A - En Operación | I34: =VLOOKUP(C33,Datos!$F:$G,6,0) -> #REF! | K34: CONSULTA EXTERNA | L34: BASCULA CON TALLIMETRO | M34: DETECTO | N34: 220KG | O34: 1731410090313 | P34: 14290 | Q34: 42769 | R34: 547000 | S34: 0 | T34: 600000 | U34: FALSE | V34: No requiere renovación | W34: =VLOOKUP(P34,Datos!$F:$G,6,0) -> #REF!
A35: B | B35: #N/A | C35: #N/A | D35: #N/A | E35: #N/A | F35: #N/A | G35: #N/A | H35: #N/A | I35: =VLOOKUP(C34,Datos!$F:$G,6,0) -> #REF! | K35: CONSULTA EXTERNA | L35: BASCULA CON TALLIMETRO | M35: HEALTH O METER | N35: 450kL | O35: 4500015992 | P35: 15752 | Q35: 43676 | R35: 1206284 | S35: 0 | T35: 600000 | U35: 3 | V35: No requiere renovación | W35: =VLOOKUP(P35,Datos!$F:$G,6,0) -> #REF!
A36: BMO-MOSIV-00000285 | B36: Monitor De Signos Vitales | C36: 285 | D36: AA93114424 | E36: Salas De Cirugia | F36: Mindray | G36: Pm8000 | H36: A - En Operación | I36: =VLOOKUP(C35,Datos!$F:$G,6,0) -> #N/A | K36: CENTRO MEDICO | L36: BASCULA CON TALLIMETRO | M36: BBG | N36: PP-150 | O36: 20015040300 | P36: 15302 | Q36: 43266 | R36: 875840 | S36: 0 | T36: 600000 | U36: 2 | V36: No requiere renovación | W36: =VLOOKUP(P36,Datos!$F:$G,6,0) -> #REF!
A37: BFE-LAMPI-00000067 | B37: Lampara Pielitica Auxiliar De Cirugia | C37: 67 | D37: E031-G1-0002 | E37: Ginecologia | F37: Trident Medical | G37: Domelux6200s | H37: A - En Operación | I37: =VLOOKUP(C36,Datos!$F:$G,6,0) -> #REF! | K37: CONSULTA EXTERNA | L37: BASCULA CON TALLIMETRO | M37: HEALTH O METER | N37: 160 KG | O37: SIN SERIE | P37: 6111/12760 | Q37: 38930 | R37: 500000 | S37: 0 | T37: 600000 | U37: FALSE | V37: Funcionamiento aprox 1 año | W37: =VLOOKUP(P37,Datos!$F:$G,6,0) -> #REF!
A38: B | B38: #N/A | C38: #N/A | D38: #N/A | E38: #N/A | F38: #N/A | G38: #N/A | H38: #N/A | I38: =VLOOKUP(C37,Datos!$F:$G,6,0) -> #REF! | K38: URGENCIAS ADULTOS | L38: BASCULA CON TALLIMETRO | M38: HEALTH O METER | N38: 140KG | O38: SIN SERIE | P38: 1066 | Q38: 38930 | R38: 500000 | S38: 0 | T38: 600000 | U38: FALSE | V38: Reemplazo inmmediato | W38: =VLOOKUP(P38,Datos!$F:$G,6,0) -> #REF!
A39: BMO-MONFE-00007841 | B39: Monitor Fetal | C39: 7841 | D39: SAS10024555PA | E39: Ginecologia | F39: General Electric | G39: Corometrics 170 | H39: A - En Operación | I39: =VLOOKUP(C38,Datos!$F:$G,6,0) -> #N/A | K39: CENTRO MEDICO | L39: BASCULA CON TALLIMETRO | M39: HEALTH O METER | N39: 142KL | O39: 1420078451 | P39: 15747 | Q39: 43669 | R39: 154700 | S39: 0 | T39: 600000 | U39: FALSE | V39: No requiere renovación | W39: =VLOOKUP(P39,Datos!$F:$G,6,0) -> #REF!
A40: BMO-MOSIV-00014800 | B40: Monitor De Signos Vitales | C40: 14800 | D40: KN73006799 | E40: Hospitalización | F40: Mindray | G40: Umec 10 | H40: A - En Operación | I40: =VLOOKUP(C39,Datos!$F:$G,6,0) -> #REF! | K40: CONSULTA EXTERNA | L40: BASCULA CON TALLIMETRO | M40: SECA | N40: 777 | O40: 10000000305725 | P40: 16901 | Q40: 44286 | R40: 2474010 | S40: 0 | T40: 600000 | U40: 4 | V40: No requiere renovación | W40: =VLOOKUP(P40,Datos!$F:$G,6,0) -> #REF!
A41: BMO-MOSIV-00014951 | B41: Monitor De Signos Vitales | C41: 14951 | D41: KN75009297 | E41: Urgencias Adulto | F41: Mindray | G41: Umec 10 | H41: A - En Operación | I41: =VLOOKUP(C40,Datos!$F:$G,6,0) -> #REF! | K41: URGENCIAS | L41: BASCULA CON TALLIMETRO | M41: SECA | N41: 769 | O41: 10000000866906 | P41: 18955 | Q41: 45132 | R41: 2853196 | S41: 0 | T41: 400000 | U41: 4 | V41: No requiere renovación | W41: =VLOOKUP(P41,Datos!$F:$G,6,0) -> #REF!
A42: BMO-MOSIV-00009877 | B42: Monitor De Signos Vitales | C42: 9877 | D42: CC26122857 | E42: Urgencias Adulto | F42: Mindray | G42: Mec1200 | H42: I - Dado de Baja | I42: =VLOOKUP(C41,Datos!$F:$G,6,0) -> #REF! | K42: CENTRO MEDICO | L42: BASCULA MECANICA | M42: NEWMED | N42: DT-05 | O42: BANM2015509 | P42: 14225 | Q42: 42692 | R42: 220400 | S42: 0 | T42: 600000 | U42: FALSE | V42: Evaluar tecnología en un año | W42: =VLOOKUP(P42,Datos!$F:$G,6,0) -> #REF!
A43: BMO-TRMOH-00014894 | B43: Termohigrometro Digital | C43: 14894 | D43: N/A | E43: Salas De Cirugia | F43: Kex Germany | G43: Digital | H43: A - En Operación | I43: =VLOOKUP(C42,Datos!$F:$G,6,0) -> #REF! | K43: CENTRO MEDICO | L43: BASCULA MECANICA | M43: NEWMED | N43: DT-06 | O43: BANM20157050 | P43: 14429 | Q43: 42894 | R43: 226100 | S43: 0 | T43: 600000 | U43: FALSE | V43: No requiere renovación | W43: =VLOOKUP(P43,Datos!$F:$G,6,0) -> #REF!
A44: OTP | B44: #N/A | C44: #N/A | D44: #N/A | E44: #N/A | F44: #N/A | G44: #N/A | H44: #N/A | I44: =VLOOKUP(C43,Datos!$F:$G,6,0) -> #REF! | K44: UNIDAD QUIRURGICA | L44: BASCULA MECANICA | M44: NEWMED | N44: DT-05 | O44: BANM2015592 | P44: 15276 | Q44: 43215 | R44: 226100 | S44: 0 | T44: 600000 | U44: FALSE | V44: No requiere renovación | W44: =VLOOKUP(P44,Datos!$F:$G,6,0) -> #REF!
A45: BDG-MOSIV-00117728 | B45: Monitor De Signos Vitales | C45: Alquiler | D45: 117728 | E45: Biomedica | F45: Nihon kohden | G45: PVM-2701 | H45: A - En Operación | I45: =VLOOKUP(C44,Datos!$F:$G,6,0) -> #N/A | K45: HOSPITALIZACION | L45: BASCULA MECANICA | M45: HEALTH O METER | N45: 142KL | O45: 1420063087 | P45: 14089 | Q45: 42587 | R45: 228109 | S45: 0 | T45: 600000 | U45: FALSE | V45: Evaluar tecnología en un año | W45: =VLOOKUP(P45,Datos!$F:$G,6,0) -> #REF!
A46: BSD-ESTVA-00009771 | B46: Esterilizador A Vapor | C46: 9771 | D46: 2907032 | E46: Central De Esterilizacion | F46: Tuttnauer | G46: T-MAX6 | H46: A - En Operación | I46: =VLOOKUP(C45,Datos!$F:$G,6,0) -> #REF! | K46: HOSPITALIZACION | L46: BASCULA MECANICA | M46: NEWMED | N46: DT-05 | O46: BANM2015568 | P46: 15012 | Q46: 43129 | R46: 226100 | S46: 0 | T46: 600000 | U46: FALSE | V46: No requiere renovación | W46: =VLOOKUP(P46,Datos!$F:$G,6,0) -> #REF!
A47: BOF-AUTOP-00006040 | B47: Auto Proyector | C47: 6040 | D47: 3PC9B0030 | E47: Consulta Externa | F47: Luxvision | G47: Ccp3100 | H47: I - Dado de Baja | I47: =VLOOKUP(C46,Datos!$F:$G,6,0) -> #REF! | K47: TERAPIA FISICA | L47: BASCULA MECANICA | M47: NEWMED | N47: DT-05 | O47: BANM2015594 | P47: 15077 | Q47: 43140 | R47: 226100 | S47: 0 | T47: 600000 | U47: FALSE | V47: No requiere renovación | W47: =VLOOKUP(P47,Datos!$F:$G,6,0) -> #REF!
A48: BQX-MTORA-NTC62546 | B48: Motor De Alta Revolucion | C48: Comodato | D48: NTC62546 | E48: Central De Esterilizacion | F48: Medtronic Midas | G48: Ec300/Em200 | H48: A - En Operación | I48: =VLOOKUP(C47,Datos!$F:$G,6,0) -> #REF! | K48: TERAPIA FISICA | L48: BASCULA MECANICA | M48: NEWMED | N48: DT-05 | O48: BANM2015694 | P48: 15081 | Q48: 43140 | R48: 226100 | S48: 0 | T48: 600000 | U48: FALSE | V48: No requiere renovación | W48: =VLOOKUP(P48,Datos!$F:$G,6,0) -> #REF!
A49: BQX-MTORA-NTC60563 | B49: Motor De Alta Revolucion | C49: Comodato | D49: NTC60563 | E49: Central De Esterilizacion | F49: Medtronic Midas | G49: Ec300/Em200 | H49: A - En Operación | I49: =VLOOKUP(C48,Datos!$F:$G,6,0) -> #REF! | K49: UNIDAD QUIRURGICA | L49: BASCULA MECANICA | M49: NEWMED | N49: DT-05 | O49: BANM2015593 | P49: 15176 | Q49: 43159 | R49: 226100 | S49: 0 | T49: 600000 | U49: FALSE | V49: No requiere renovación | W49: =VLOOKUP(P49,Datos!$F:$G,6,0) -> #REF!
A50: BQX-MTORA-NTC60557 | B50: Motor De Alta Revolucion | C50: Comodato | D50: NTC60557 | E50: Central De Esterilizacion | F50: Medtronic Midas | G50: Ec300/Em200 | H50: A - En Operación | I50: =VLOOKUP(C49,Datos!$F:$G,6,0) -> #REF! | K50: URGENCIAS PEDIATRIA | L50: BASCULA MECANICA | M50: NEWMED | N50: DT-05 | O50: BANM2015630 | P50: 14925 | Q50: 43062 | R50: 174000 | S50: 0 | T50: 600000 | U50: FALSE | V50: No requiere renovación | W50: =VLOOKUP(P50,Datos!$F:$G,6,0) -> #REF!
A51: BMO-MOSIV-00015574 | B51: Monitor De Signos Vitales | C51: 15574 | D51: KN8C034437 | E51: Salas De Cirugia | F51: Mindray | G51: Umec 10 | H51: A - En Operación | I51: =VLOOKUP(C50,Datos!$F:$G,6,0) -> #REF! | K51: URGENCIAS PEDIATRIA | L51: BASCULA MECANICA | M51: NEWMED | N51: DT-06 | O51: BANM2015888 | P51: 14813 | Q51: 43060 | R51: 174000 | S51: 0 | T51: 600000 | U51: FALSE | V51: No requiere renovación | W51: =VLOOKUP(P51,Datos!$F:$G,6,0) -> #REF!
A52: OTP | B52: #N/A | C52: #N/A | D52: #N/A | E52: #N/A | F52: #N/A | G52: #N/A | H52: #N/A | I52: =VLOOKUP(C51,Datos!$F:$G,6,0) -> #REF! | K52: LABORATORIO DE MARCHA | L52: BASCULA CON TALLIMETRO | M52: HEALTH O METER | N52: 450kL | O52: 4500010040 | P52: 13929 | Q52: 42482 | R52: 1017900 | S52: 0 | T52: 600000 | U52: 3 | V52: Evaluar tecnología en un año | W52: =VLOOKUP(P52,Datos!$F:$G,6,0) -> #REF!
A53: BMO-MOSIV-00007534 | B53: Monitor De Signos Vitales | C53: 7534 | D53: AA79102588 | E53: Salas De Cirugia | F53: Mindray | G53: Pm8000 | H53: A - En Operación | I53: =VLOOKUP(C52,Datos!$F:$G,6,0) -> #N/A | K53: CONSULTA EXTERNA | L53: BASCULA MECANICA | M53: NEWMED | N53: DT-05 | O53: BANM2015868 | P53: 15433 | Q53: 43448 | R53: 249900 | S53: 0 | T53: 600000 | U53: FALSE | V53: No requiere renovación | W53: =VLOOKUP(P53,Datos!$F:$G,6,0) -> #REF!
A54: BMP-MESAC-00009170 | B54: Mesa De Procedimientos Quirurgicos | C54: 9170 | D54: A013-G2-0003 | E54: Salas De Cirugia | F54: Trident Medical | G54: Novel 330tk | H54: I - Dado de baja | I54: =VLOOKUP(C53,Datos!$F:$G,6,0) -> #REF! | K54: HOSPITALIZACION | L54: BASCULA MECANICA | M54: NEWMED | N54: DT-05 | O54: BANM2015787 | P54: 15432 | Q54: 43448 | R54: 249900 | S54: 0 | T54: 600000 | U54: FALSE | V54: No requiere renovación | W54: =VLOOKUP(P54,Datos!$F:$G,6,0) -> #REF!
A55: BMO-MOSIV-00008128 | B55: Monitor De Signos Vitales | C55: 8128 | D55: DM06002156 | E55: Ginecologia | F55: Mindray | G55: Ipm9800 | H55: A - En Operación | I55: =VLOOKUP(C54,Datos!$F:$G,6,0) -> #REF! | K55: UNIDAD QUIRURGICA | L55: BASCULA MECANICA | M55: NEWMED | N55: DT-05 | O55: BANM2015672 | P55: 15479 | Q55: 43523 | R55: 249900 | S55: 0 | T55: 600000 | U55: FALSE | V55: No requiere renovación | W55: =VLOOKUP(P55,Datos!$F:$G,6,0) -> #REF!
A56: BMO-MOSIV-00013422 | B56: Monitor De Signos Vitales | C56: 13422 | D56: CC53131291 | E56: Salas De Cirugia | F56: Mindray | G56: Mec 1200 | H56: A - En Operación | I56: =VLOOKUP(C55,Datos!$F:$G,6,0) -> #REF! | K56: URGENCIAS ADULTOS | L56: BASCULA CON TALLIMETRO | M56: DETECTO | N56: SIN IDENTIFICAR | O56: SIN SERIE | P56: 14094 | Q56: 42598 | R56: 638000 | S56: 0 | T56: 600000 | U56: 1 | V56: Evaluar tecnología en un año | W56: =VLOOKUP(P56,Datos!$F:$G,6,0) -> #REF!
A57: BMO-MOSIV-00015787 | B57: Monitor De Signos Vitales | C57: 15787 | D57: KN-94041449 | E57: Hospitalización | F57: Mindray | G57: uMEC 10 | H57: A - En Operación | I57: =VLOOKUP(C56,Datos!$F:$G,6,0) -> #REF! | K57: URGENCIAS ADULTOS | L57: BASCULA MECANICA | M57: NEWMED | N57: DT-05 | O57: BANM2015628 | P57: 14949 | Q57: 43081 | R57: 226100 | S57: 0 | T57: 600000 | U57: FALSE | V57: No requiere renovación | W57: =VLOOKUP(P57,Datos!$F:$G,6,0) -> #REF!
A58: BCC-ELCBI-00009135 | B58: Electrobisturi | C58: 9135 | D58: SF0H07611A | E58: Salas De Cirugia | F58: Valleylab | G58: Force Fx | H58: A - En Operación | I58: =VLOOKUP(C57,Datos!$F:$G,6,0) -> #REF! | K58: URGENCIAS PEDIATRIA | L58: BASCULA MECANICA | M58: SOEHNLE | N58: SIN MODELO | O58: SIN SERIE | P58: 7880 | Q58: 42482 | R58: 2853196 | S58: 0 | T58: 600000 | U58: 4 | V58: No requiere renovación | W58: =VLOOKUP(P58,Datos!$F:$G,6,0) -> #REF!
A59: BMO-MOSIV-00015576 | B59: Monitor De Signos Vitales | C59: 15576 | D59: KN8C034490 | E59: Salas De Cirugia | F59: Mindray | G59: Umec 10 | H59: A - En Operación | I59: =VLOOKUP(C58,Datos!$F:$G,6,0) -> #REF! | K59: HOSPITALIZACION | L59: BASCULA MECANICA | M59: NEWMED | N59: 130KG | O59: BANM2015514 | P59: 14107 | Q59: 42620 | R59: 220400 | S59: 0 | T59: 600000 | U59: FALSE | V59: Evaluar tecnología en un año | W59: =VLOOKUP(P59,Datos!$F:$G,6,0) -> #REF!
A60: BMO-MOSIV-00008128 | B60: Monitor De Signos Vitales | C60: 8128 | D60: DM06002156 | E60: Ginecologia | F60: Mindray | G60: Ipm9800 | H60: A - En Operación | I60: =VLOOKUP(C59,Datos!$F:$G,6,0) -> #REF! | K60: HOSPITALIZACION | L60: BASCULA MECANICA | M60: NEWMED | N60: DT-05 | O60: BANM2015629 | P60: 14903 | Q60: 43059 | R60: 226100 | S60: 0 | T60: 600000 | U60: FALSE | V60: No requiere renovación | W60: =VLOOKUP(P60,Datos!$F:$G,6,0) -> #REF!
A61: BMO-MONFE-00007673 | B61: Monitor Fetal | C61: 7673 | D61: SAS10024554PA | E61: Ginecologia | F61: General Electric | G61: Corometrics 171 | H61: A - En Operación | I61: =VLOOKUP(C60,Datos!$F:$G,6,0) -> #REF! | K61: HOSPITALIZACION | L61: BASCULA MECANICA | M61: NEWMED | N61: DT-05 | O61: BANM2015515 | P61: 14090 | Q61: 42587 | R61: 220400 | S61: 0 | T61: 600000 | U61: FALSE | V61: Evaluar tecnología en un año | W61: =VLOOKUP(P61,Datos!$F:$G,6,0) -> #REF!
A62: BMO-MOSIV-00015574 | B62: Monitor De Signos Vitales | C62: 15574 | D62: KN8C034437 | E62: Salas De Cirugia | F62: Mindray | G62: Umec 10 | H62: A - En Operación | I62: =VLOOKUP(C61,Datos!$F:$G,6,0) -> #REF! | K62: BANCO DE SANGRE | L62: BASCULA MECANICA | M62: NEWMED | N62: DT05 | O62: BANM2015884 | P62: 14214 | Q62: 42664 | R62: 220400 | S62: 0 | T62: 600000 | U62: FALSE | V62: Evaluar tecnología en un año | W62: =VLOOKUP(P62,Datos!$F:$G,6,0) -> #REF!
A63: BMO-MONFE-00007673 | B63: Monitor Fetal | C63: 7673 | D63: SAS10024554PA | E63: Ginecologia | F63: General Electric | G63: Corometrics 171 | H63: A - En Operación | I63: =VLOOKUP(C62,Datos!$F:$G,6,0) -> #REF! | K63: BANCO DE SANGRE | L63: BASCULA MECANICA | M63: NEWMED | N63: DT06 | O63: BANM2015731 | P63: 14756 | Q63: 42990 | R63: 19631410 | S63: 0 | T63: 600000 | U63: 5 | V63: No requiere renovación | W63: =VLOOKUP(P63,Datos!$F:$G,6,0) -> #REF!
A64: BMO-MOSIV-00010012 | B64: Monitor De Signos Vitales | C64: 10012 | D64: CC28123459 | E64: Imagenes Diagnosticas | F64: Mindray | G64: Mec1200 | H64: A - En Operación | I64: =VLOOKUP(C63,Datos!$F:$G,6,0) -> #REF! | K64: CONSULTA EXTERNA | L64: BASCULA MECANICA | M64: HEALTH O METER | N64: 142KG | O64: 1420063178 | P64: 13811 | Q64: 42420 | R64: 228109 | S64: 0 | T64: 600000 | U64: FALSE | V64: Evaluar tecnología en un año | W64: =VLOOKUP(P64,Datos!$F:$G,6,0) -> #REF!
A65: BDG-MOSIV-00015947 | B65: Monitor De Signos Vitales | C65: 15947 | D65: KQ-9B029525 | E65: Hospitalización | F65: Mindray | G65: Umec12 | H65: A - En Operación | I65: =VLOOKUP(C64,Datos!$F:$G,6,0) -> #REF! | K65: CONSULTA EXTERNA | L65: BASCULA MECANICA | M65: HEALTH O METER | N65: 142KG | O65: 1420063179 | P65: 13810 | Q65: 42420 | R65: 228109 | S65: 0 | T65: 600000 | U65: FALSE | V65: Evaluar tecnología en un año | W65: =VLOOKUP(P65,Datos!$F:$G,6,0) -> #REF!
A66: BMO-MOSIV-00015577 | B66: Monitor De Signos Vitales | C66: 15577 | D66: KN8C034414 | E66: Salas De Cirugia | F66: Mindray | G66: Umec 10 | H66: A - En Operación | I66: =VLOOKUP(C65,Datos!$F:$G,6,0) -> #REF! | K66: CONSULTA EXTERNA | L66: BASCULA MECANICA | M66: HEALTH O METER | N66: 142KG | O66: 1420063129 | P66: 13808 | Q66: 42420 | R66: 228109 | S66: 0 | T66: 600000 | U66: FALSE | V66: Evaluar tecnología en un año | W66: =VLOOKUP(P66,Datos!$F:$G,6,0) -> #REF!
A67: BMO-PULSO-00015683 | B67: Pulsoximetro | C67: 12491/15683 | D67: 134231400674 | E67: Terapia Respiratoria | F67: AIRIAL | G67: MQ3000 | H67: I - Dado de Baja | I67: =VLOOKUP(C66,Datos!$F:$G,6,0) -> #REF! | K67: CONSULTA EXTERNA | L67: BASCULA MECANICA | M67: HEALTH O METER | N67: 142KG | O67: 1420063086 | P67: 13806 | Q67: 42420 | R67: 991172 | S67: 0 | T67: 600000 | U67: 2 | V67: Evaluar tecnología en un año | W67: =VLOOKUP(P67,Datos!$F:$G,6,0) -> #REF!
A68: BMO-MOSIV-00000121 | B68: Monitor De Signos Vitales | C68: 121 | D68: AAW07300275CA | E68: Salas De Cirugia | F68: General Electric | G68: Procare 300 | H68: I - Dado de baja | I68: =VLOOKUP(C67,Datos!$F:$G,6,0) -> #REF! | K68: URGENCIAS ADULTOS | L68: BASCULA CON TALLIMETRO | M68: SOEHNLE | N68: 130KG | O68: SIN | P68: 13243 | Q68: 42124 | R68: 568400 | S68: 0 | T68: 600000 | U68: FALSE | V68: Evaluar tecnología en un año | W68: =VLOOKUP(P68,Datos!$F:$G,6,0) -> #REF!
A69: BMO-MSVAN-00007604 | B69: Monitor Multiparametros De Anestesia | C69: 7604 | D69: 6627939 | E69: Salas De Cirugia | F69: Ge Datex-Ohmeda | G69: Cardiocap /5 | H69: A - En Operación | I69: =VLOOKUP(C68,Datos!$F:$G,6,0) -> #REF! | K69: CONSULTA EXTERNA | L69: BASCULA MECANICA | M69: SOEHNLE | N69: 130KG | O69: SIN | P69: 12811 | Q69: 41922 | R69: 52200 | S69: 0 | T69: 600000 | U69: FALSE | V69: Evaluar tecnología en un año | W69: =VLOOKUP(P69,Datos!$F:$G,6,0) -> #REF!
A70: BMO-MOSIV-00015576 | B70: Monitor De Signos Vitales | C70: 15576 | D70: KN8C034490 | E70: Salas De Cirugia | F70: Mindray | G70: Umec 10 | H70: A - En Operación | I70: =VLOOKUP(C69,Datos!$F:$G,6,0) -> #REF! | K70: URGENCIAS PEDIATRIA | L70: BASCULA MECANICA | M70: HEALTH METER | N70: 1522KL | O70: 1522010830 | P70: 11866 | Q70: 41659 | R70: 748200 | S70: 0 | T70: 600000 | U70: 2 | V70: Evaluar tecnología en un año | W70: =VLOOKUP(P70,Datos!$F:$G,6,0) -> #REF!
A71: B | B71: #N/A | C71: #N/A | D71: #N/A | E71: #N/A | F71: #N/A | G71: #N/A | H71: #N/A | I71: =VLOOKUP(C70,Datos!$F:$G,6,0) -> #REF! | K71: CONSULTA EXTERNA | L71: BASCULA MECANICA | M71: NEW MED | N71: DT-05 | O71: BANM2015816 | P71: 14196 | Q71: 42653 | R71: 220400 | S71: 0 | T71: 600000 | U71: FALSE | V71: Evaluar tecnología en un año | W71: =VLOOKUP(P71,Datos!$F:$G,6,0) -> #REF!
A72: BMO-MOSIV-00015575 | B72: Monitor De Signos Vitales | C72: 15575 | D72: KN8C034399 | E72: Ginecologia | F72: Mindray | G72: Umec 10 | H72: A - En Operación | I72: =VLOOKUP(C71,Datos!$F:$G,6,0) -> #N/A | K72: HOSPITALIZACION | L72: BASCULA MECANICA | M72: NEOMED | N72: 130KG | O72: BANM2015517 | P72: 14106 | Q72: 42620 | R72: 220400 | S72: 0 | T72: 600000 | U72: FALSE | V72: Evaluar tecnología en un año | W72: =VLOOKUP(P72,Datos!$F:$G,6,0) -> #REF!
A73: B | B73: #N/A | C73: #N/A | D73: #N/A | E73: #N/A | F73: #N/A | G73: #N/A | H73: #N/A | I73: =VLOOKUP(C72,Datos!$F:$G,6,0) -> #REF! | K73: CONSULTA EXTERNA | L73: BASCULA MECANICA | M73: HEALTH O METER | N73: 142KL | O73: 1420080503 | P73: 16057 | Q73: 43923 | R73: 321300 | S73: 0 | T73: 600000 | U73: FALSE | V73: No requiere renovación | W73: =VLOOKUP(P73,Datos!$F:$G,6,0) -> #REF!
A74: BMO-MOSIV-00013420 | B74: Monitor De Signos Vitales | C74: 13420 | D74: CC53131308 | E74: Salas De Cirugia | F74: Mindray | G74: Mec 1200 | H74: A - En Operación | I74: =VLOOKUP(C73,Datos!$F:$G,6,0) -> #N/A | K74: HOSPITALIZACIÓN | L74: BASCULA MECANICA | M74: HEALTH O METER | N74: 142KL | O74: 1420080502 | P74: 16058 | Q74: 43923 | R74: 321300 | S74: 0 | T74: 400000 | U74: FALSE | V74: No requiere renovación | W74: =VLOOKUP(P74,Datos!$F:$G,6,0) -> #REF!
A75: BMO-MOSIV-00015211 | B75: Monitor De Signos Vitales | C75: 15211 | D75: KN-7A015277 | E75: Ginecologia | F75: Mindray | G75: Umec 10 | H75: A - En Operación | I75: =VLOOKUP(C74,Datos!$F:$G,6,0) -> #REF! | K75: CONSULTA EXTERNA | L75: BASCULA MECANICA | M75: HEALTH O METER | N75: 450KL | O75: 4500009804 | P75: 13807 | Q75: 42420 | R75: 228109 | S75: 0 | T75: 600000 | U75: FALSE | V75: Evaluar tecnología en un año | W75: =VLOOKUP(P75,Datos!$F:$G,6,0) -> #REF!
A76: BMO-MOSIV-00000294 | B76: Monitor De Signos Vitales | C76: 294 | D76: AAW07240072SA | E76: Biomedica | F76: General Electric | G76: Procare 300 | H76: I - Dado de baja | I76: =VLOOKUP(C75,Datos!$F:$G,6,0) -> #REF! | K76: CONSULTA EXTERNA | L76: BASCULA PESA BEBE | M76: CHARDER | N76: MS2400 | O76: C14020897 | P76: 12873 | Q76: 41978 | R76: 462840 | S76: 0 | T76: 600000 | U76: FALSE | V76: Evaluar tecnología en un año | W76: =VLOOKUP(P76,Datos!$F:$G,6,0) -> #REF!
A77: BMO-MONFE-00007673 | B77: Monitor Fetal | C77: 7673 | D77: SAS10024554PA | E77: Ginecologia | F77: General Electric | G77: Corometrics 171 | H77: A - En Operación | I77: =VLOOKUP(C76,Datos!$F:$G,6,0) -> #REF! | K77: URGENCIAS PEDIATRIA | L77: BÁSCULA PESA BEBE | M77: HEALTH O METER | N77: 1386 | O77: 38600006506 | P77: 13244 | Q77: 42124 | R77: 372360 | S77: 0 | T77: 600000 | U77: FALSE | V77: Evaluar tecnología en un año | W77: =VLOOKUP(P77,Datos!$F:$G,6,0) -> #REF!
A78: BMO-MOSIV-00014801 | B78: Monitor De Signos Vitales | C78: 14801 | D78: KN73006801 | E78: Ginecologia | F78: Mindray | G78: Umec 10 | H78: A - En Operación | I78: =VLOOKUP(C77,Datos!$F:$G,6,0) -> #REF! | K78: UNIDAD QUIRURGICA | L78: BISTURI ELECTRICO DE CORTE Y RADIOFRECUENCIA | M78: ELLMAN SURGITRON | N78: SIN MODELO | O78: 9120003529 | P78: 7119/12978 | Q78: 38718 | R78: 2853196 | S78: 0 | T78: 600000 | U78: 4 | V78: Funcionamiento aprox 1 año | W78: =VLOOKUP(P78,Datos!$F:$G,6,0) -> #REF!
A79: BMO-MONFE-00014448 | B79: Monitor Fetal | C79: 14848 | D79: SAS16115513PAS | E79: Ginecologia | F79: General Electric | G79: Corometrics 171 | H79: A - En Operación | I79: =VLOOKUP(C78,Datos!$F:$G,6,0) -> #REF! | K79: UNIDAD QUIRURGICA | L79: CALENTADOR DE LIQUIDOS | M79: STERIS | N79: warmin cabinet | O79: 424516011 | P79: 14514 | Q79: 42914 | R79: 19631410 | S79: 0 | T79: 1200000 | U79: 5 | V79: No requiere renovación | W79: =VLOOKUP(P79,Datos!$F:$G,6,0) -> #REF!
A80: BMO-MOSIV-00015211 | B80: Monitor De Signos Vitales | C80: 15211 | D80: KN-7A015277 | E80: Ginecologia | F80: Mindray | G80: Umec 10 | H80: A - En Operación | I80: =VLOOKUP(C79,Datos!$F:$G,6,0) -> #REF! | K80: GINECOLOGIA | L80: CALENTADOR DE LIQUIDOS | M80: LW SCIENTIFIC | N80: 20 LITROS | O80: 3812 | P80: 18241 | Q80: 44838 | R80: 4379200 | S80: 0 | T80: 600000 | U80: 4 | V80: Funcionamiento aprox 1 año | W80: =VLOOKUP(P80,Datos!$F:$G,6,0) -> #REF!
A81: BDG-TENPO-00008760 | B81: Tensiometro Portatil | C81: 8760 | D81: 532734 | E81: Hospitalización | F81: WELCH ALLYN | G81: NO TIENE | H81: A - En Operación | I81: =VLOOKUP(C80,Datos!$F:$G,6,0) -> #REF! | K81: CONSULTA EXTERNA | L81: CABINA SONOAMORTIGUADA | M81: DISTRIAUDIO | N81: NO TIENE | O81: NO TIENE | P81: 6025 | Q81: 39855 | R81: 1 | S81: 0 | T81: 946050 | U81: FALSE | V81: Funcionamiento aprox 1 año | W81: =VLOOKUP(P81,Datos!$F:$G,6,0) -> #REF!
A82: BMO-MONFE-00015809 | B82: Monitor Fetal | C82: 15809 | D82: SNU18110230PAS | E82: Ginecologia | F82: General Electric | G82: Corometrics 170 | H82: A - En Operación | I82: =VLOOKUP(C81,Datos!$F:$G,6,0) -> #REF! | K82: URGENCIAS ADULTOS | L82: CAPNOGRAFO | M82: EMMA | N82: ETCO | O82: 605102 | P82: 9896 | Q82: No registra | R82: 6032000 | S82: 0 | T82: 600000 | U82: 5 | V82: Evaluar tecnología en un año | W82: =VLOOKUP(P82,Datos!$F:$G,6,0) -> #REF!
A83: BMO-MOSIV-00013420 | B83: Monitor De Signos Vitales | C83: 13420 | D83: CC53131308 | E83: Salas De Cirugia | F83: Mindray | G83: Mec 1200 | H83: A - En Operación | I83: =VLOOKUP(C82,Datos!$F:$G,6,0) -> #REF! | K83: UNIDAD QUIRURGICA | L83: CAPTURADOR DE IMAGEN (WOLF) | M83: MEDI CAPTURE | N83: USB200 | O83: 2211044 | P83: 10234 | Q83: 41019 | R83: 14000000 | S83: 0 | T83: 600000 | U83: 5 | V83: Evaluar tecnología en un año | W83: =VLOOKUP(P83,Datos!$F:$G,6,0) -> #REF!
A84: BMO-MONFE-00015809 | B84: Monitor Fetal | C84: 15809 | D84: SNU18110230PAS | E84: Ginecologia | F84: General Electric | G84: Corometrics 170 | H84: A - En Operación | I84: =VLOOKUP(C83,Datos!$F:$G,6,0) -> #REF! | K84: UNIDAD QUIRURGICA | L84: CALENTADOR DE SANGRE | M84: 3M | N84: RANGER 245 | O84: 81045 | P84: 15882 | Q84: 43822 | R84: 5777450 | S84: 0 | T84: 600000 | U84: 4 | V84: No requiere renovación | W84: =VLOOKUP(P84,Datos!$F:$G,6,0) -> #REF!
A85: BMO-MOSIV-00015588 | B85: Monitor De Signos Vitales | C85: 15588 | D85: 6009532669 | E85: Salas De Cirugia | F85: Drager | G85: Infinity Del | H85: A - En Operación | I85: =VLOOKUP(C84,Datos!$F:$G,6,0) -> #REF! | K85: HOSPITALIZACION | L85: CENTRAL DE MONITOREO | M85: MINDRAY | N85: HYPERVISOR VI | O85: 1578A21MJAEH58 | P85: 8135 | Q85: 40618 | R85: 1438726 | S85: 0 | T85: 600000 | U85: 3 | V85: Funcionamiento aprox 1 año | W85: =VLOOKUP(P85,Datos!$F:$G,6,0) -> #REF!
A86: BMO-MOSIV-00012982 | B86: Monitor De Signos Vitales | C86: 12982 | D86: EW-43009160 | E86: Urgencias Pediatria | F86: Mindray | G86: Imec8 | H86: A - En Operación | I86: =VLOOKUP(C85,Datos!$F:$G,6,0) -> #REF! | K86: BANCO DE SANGRE | L86: CENTRIFUGA REFRIGERADA | M86: THERMO | N86: 5500i | O86: 41154063 | P86: 8076 | Q86: 40533 | R86: 66120000 | S86: 0 | T86: 600000 | U86: 5 | V86: Funcionamiento aprox 1 año | W86: =VLOOKUP(P86,Datos!$F:$G,6,0) -> #REF!
A87: BMO-MONFE-00007146 | B87: Monitor Fetal | C87: 7146 | D87: SAS09063392PA | E87: Ginecologia | F87: General Electric | G87: Corometrics 172 | H87: A - En Operación | I87: =VLOOKUP(C86,Datos!$F:$G,6,0) -> #REF! | K87: BANCO DE SANGRE | L87: CENTRIFUGA | M87: CLAY ADAMS | N87: ANALITICA | O87: 26808 | P87: 5607 | Q87: 38933 | R87: 10000000 | S87: 0 | T87: 600000 | U87: 5 | V87: Funcionamiento aprox 1 año | W87: =VLOOKUP(P87,Datos!$F:$G,6,0) -> #REF!
A88: BAN-MAQAN-00002780 | B88: Maquina De Anestesia | C88: 2780 | D88: AMXL01116 | E88: Salas De Cirugia | F88: Datex Ohmeda | G88: Aespire 7100 | H88: A - En Operación | I88: =VLOOKUP(C87,Datos!$F:$G,6,0) -> #REF! | K88: BANCO DE SANGRE | L88: CENTRIFUGA | M88: SIGMA | N88: 2-6E | O88: 159924 | P88: 13816 | Q88: 42432 | R88: 11368000 | S88: 0 | T88: 600000 | U88: 5 | V88: No requiere renovación | W88: =VLOOKUP(P88,Datos!$F:$G,6,0) -> #REF!
A89: BMO-MONFE-00011315 | B89: Monitor Fetal | C89: 11315 | D89: SAS13360902SA | E89: Ginecologia | F89: General Electric | G89: Corometrics 171 | H89: A - En Operación | I89: =VLOOKUP(C88,Datos!$F:$G,6,0) -> #REF! | K89: BANCO DE SANGRE | L89: CENTRIFUGA | M89: SIGMA | N89: 2-6E | O89: 155668 | P89: 13779 | Q89: 42391 | R89: 11368000 | S89: 0 | T89: 600000 | U89: 5 | V89: No requiere renovación | W89: =VLOOKUP(P89,Datos!$F:$G,6,0) -> #REF!
A90: BMO-MOSIV-00014211 | B90: Monitor De Signos Vitales | C90: 14211 | D90: FG-54019473 | E90: Salas De Cirugia | F90: Mindray | G90: Ipm10 | H90: A - En Operación | I90: =VLOOKUP(C89,Datos!$F:$G,6,0) -> #REF! | K90: UNIDAD QUIRURGICA | L90: COMPRESOR VASCULAR | M90: COVIDIEN | N90: SCD700 | O90: V1820564SX | P90: 15783 | Q90: 43697 | R90: 5011685 | S90: 0 | T90: 600000 | U90: 4 | V90: No requiere renovación | W90: =VLOOKUP(P90,Datos!$F:$G,6,0) -> #REF!
A91: BMO-MONFE-00007146 | B91: Monitor Fetal | C91: 7146 | D91: SAS09063392PA | E91: Ginecologia | F91: General Electric | G91: Corometrics 172 | H91: A - En Operación | I91: =VLOOKUP(C90,Datos!$F:$G,6,0) -> #REF! | K91: BANCO DE SANGRE | L91: CONGELADOR | M91: HELMER | N91: IPF120 | O91: 2071461 | P91: 16000 | Q91: 43862 | R91: 49861000 | S91: 0 | T91: 600000 | U91: 5 | V91: No requiere renovación | W91: =VLOOKUP(P91,Datos!$F:$G,6,0) -> #REF!
A92: BMO-MOSIV-00000162 | B92: Monitor De Signos Vitales | C92: 162 | D92: AAW07240075SA | E92: Ginecologia | F92: General Electric | G92: Procare 300 | H92: I - Dado de Baja | I92: =VLOOKUP(C91,Datos!$F:$G,6,0) -> #REF! | K92: UNIDAD QUIRURGICA | L92: CONGELADOR | M92: ECOFRIAL | N92: BD-120 | O92: 105058304 | P92: 9990 | Q92: 41223 | R92: 744000 | S92: 0 | T92: 600000 | U92: 2 | V92: Evaluar tecnología en un año | W92: =VLOOKUP(P92,Datos!$F:$G,6,0) -> #REF!
A93: BMO-MONFE-00007146 | B93: Monitor Fetal | C93: 7146 | D93: SAS09063392PA | E93: Ginecologia | F93: General Electric | G93: Corometrics 172 | H93: A - En Operación | I93: =VLOOKUP(C92,Datos!$F:$G,6,0) -> #REF! | K93: NUTRICIÓN | L93: REFRIGERADOR | M93: SUPERNODICO | N93: NO TIENE | O93: NO REGISTRA | P93: 12925 | Q93: 42010 | R93: 3315280 | S93: 0 | T93: 600000 | U93: 4 | V93: No requiere renovación | W93: =VLOOKUP(P93,Datos!$F:$G,6,0) -> #REF!
A94: BMO-MONFE-00007146 | B94: Monitor Fetal | C94: 7146 | D94: SAS09063392PA | E94: Ginecologia | F94: General Electric | G94: Corometrics 172 | H94: A - En Operación | I94: =VLOOKUP(C93,Datos!$F:$G,6,0) -> #REF! | K94: BANCO DE SANGRE | L94: CONGELADOR | M94: HELMER | N94: IPF125 | O94: 2039239 | P94: 14688 | Q94: 42976 | R94: 40341000 | S94: 0 | T94: 600000 | U94: 5 | V94: No requiere renovación | W94: =VLOOKUP(P94,Datos!$F:$G,6,0) -> #REF!
A95: BMO-MONFE-00014448 | B95: Monitor Fetal | C95: 14848 | D95: SAS16115513PAS | E95: Ginecologia | F95: General Electric | G95: Corometrics 171 | H95: A - En Operación | I95: =VLOOKUP(C94,Datos!$F:$G,6,0) -> #REF! | K95: BANCO DE SANGRE | L95: CONGELADOR | M95: THERMO | N95: FFPF2330A20 | O95: 0 117509801100929 | P95: 8096 | Q95: 40536 | R95: 23200000 | S95: 0 | T95: 600000 | U95: 5 | V95: Funcionamiento aprox 1 año | W95: =VLOOKUP(P95,Datos!$F:$G,6,0) -> #REF!
A96: B | B96: #N/A | C96: #N/A | D96: #N/A | E96: #N/A | F96: #N/A | G96: #N/A | H96: #N/A | I96: =VLOOKUP(C95,Datos!$F:$G,6,0) -> #REF! | K96: BIOMEDICA | L96: CONSOLA DE CAMARA | M96: RICHARD WOLF | N96: 1100218590 | O96: 5525108 | P96: 13797 | Q96: 42419 | R96: 55487347 | S96: 0 | T96: 600000 | U96: 5 | V96: No requiere renovación | W96: =VLOOKUP(P96,Datos!$F:$G,6,0) -> #REF!
A97: BMO-MOSIV-00010047 | B97: Monitor De Signos Vitales | C97: 10047 | D97: EX-31004636 | E97: Hospitalización | F97: Mindray | G97: Imec10 | H97: A - En Operación | I97: =VLOOKUP(C96,Datos!$F:$G,6,0) -> #N/A | K97: UNIDAD QUIRURGICA | L97: CONSOLA RECEPTOSCOPIO | M97: BOWA | N97: S-LINE-400 | O97: 40000040 | P97: 12429 | Q97: 41620 | R97: 18829694 | S97: 0 | T97: 969000 | U97: 5 | V97: Evaluar tecnología en un año | W97: =VLOOKUP(P97,Datos!$F:$G,6,0) -> #REF!
A98: BMO-MONFE-00000172 | B98: Monitor Fetal | C98: 172 | D98: SAS07390796PA | E98: Ginecologia | F98: General Electric | G98: Corometrics 172 | H98: I - Dado de baja | I98: =VLOOKUP(C97,Datos!$F:$G,6,0) -> #REF! | K98: UNIDAD QUIRURGICA | L98: CONSOLA RECEPTOSCOPIO | M98: KLS MARTIN | N98: 800420204 | O98: ME402I0703189009 | P98: 15443 | Q98: 43490 | R98: 26000000 | S98: 0 | T98: 600000 | U98: 5 | V98: No requiere renovación | W98: =VLOOKUP(P98,Datos!$F:$G,6,0) -> #REF!
A99: BDG-PESBE-00003308 | B99: Pesa Bebes Digital | C99: 3308/FUCS797 | D99: 8912-97 | E99: Hospitalización | F99: Detecto | G99: 6800 | H99: I - Dado de Baja | I99: =VLOOKUP(C98,Datos!$F:$G,6,0) -> #REF! | K99: BANCO DE SANGRE | L99: DESCONGELADOR DE PLASMA | M99: HELMER | N99: DH4 | O99: 2087554 | P99: 16899 | Q99: 44293 | R99: 29724248 | S99: 0 | T99: 600000 | U99: 5 | V99: No requiere renovación | W99: =VLOOKUP(P99,Datos!$F:$G,6,0) -> #REF!
A100: BMO-MONFE-00007673 | B100: Monitor Fetal | C100: 7673 | D100: SAS10024554PA | E100: Ginecologia | F100: General Electric | G100: Corometrics 171 | H100: A - En Operación | I100: =VLOOKUP(C99,Datos!$F:$G,6,0) -> #REF! | K100: HOSPITALIZACION | L100: DESFIBRILADOR | M100: NIHON KOHDEN | N100: TEC-5531 | O100: 3691 | P100: 13597 | Q100: 42234 | R100: 21384310 | S100: 230000 | T100: 600000 | U100: 5 | V100: No requiere renovación | W100: =VLOOKUP(P100,Datos!$F:$G,6,0) -> #REF!
...

Sheet Ingreso
A1: FECHA INGRESO SERVINTE | B1: CODIGO SERVINTE | C1: DESCRIPCIÓN | D1: DESCRIPCION DETALLADA | E1: PROPIETARIO | F1: MARCA | G1: MODELO | H1: SERIE | I1: PLACA HIUSJ
A2: 41942 | B2: D13334 | C2: ARCO EN C | D2: INTENSIFICADOR DE IMÁGENES | E2: SIN IDENTIFICAR | F2: SIREMOBIL COMPACT | G2: SIEMENS | H2: 9857- 4429 | I2: 265
A3: 41942 | B3: D16234 | C3: TERMOHIGROMETRO DIGITAL | D3: TERMOMETRO HIGROMETRO DIGITAL | E3: SIN IDENTIFICAR | F3: 1452 | G3: TAYLOR | H3: SIN SERIE | I3: 5631
A4: 41942 | B4: D16235 | C4: TERMOHIGROMETRO DIGITAL | D4: TERMOMETRO HIGROMETRO DIGITAL | E4: SIN IDENTIFICAR | F4: SH109 | G4: KEX GERMANY | H4: SIN SERIE | I4: 11326
A5: 41942 | B5: D16236 | C5: TERMOHIGROMETRO DIGITAL | D5: TERMOMETRO HIGROMETRO DIGITAL | E5: SIN IDENTIFICAR | F5: SH109 | G5: KEX GERMANY | H5: SIN SERIE | I5: 9054
A6: 41942 | B6: D16242 | C6: TERMOHIGROMETRO DIGITAL | D6: TERMO HIGRONOMETRO | E6: SIN IDENTIFICAR | F6: SH-109 | G6: KEX GERMANY | H6: SIN SERIE | I6: 11665
A7: 41942 | B7: D16243 | C7: TERMOHIGROMETRO DIGITAL | D7: TERMOHIGROMETRO | E7: SIN IDENTIFICAR | F7: 3209V0270 | G7: TAYLOR | H7: 1423 | I7: 11862
A8: 41942 | B8: D16727 | C8: MONITOR DE SIGNOS VITALES | D8: MONITOR DE SIGNOS VITALES | E8: SIN IDENTIFICAR | F8: CARDIOCAP | G8: DATEX HOMEDA | H8: 6305699 | I8: 504
A9: 41942 | B9: D16630 | C9: GLUCOMETRO FREESTYLE OPTIUM NEO H ( CON ESTUCHE) | D9: MEDIDOR DE GLUCOSA | E9: COMODATO | F9: NEO H | G9: FREESTYLE | H9: LBGU198F12011 | I9: COMODATO
A10: 41942 | B10: D16631 | C10: GLUCOMETRO FREESTYLE OPTIUM NEO H ( CON ESTUCHE) | D10: MEDIDOR DE GLUCOSA | E10: COMODATO | F10: NEO H | G10: FREESTYLE | H10: LBGV160S04741 | I10: COMODATO
A11: 41942 | B11: D16632 | C11: GLUCOMETRO FREESTYLE OPTIUM NEO H ( CON ESTUCHE) | D11: MEDIDOR DE GLUCOSA | E11: COMODATO | F11: NEO H | G11: FREESTYLE | H11: LBGV160S01836 | I11: COMODATO
A12: 41942 | B12: D16633 | C12: GLUCOMETRO FREESTYLE OPTIUM NEO H ( CON ESTUCHE) | D12: MEDIDOR DE GLUCOSA | E12: COMODATO | F12: NEO H | G12: FREESTYLE | H12: LBGV160S03485 | I12: COMODATO
A13: 41942 | B13: D16634 | C13: GLUCOMETRO FREESTYLE OPTIUM NEO H ( CON ESTUCHE) | D13: MEDIDOR DE GLUCOSA | E13: COMODATO | F13: NEO H | G13: FREESTYLE | H13: LBGV120S01912 | I13: COMODATO
A14: 41942 | B14: D16635 | C14: GLUCOMETRO FREESTYLE OPTIUM NEO H ( CON ESTUCHE) | D14: MEDIDOR DE GLUCOSA | E14: COMODATO | F14: NEO H | G14: FREESTYLE | H14: LBGV160S03167 | I14: COMODATO
A15: 41942 | B15: D16636 | C15: GLUCOMETRO FREESTYLE OPTIUM NEO H ( CON ESTUCHE) | D15: MEDIDOR DE GLUCOSA | E15: COMODATO | F15: NEO H | G15: FREESTYLE | H15: LBGV160S01811 | I15: COMODATO
A16: 41942 | B16: D16637 | C16: GLUCOMETRO FREESTYLE OPTIUM NEO H ( CON ESTUCHE) | D16: MEDIDOR DE GLUCOSA | E16: COMODATO | F16: NEO H | G16: FREESTYLE | H16: LBGV160S03097 | I16: COMODATO
A17: 41942 | B17: D16638 | C17: GLUCOMETRO FREESTYLE OPTIUM NEO H ( CON ESTUCHE) | D17: MEDIDOR DE GLUCOSA | E17: COMODATO | F17: NEO H | G17: FREESTYLE | H17: LBGU319F09464 | I17: COMODATO
A18: 41942 | B18: D16639 | C18: GLUCOMETRO FREESTYLE OPTIUM NEO H ( CON ESTUCHE) | D18: MEDIDOR DE GLUCOSA | E18: COMODATO | F18: NEO H | G18: FREESTYLE | H18: LBGV160S01811 | I18: COMODATO
A19: 41942 | B19: D16642 | C19: GLUCOMETRO FREESTYLE OPTIUM NEO H ( CON ESTUCHE) | D19: MEDIDOR DE GLUCOSA | E19: COMODATO | F19: NEO H | G19: FREESTYLE | H19: LBGU198F12011 | I19: COMODATO
A20: 41942 | B20: D16643 | C20: GLUCOMETRO FREESTYLE OPTIUM NEO H ( CON ESTUCHE) | D20: MEDIDOR DE GLUCOSA | E20: COMODATO | F20: NEO H | G20: FREESTYLE | H20: LBGV160S04741 | I20: COMODATO
A21: 41942 | B21: D10134 | C21: MAQUINA DE ANESTESIA | D21: MAQUINA DE ANESTESIA | E21: HOSPITAL | F21: AESTIVA/5 MRI | G21: GE | H21: AMTR-500247 | I21: 9931
A22: 41942 | B22: D13343 | C22: SUCCIONADOR PORTATIL | D22: SUCCIONADOR | E22: HOSPITAL | F22: 1630 | G22: THOMAS | H22: 10900002151 | I22: 7512
A23: 41942 | B23: D13344 | C23: SUCCIONADOR PORTATIL | D23: ASPIRADOR PORTATIL REF 1630 THOMAS | E23: HOSPITAL | F23: 1630 | G23: THOMAS | H23: 81100007270 | I23: 10020-15773
A24: 41942 | B24: D13346 | C24: SUCCIONADOR PORTATIL | D24: SUCCIONADOR | E24: HOSPITAL | F24: 1630-BEJL06449 | G24: THOMAS | H24: 010900002152 | I24: 15775
A25: 41942 | B25: D13373 | C25: PESA BEBE | D25: PESA BEBE | E25: HOSPITAL | F25: 1522KL | G25: HEALTH A METER | H25: 1522010830 | I25: 11866
A26: 41942 | B26: D13376 | C26: BANDEJA PORTA DIFUNTO | D26: BANDEJA METALICA PARA CADAVERES | E26: HOSPITAL | F26: SIN MODELO | G26: SIN MARCA | H26: SIN SERIE | I26: 0
A27: 41942 | B27: D13377 | C27: BANDEJA PORTA DIFUNTO | D27: BANDEJA METALICA PARA CADAVERES | E27: HOSPITAL | F27: SIN MODELO | G27: SIN MARCA | H27: SIN SERIE | I27: 9999
A28: 41942 | B28: D13381 | C28: BASCULA MECANICA | D28: BASCULA PESA BEBE | E28: HOSPITAL | F28: 70 KL | G28: HEALTH A METER | H28: 483418 | I28: 7520
A29: 41942 | B29: D13396 | C29: BASCULA MECANICA | D29: PESA BEBE DIGITAL | E29: HOSPITAL | F29: MECANICA | G29: SIN MARCA | H29: SIN SERIE | I29: 108
A30: 41942 | B30: D13400 | C30: BASCULA TALLIMETRO | D30: BASCULA TALLIMETRO | E30: HOSPITAL | F30: SIN MODELO | G30: DETECTO | H30: SIN SERIE | I30: 9742
A31: 41942 | B31: D13413 | C31: TALLIMETRO EN ACRILICO | D31: TALLIMETRO EN ACRILICO | E31: HOSPITAL | F31: SIN MODELO | G31: SIN MARCA | H31: SIN SERIE | I31: 9572
A32: 41942 | B32: D13418 | C32: BASCULA TALLIMETRO | D32: PESA TALLIMETRO | E32: HOSPITAL | F32: 200 KG | G32: DETECTO | H32: SIN SERIE | I32: 7507
A33: 41942 | B33: D13465 | C33: CAMPANA ACOPLE DUCTO | D33: CAMPANA ACOPLE DUCTO | E33: HOSPITAL | F33: SIN MODELO | G33: SIN MARCA | H33: SIN SERIE | I33: 0
A34: 41942 | B34: D13466 | C34: CAMPANA CENTRAL | D34: CAMPANA CENTRAL | E34: HOSPITAL | F34: SIN MODELO | G34: SIN MARCA | H34: SIN SERIE | I34: 0
A35: 41942 | B35: D13514 | C35: CAPNOGRAFO MONITOR EMMA CON AL | D35: CAPNOGRAFO | E35: HOSPITAL | F35: ETCO | G35: EMMA | H35: 605102 | I35: 9896
A36: 41942 | B36: D13515 | C36: CAPNOGRAFO MONITOR EMMA CON AL | D36: CAPNOGRAFO MONITOR EMMA CON ALARMA MEDICION MMHG | E36: HOSPITAL | F36: SIN MODELO | G36: SIN MARCA | H36: SIN SERIE | I36: 0
A37: 41942 | B37: D13516 | C37: CARRO TRANSP COMPUTADOR | D37: CARRO TRANSP COMPUTADOR | E37: HOSPITAL | F37: SIN MODELO | G37: SIN MARCA | H37: SIN SERIE | I37: 10606-14302
A38: 41942 | B38: D13517 | C38: CARRO PORTA CILINDROS | D38: CARRO DE TRANSPORTE PEQUEÑO DE GASES | E38: HOSPITAL | F38: SIN MODELO | G38: SIN MARCA | H38: SIN SERIE | I38: 18599
A39: 41942 | B39: D13518 | C39: CENTRAL DE MONITOREO | D39: CPU | E39: HOSPITAL | F39: HIPERVISORVY | G39: MINDRAY/LENOVO | H39: AF05100666 | I39: 8135
A40: 41942 | B40: D13519 | C40: CENTRIFUGA CLAY ADAMS DYNAC | D40: CENTRIFUGA CLAY ADAMS DYNAC | E40: FUCS | F40: PR-7000M | G40: CLAY ADAMS | H40: 268078 | I40: 5607
A41: 41942 | B41: D13520 | C41: CENTRIFUGA REFRIGERADA | D41: CENTRIFUGA REFRIGERADA | E41: HOSPITAL | F41: CRYOFUGE 5500 I | G41: THERMO SCIENTIFIC | H41: 41154063 | I41: 8076
A42: 41942 | B42: D13608 | C42: COLPOSCOPIO | D42: COLPOSCOPIO | E42: HOSPITAL | F42: MTV-73X11HN-COLPO 99 | G42: SOUNVED | H42: CO0502040 | I42: 5868
A43: 41942 | B43: D13609 | C43: COLUMNA CIELITICA FIJA PH-A-4B | D43: COLUMNA CIELITICA FIJA PH-A-4B | E43: HOSPITAL | F43: SIN MODELO | G43: SIN MARCA | H43: SIN SERIE | I43: 0
A44: 41942 | B44: D13610 | C44: COLUMNA CIELITICA FIJA PH-A-4B | D44: COLUMNA CIELITICA FIJA PH-A-4B | E44: HOSPITAL | F44: SIN MODELO | G44: SIN MARCA | H44: SIN SERIE | I44: 0
A45: 41942 | B45: D13615 | C45: CONGELADOR - REFRIGERADOR | D45: CONGELADOR DE 20C | E45: HOSPITAL | F45: CAJN2428Z | G45: MAXILINE | H45: 10234 | I45: 11371
A46: 41942 | B46: D13618 | C46: CONGELADOR ECOFRIAL IBD-120 | D46: PRENSA RAPIDA MANUAL DE 12 " | E46: HOSPITAL | F46: BD-120 | G46: ECOFRIAL | H46: 105058304 | I46: 009990/007078
A47: 41942 | B47: D13694 | C47: DESTRUCTORA DE PAPEL MARTIN | D47: DESTRUCTORA DE PAPEL MARTIN | E47: HOSPITAL | F47: SIN MODELO | G47: SIN MARCA | H47: SIN SERIE | I47: 8059
A48: 41942 | B48: D13698 | C48: DISECCION ADSON CON GARRA | D48: DISECCION ADSON CON GARRA | E48: HOSPITAL | F48: SIN MODELO | G48: SIN MARCA | H48: HIUSJ/07/2014 | I48: 0
A49: 41942 | B49: D13714 | C49: DISECCION ADSON SIN GARRA | D49: DISECCION ADSON SIN GARRA | E49: HOSPITAL | F49: SIN MODELO | G49: SIN MARCA | H49: HIUSJ/07/2014 | I49: 0
A50: 41942 | B50: D13715 | C50: DISECCION ADSON SIN GARRA | D50: DISECCION ADSON SIN GARRA | E50: HOSPITAL | F50: SIN MODELO | G50: SIN MARCA | H50: HIUSJ/07/2014 | I50: 0
A51: 41942 | B51: D13792 | C51: ELECTROBISTURI | D51: GENERADOR DE ELECTROCIRUGÍA | E51: HOSPITAL | F51: FORCE FX | G51: VALEYBALL | H51: F9A63183A | I51: 506
A52: 41942 | B52: D13796 | C52: ELECTROBISTURI | D52: GENERADOR DE ELECTROCIRUGÍA | E52: HOSPITAL | F52: FORCE FX | G52: VALEYBALL | H52: F8L62982A | I52: 482
A53: 41942 | B53: D13801 | C53: ELECTROBISTURI | D53: GENERADOR DE ELECTROCIRUGÍA | E53: FUCS | F53: FORCE LX | G53: VALEYBALL | H53: F7J57229A | I53: 009135/000486
A54: 41942 | B54: D13816 | C54: EQUIPO DE ORGANOS PORTATIL | D54: EQUIPO DE ORGANOS MANUAL | E54: HOSPITAL | F54: 19090 | G54: WELCH ALLYN | H54: SIN SERIE | I54: 12668
A55: 41942 | B55: D13885 | C55: ESPECULA NASAL VIENA PEDIATRIC | D55: ESPECULA NASAL VIENA PEDIATRICO | E55: HOSPITAL | F55: SIN MODELO | G55: SIN MARCA | H55: SIN SERIE | I55: 0
A56: 41942 | B56: D13886 | C56: ESPECULA NASAL VIENA PEDIATRIC | D56: ESPECULA NASAL VIENA PEDIATRICO | E56: HOSPITAL | F56: SIN MODELO | G56: SIN MARCA | H56: SIN SERIE | I56: 0
A57: 41942 | B57: D13887 | C57: ESPECULA NASAL VIENA PEDIATRIC | D57: ESPECULA NASAL VIENA PEDIATRICO | E57: HOSPITAL | F57: SIN MODELO | G57: SIN MARCA | H57: SIN SERIE | I57: 0
A58: 41942 | B58: D13901 | C58: ESPECULO NASAL PEDIATRICO 7966 | D58: ESPECULO NASAL PEDIATRICO | E58: HOSPITAL | F58: SIN MODELO | G58: SIN MARCA | H58: HIUSJ 09/2014 | I58: 0
A59: 41942 | B59: D13902 | C59: ESPECULO NASAL PEDIATRICO 7966 | D59: ESPECULO NASAL PEDIATRICO | E59: HOSPITAL | F59: SIN MODELO | G59: SIN MARCA | H59: HIUSJ 09/2014 | I59: 0
A60: 41942 | B60: D13903 | C60: ESPECULO NASAL PEDIATRICO 7966 | D60: ESPECULO NASAL PEDIATRICO | E60: HOSPITAL | F60: SIN MODELO | G60: SIN MARCA | H60: HIUSJ 09/2014 | I60: 0
A61: 41942 | B61: D13904 | C61: ESPECULO NASAL PEDIATRICO 7966 | D61: ESPECULO NASAL PEDIATRICO | E61: HOSPITAL | F61: SIN MODELO | G61: SIN MARCA | H61: HIUSJ 09/2014 | I61: 0
A62: 41942 | B62: D13905 | C62: ESPECULO NASAL PEDIATRICO 7966 | D62: ESPECULO NASAL PEDIATRICO | E62: HOSPITAL | F62: SIN MODELO | G62: SIN MARCA | H62: HIUSJ 09/2014 | I62: 0
A63: 41942 | B63: D13909 | C63: ESPECULO NASAL VIENA | D63: ESPECULO NASAL VIENA | E63: HOSPITAL | F63: SIN MODELO | G63: SIN MARCA | H63: SIN SERIE | I63: 0
A64: 41942 | B64: D13910 | C64: ESPECULO NASAL VIENA ADULTO | D64: ESPECULO NASAL VIENA ADULTO | E64: HOSPITAL | F64: SIN MODELO | G64: SIN MARCA | H64: HIUSJ 09/2014 | I64: 0
A65: 41942 | B65: D13911 | C65: ESPECULO NASAL VIENA ADULTO | D65: ESPECULO NASAL VIENA ADULTO | E65: HOSPITAL | F65: SIN MODELO | G65: SIN MARCA | H65: HIUSJ 09/2014 | I65: 0
A66: 41942 | B66: D13912 | C66: ESPECULO NASAL VIENA ADULTO | D66: ESPECULO NASAL VIENA ADULTO | E66: HOSPITAL | F66: SIN MODELO | G66: SIN MARCA | H66: HIUSJ 09/2014 | I66: 0
... A159: 41942 | B159: D14168 | C159: FOTOSFORO | D159: FOTOFORO | E159: HOSPITAL | F159: SIN MODELO | G159: WELCH ALLYN | H159: SIN SERIE | I159: 12083
A160: 41942 | B160: D14170 | C160: FOTOSFORO LAMPARA FRONTAL MD 1 | D160: FOTOFORO LAMPARA FRONTAL MD 1000 F.O CO | E160: HOSPITAL | F160: XENON 1000 | G160: HEINE GERMANY | H160: 1260380 | I160: 10024
A161: 41942 | B161: D14173 | C161: FUENTE DE LUZ DYONICS | D161: FUENTE DE LUZ | E161: HOSPITAL | F161: 7206084 | G161: SMITHYNEPHEW | H161: 60848006 | I161: 012520-012977
A162: 41942 | B162: D14207 | C162: GENERADOR MONOPOLAR | D162: GENERADOR MONOPOLAR | E162: HOSPITAL | F162: 300 | G162: LIGASURE | H162: SIN SERIE | I162: 0
A163: 41942 | B163: D14256 | C163: LAMPARA DE CALOR RADIANTE | D163: LAMPARA DE CALOR RADIANTE | E163: HOSPITAL | F163: MU20503-RESUSCITAIRE | G163: DRAGER | H163: HU08586 | I163: 011316/8134
A164: 41942 | B164: D14257 | C164: INCUBADORA NEONATAL TI 500 | D164: INCUBADORA DE TRANSPORTE | E164: HOSPITAL | F164: TI500 | G164: DRAGER | H164: EG08204 | I164: 9322
A165: 41942 | B165: D14263 | C165: PINZA TIPO COCODRILO WA63072A | D165: PINZA TIPO COCODRILO WA63072A | E165: HOSPITAL | F165: SIN MODELO | G165: SIN MARCA | H165: SIN SERIE | I165: 0
A166: 41942 | B166: D14287 | C166: KERATOMETRO MANUAL KR800 | D166: KERATOMETRO MANUAL KR800 | E166: HOSPITAL | F166: SIN MODELO | G166: SIN MARCA | H166: SIN SERIE | I166: 0
A167: 41942 | B167: D14310 | C167: LAMPARA DE CALOR RADIANTE | D167: INCUBADORA ,LAMPARA DE CALOR RADIANTE | E167: HOSPITAL | F167: RESUSSITAIRE | G167: DRAGER | H167: NG06496 | I167: 8124
A168: 41942 | B168: D14316 | C168: LAMPARA PIELITICA | D168: LAMPARA PIELITICA | E168: HOSPITAL | F168: AMAX30FMEL | G168: BRANDON | H168: 3574/1 | I168: 10835
A169: 41942 | B169: D14319 | C169: LAMPARA CIELITICA | D169: LAMPARA PIELITICA | E169: PATRIMONIO AUTONOMO | F169: DOMELUX-6200S | G169: TRIDENT | H169: E031-G1-0002 | I169: 67
A170: 41942 | B170: D14323 | C170: LARINGOSCOPIO 6 HOJAS | D170: LARINGOSCOPIO 6 HOJAS | E170: HOSPITAL | F170: SIN MODELO | G170: SIN MARCA | H170: SIN SERIE | I170: 12078
A171: 41942 | B171: D14327 | C171: LARINGOSCOPIO WELCH ALLYN | D171: LARINGOSCOPIO | E171: HOSPITAL | F171: 60813 | G171: WELCH ALLYN | H171: SIN SERIE | I171: 12075
A172: 41942 | B172: D14328 | C172: LARINGOSCOPIO WELCH ALLYN | D172: LARINGOSCOPIO | E172: HOSPITAL | F172: 60813 | G172: WELCH ALLYN | H172: SIN SERIE | I172: 12077
A173: 41942 | B173: D14330 | C173: LARINGOSCOPIO WELCH ALLYN | D173: LARINGOSCOPIO | E173: HOSPITAL | F173: 60813 | G173: WELCH ALLYN | H173: SIN SERIE | I173: 1002-018146
A174: 41942 | B174: D14334 | C174: LARINGOSCOPIO WELCH ALLYN | D174: LARINGOSCOPIO 5 HOJAS | E174: HOSPITAL | F174: 60813 | G174: WELCH ALLYN | H174: SIN SERIE | I174: 12366
A175: 41942 | B175: D14341 | C175: LARINGOSCOPIO WELCH ALLYN | D175: LARINGOSCOPIO WELCH ALLYN | E175: HOSPITAL | F175: 60813 | G175: WELCH ALLYN | H175: SIN SERIE | I175: 1387
A176: 41942 | B176: D14347 | C176: AGITADOR VORTEX FISHER | D176: AGITADOR VORTEX FISHER | E176: HOSPITAL | F176: 60813 | G176: WELCH ALLYN | H176: 204148 | I176: 5197
A177: 41942 | B177: D14348 | C177: LARINGOSCOPIO WELCH ALLYN | D177: LARINGOSCOPIO WELCH ALLYN | E177: HOSPITAL | F177: 60813 | G177: WELCH ALLYN | H177: SIN SERIE | I177: 16805
A178: 41942 | B178: D14349 | C178: LARINGOSCOPIO WELCH ALLYN | D178: LARINGOSCOPIO 6 HOJAS | E178: HOSPITAL | F178: 60813 | G178: WELCH ALLYN | H178: SIN SERIE | I178: 12367
A179: 41942 | B179: D14350 | C179: LAVAMANOS QUIRURGICO | D179: LAVAMANOS METALICO | E179: HOSPITAL | F179: SIN MODELO | G179: SIN MARCA | H179: SIN SERIE | I179: 11351
A180: 41942 | B180: D14361 | C180: LENSOMETRO | D180: LENSOMETRO | E180: HOSPITAL | F180: LM 190 | G180: LUXVISION | H180: 103774 | I180: 6056
A181: 41942 | B181: D14457 | C181: MANOMETRO PARA NITROGENO CON A | D181: MANOMETRO PARA NITROGENO CON ACCESORIOS | E181: HOSPITAL | F181: SIN MODELO | G181: SIN MARCA | H181: SIN SERIE | I181: 13549
A182: 41942 | B182: D14459 | C182: MAQUINA DE ANESTESIA | D182: MAQUINA DE ANESTISIA | E182: PATRIMONIO AUTONOMO | F182: AS-A5AESPIRE 7100 | G182: DATEX OHMEDA | H182: AMXL01116 | I182: 2780
A183: 41942 | B183: D14461 | C183: MAQUINA DE ANESTESIA | D183: MAQUINA DE ANESTESIA | E183: PATRIMONIO AUTONOMO | F183: AS-A5AESPIRE 7100 | G183: DATEX OHMEDA | H183: AMXL01131 | I183: 009168-000449
A184: 41942 | B184: D14462 | C184: MAQUINA DE ANESTESIA | D184: MAQUINA DE ANESTESIA | E184: HOSPITAL | F184: AVANCECONFIC | G184: GE | H184: ANBR01647 | I184: 10225
A185: 41942 | B185: D14463 | C185: MAQUINA DE ANESTESIA | D185: MAQUINA DE ANESTESIA | E185: PATRIMONIO AUTONOMO | F185: AS-A5AESPIRE 7100 | G185: DATEX OHMEDA | H185: AMXL01136 | I185: 431
A186: 41942 | B186: D14468 | C186: MAQUINA DE ANESTESIA | D186: MAQUINA DE ANESTESIA | E186: PATRIMONIO AUTONOMO | F186: AS-A5AESPIRE 7100 | G186: DATEX OHMEDA | H186: ANCL00664 | I186: 0
A187: 41942 | B187: D14481 | C187: MESA DE AUTOPSIAS | D187: MESA FIJA PARA AUTOPSIAS DE CADAVERES | E187: HOSPITAL | F187: SIN MODELO | G187: SIN MARCA | H187: SIN SERIE | I187: 8634
A188: 41942 | B188: D14482 | C188: MESA DE CIRUGIA | D188: MESA DE CIRUGIA | E188: PATRIMONIO AUTONOMO | F188: 29330TK | G188: TRIDENT | H188: A026-G1-0001 | I188: 1
A189: 41942 | B189: D14490 | C189: MESA DE CIRUGIA | D189: MESA DE CIRUGIA | E189: FUCS | F189: NOVEL 330TK | G189: TRIDENT | H189: A013-G4-0009 | I189: 467
A190: 41942 | B190: D14494 | C190: MESA DE CIRUGIA DE HOMBRO | D190: MESA DE CIRUGIA DE HOMBRO | E190: HOSPITAL | F190: SU-02 | G190: FAMED | H190: 120701253 | I190: 2812
A191: 41942 | B191: D14495 | C191: MESA DE CIRUGIA | D191: MESA DE CIRUGIA | E191: PATRIMONIO AUTONOMO | F191: SU05 | G191: FAMED | H191: 0508/00110 | I191: 2782
A192: 41942 | B192: D14497 | C192: MESA DE EXAMEN GINECO-OBSTETRI | D192: MESA DE EXAMEN GINECO-OBSTETRICA VG-MEDICAL | E192: HOSPITAL | F192: YF-5 | G192: VG-MEDICAL | H192: 101202-004 | I192: 12524
...

Sheet Correctivo menor
A1: BDG-BASTA-00007156 | B1: 3770 | C1: 41942 | D1: 2019-10-02 11:00:00 | E1: 2019-10-02 10:00:00 | F1: -NO_DEFINIDO - Se realiza ajuste de indicador de peso de la báscula que se bloqueaba | G1: Correctivo menor | H1: Bascula Con Tallimetro | I1: 19426 | J1: 10000001187681 | K1: 6 | L1: 1 | M1: 1798.4583 | N1: 0.0033361907 | O1: 299.74306 | P1: 0.0033361907 | Q1: 0.1814096 | R1: 0.70409287 | S1: #N/A
A2: BMO-TRMOH-00014894 | B2: 3074.5 | C2: 41942 | D2: 2020-03-25 10:30:00 | E2: 2020-02-25 10:00:00 | F2: -NO_DEFINIDO - CREADA DESDE AMsi&#x0D; Reclasificada desde la compañía 8 por el usuario JBARRERA&#x0D; &#x0D; Se realiza revisión del termohigrometro, se ajusta batería y queda funcionando correctamente. | G2: Correctivo menor | H2: Termohigrometro Digital | I2: 14894 | J2: N/A | K2: 2 | L2: 696.5 | M2: 1973.4375 | N2: 0.00101346 | O2: 986.71875 | P2: 0.00101346 | Q2: 0.058995729 | R2: 0.30569616 | S2: #N/A
A3: BAN-LARIN-00000768 | B3: 3770.5833 | C3: 41942 | D3: 2021-05-21 07:15:00 | E3: 2021-05-21 06:50:00 | F3: -NO_DEFINIDO - CREADA DESDE AMsi&#x0D; Reclasificada desde la compañía 8 por el usuario JBARRERA&#x0D; &#x0D; Se realiza revisión general del equipo, se evidencia socket sucio y desajustado, se realiza el ajuste necesario y pruebas de funcionamiento satisfactorias. Equipo operativo en el servicio | G3: Correctivo menor | H3: Laringoscopio | I3: 768 | J3: N/A | K3: 3 | L3: 0.41666667 | M3: 2395.3021 | N3: 0.0012524516 | O3: 798.43403 | P3: 0.0012524516 | Q3: 0.072392973 | R3: 0.36293436 | S3: #N/A
A4: BMO-TRMOH-00014607 | B4: 1011.6667 | C4: 41942 | D4: 2022-05-20 09:30:00 | E4: 2022-05-20 08:00:00 | F4: 18/05/2022-NO_DEFINIDO - Solicitud de Servico Creada desde AMSi, 03/06/2022-Novatecnica - Se realiza ajuste de carcasa de termohigrómetro, se realiza pruebas y equipo queda funcionando correctamente, se realiza instalación del termohigrómetro y se entrega al servicio en buenas condiciones. se recomienda al personal el cuidado de estos equipos. | G4: Correctivo menor | H4: Termometro Digital | I4: 14607 | J4: N/A | K4: 3 | L4: 1.5 | M4: 2759.3958 | N4: 0.0010871945 | O4: 919.79861 | P4: 0.0010871945 | Q4: 0.063149602 | R4: 0.3238836 | S4: #N/A
A5: OTP-CAMIL-00007665 | B5: 970.70833 | C5: 41942 | D5: 2022-06-30 08:00:00 | E5: 2022-06-30 07:00:00 | F5: 28/06/2022-NO_DEFINIDO - Solicitud de Servico Creada desde AMSi, 01/07/2022-Senior - Se realiza la Verificación de funcionamiento, encontrando baranda con seguros desajustados , se procede a realizar el ajuste mécanico pertinente, pruebas de funcionamiento OK. Se adjunta reporte de servicio. | G5: Correctivo menor | H5: Camilla De Transporte | I5: 7665/9976 | J5: N/A | K5: 3 | L5: 1 | M5: 2800.3333 | N5: 0.001071301 | O5: 933.44444 | P5: 0.001071301 | Q5: 0.062255788 | R5: 0.32000401 | S5: #N/A
A6: OTP-CAMIL-00000271 | B6: 935.57361 | C6: 41942 | D6: 2022-08-04 14:00:00 | E6: 2022-08-04 10:14:00 | F6: 01/08/2022-NO_DEFINIDO - Solicitud de Servico Creada desde AMSi, 09/08/2022-Senior - Se realiza inspección de la cama encontrando la baranda sin tornilleria de ajsute, se procede con la instalación de tornillos nuevos. Se realizan pruebas y funciona ok. Se adjunta reporte de servicio. | G6: Correctivo menor | H6: Camilla De Transporte | I6: 271 | J6: N/A | K6: 2 | L6: 3.7666667 | M6: 2835.5833 | N6: 0.00070532224 | O6: 1417.7917 | P6: 0.00070532224 | Q6: 0.041436371 | R6: 0.22424304 | S6: #N/A
A7: BDG-TENAT-00012861 | B7: 931.3625 | C7: 41942 | D7: 2022-08-09 09:25:00 | E7: 2022-08-08 15:18:00 | F7: 07/08/2022-NO_DEFINIDO - Solicitud de Servico Creada desde AMSi, 08/08/2022-Biomedico1 - Se retira tensiometro el cual se encuentra roto servicio informa que el equipo fu entragado roto, 09/08/2022-Biomedico1 - Se realiza ajuste de tensiometro con pegamento se realizan pruebas de funcionamiento equipo funciona correctamente se recomienda al servicio tener precaucion a la hora de manejar los equipos biomedicos | G7: Correctivo menor | H7: Tensiometro De Atril | I7: 12861 | J7: N/A | K7: 4 | L7: 18.116667 | M7: 2840.3924 | N7: 0.0014082561 | O7: 710.09809 | P7: 0.0014082561 | Q7: 0.081024089 | R7: 0.39768349 | S7: #N/A
A8: BFE-FOTOF-00016943 | B8: 903.70417 | C8: 41942 | D8: 2022-09-05 09:00:00 | E8: 2022-09-05 07:06:00 | F8: 03/09/2022-NO_DEFINIDO - Solicitud de Servico Creada desde AMSi, 05/10/2022-Senior - Se realiza ajuste de soporte ya que se encontró fracturado. OBS. El equipo ya previamente había sido reparado | G8: Correctivo menor | H8: Fotoforo | I8: 16943 | J8: N/A | K8: 2 | L8: 1.9 | M8: 2867.375 | N8: 0.00069750207 | O8: 1433.6875 | P8: 0.00069750207 | Q8: 0.040986497 | R8: 0.22205601 | S8: #N/A
A9: OTP-CAMIL-00015639 | B9: 721.61806 | C9: 41942 | D9: 2023-03-06 09:40:00 | E9: 2023-03-06 09:10:00 | F9: 14/02/2023-NO_DEFINIDO - Solicitud de Servico Creada desde AMSi, 06/03/2023-Senior - Se retira camilla, para realizar ajuste de baranda | G9: Correctivo menor | H9: Camilla De Transporte | I9: 15639 | J9: N/A | K9: 5 | L9: 0.5 | M9: 3049.4028 | N9: 0.0016396653 | O9: 609.88056 | P9: 0.0016396653 | Q9: 0.093695484 | R9: 0.44582764 | S9: #N/A
A10: BDG-TERMO-00014954 | B10: 738.66944 | C10: 41942 | D10: 2023-02-17 08:05:00 | E10: 2023-02-17 07:56:00 | F10: 15/02/2023-NO_DEFINIDO - Solicitud de Servico Creada desde AMSi, 23/02/2023-Biomedico1 - Se realiza ajuste de termómetro y se deja nuevamente en la sala 1 | G10: correctivo menor | H10: Termohigrometro Digital | I10: 14954 | J10: N/A | K10: 1 | L10: 0.15 | M10: 3032.3368 | N10: 0.00032977867 | O10: 3032.3368 | P10: 0.00032977867 | Q10: 0.019592248 | R10: 0.11194386 | S10: #N/A
A11: BDG-BASME-00007880 | B11: 735.375 | C11: 41942 | D11: 2023-02-20 15:45:00 | E11: 2023-02-20 15:00:00 | F11: 20/02/2023-NO_DEFINIDO - Solicitud de Servico Creada desde AMSi, 22/02/2023-Biomedico2 - Se realiza verificación de bascula con masas patron y se evidencia desajuste en mediciones,se retira y se reporta por garantía | G11: correctivo menor | H11: Bascula Mecanica | I11: 7880 | J11: N/A | K11: 4 | L11: 0.75 | M11: 3035.6562 | N11: 0.0013176722 | O11: 758.91406 | P11: 0.0013176722 | Q11: 0.076015826 | R11: 0.37771806 | S11: #N/A
A12: BDG-TERMO-00014955 | B12: 704.49931 | C12: 41942 | D12: 2023-03-23 12:05:00 | E12: 2023-03-23 12:01:00 | F12: 22/03/2023-NO_DEFINIDO - Solicitud de Servico Creada desde AMSi, 30/03/2023-Biomedico1 - Re realiza inspección de termohigometro sala de cirugía se realiza ajuste de sonda de temperatura equipo funciona correctamente | G12: correctivo menor | H12: Termohigrometro Digital | I12: 14955 | J12: N/A | K12: 1 | L12: 0.066666667 | M12: 3066.5035 | N12: 0.00032610431 | O12: 3066.5035 | P12: 0.00032610431 | Q12: 0.019376082 | R12: 0.11076839 | S12: #N/A
A13: BDG-BASTA-00005941 | B13: 458.41667 | C13: 41942 | D13: 2023-11-24 16:00:00 | E13: 2023-11-24 14:00:00 | F13: 23/11/2023-NO_DEFINIDO - Solicitud de Servico Creada desde AMSi, 05/12/2023-Senior - Se realiza ajuste en tallímetro, reforzando los remache que sostiene la estructura | G13: Correctivo menor | H13: Bascula Con Tallimetro | I13: 5941 | J13: N/A | K13: 5 | L13: 2 | M13: 3312.6667 | N13: 0.001509358 | O13: 662.53333 | P13: 0.001509358 | Q13: 0.086581826 | R13: 0.41921166 | S13: #N/A
A14: BDG-EQUIO-00018895 | B14: 329.61597 | C14: 41942 | D14: 2024-04-01 09:39:00 | E14: 2024-04-01 09:13:00 | F14: 26/03/2024-NO_DEFINIDO - Solicitud de Servico Creada desde AMSi, 01/04/2024-Biomedico1 - Se realiza ajuste se cono se realizan pruebas equipo funciona correctamente | G14: Correctivo menor | H14: Equipo De Organos Portatil | I14: 18895/18896 | J14: N/A | K14: 2 | L14: 0.43333333 | M14: 3441.4021 | N14: 0.00058115848 | O14: 1720.701 | P14: 0.00058115848 | Q14: 0.034268572 | R14: 0.18878086 | S14: 400000
A15: BDG-EQUIO-00014198 | B15: 145.65903 | C15: 41942 | D15: 2024-10-02 08:35:00 | E15: 2024-10-02 08:11:00 | F15: 19/09/2024-NO_DEFINIDO - Solicitud de Servico Creada desde AMSi, 02/10/2024-Biomedico1 - Se realiza ajuste de equipo de organos a la pared ya que se encontró en riesgo de caer al piso se ajusta se realizan pruebas de funcionamiento | G15: Correctivo menor | H15: Equipo De Organos Portatil | I15: 14198 | J15: N/A | K15: 1 | L15: 0.4 | M15: 3625.3576 | N15: 0.00027583486 | O15: 3625.3576 | P15: 0.00027583486 | Q15: 0.016413891 | R15: 0.09452947 | S15: #N/A
A16: BDG-EQUIO-00018895 | B16: 147.62639 | C16: 41942 | D16: 2024-09-30 09:55:00 | E16: 2024-09-30 08:58:00 | F16: 25/09/2024-NO_DEFINIDO - Solicitud de Servico Creada desde AMSi, 30/09/2024-Biomedico1 - Se realiza ajuste de cabezal de otoscopio ya que al hacer el anclaje con el mango no enciende se ajusta se realizan pruebas equipo funcionando correctamente | G16: Correctivo menor | H16: Equipo De Organos Portatil | I16: 18895/18896 | J16: N/A | K16: 2 | L16: 0.95 | M16: 3623.4132 | N16: 0.00055196576 | O16: 1811.7066 | P16: 0.00055196576 | Q16: 0.03257555 | R16: 0.18021049 | S16: 400000
A17: BFE-LAMAU-00000237 | B17: 1538.375 | C17: 41942 | D17: 2020-12-09 15:20:00 | E17: 2020-12-09 15:00:00 | F17: -NO_DEFINIDO - Se realiza revisión física y funcional de lámpara cuello de cisne, se encuentra cable suelto, se realiza ajuste del mismo y pruebas funcionales satisfactorias. | G17: Correctivo menor | H17: Lampara Auxiliar De Procedimientos | I17: 237/14680 | J17: N/A | K17: 2 | L17: 0.33333333 | M17: 2232.6389 | N17: 0.00089580093 | O17: 1116.3194 | P17: 0.00089580093 | Q17: 0.052329164 | R17: 0.27565562 | S17: 600000
A18: BDG-TENAT-00012865 | B18: 174.68611 | C18: 41942 | D18: 2024-09-03 11:33:00 | E18: 2024-09-03 07:32:00 | F18: 21/08/2024-NO_DEFINIDO - Solicitud de Servico Creada desde AMSi, 03/09/2024-Biomedico1 - Se realiza pegado de base de tensiómetro ya que se encontró roto se deja secar por un tiepo prolongado se realiza ajuste y adecuacion de tensiómetro se realiza entrga al servicio para su respectiva limpieza y desinfección | G18: Correctivo menor | H18: Tensiometro De Atril | I18: 12865 | J18: N/A | K18: 4 | L18: 4.0166667 | M18: 3596.4812 | N18: 0.0011121982 | O18: 899.12031 | P18: 0.0011121982 | Q18: 0.064554032 | R18: 0.32994224 | S18: #N/A
A19: BAN-LARIN-00015725 | B19: 1418.5625 | C19: 41942 | D19: 2021-04-08 10:55:00 | E19: 2021-04-08 10:30:00 | F19: -NO_DEFINIDO - Se realiza revisión general del equipo, se evidencia socket con suciedad y desajustado. &#x0D; Se realiza limpieza y ajuste de bombilla, equipo operativo en el servicio. | G19: Correctivo menor | H19: Laringoscopio | I19: 15725 | J19: N/A | K19: 2 | L19: 0.41666667 | M19: 2352.4549 | N19: 0.00085017572 | O19: 1176.2274 | P19: 0.00085017572 | Q19: 0.049731348 | R19: 0.26365996 | S19: #N/A
A20: BFE-FOTOF-00015060 | B20: 1411.6458 | C20: 41942 | D20: 44301.368 | E20: 2021-04-15 08:30:00 | F20: -NO_DEFINIDO - Se realiza ajuste de cable de fotóforo ya que presentaba interferencia. &#x0D; se realizan pruebas de funcionamiento satisfactorias. &#x0D; Equipo operativo en el servicio | G20: Correctivo menor | H20: Fotoforo | I20: 15060 | J20: N/A | K20: 3 | L20: 0.33333333 | M20: 2359.3681 | N20: 0.0012715269 | O20: 786.45602 | P20: 0.0012715269 | Q20: 0.073454028 | R20: 0.36729417 | S20: #N/A
A21: BFE-FOTOF-00018993 | B21: 24.368056 | C21: 41942 | D21: 2025-01-31 15:30:00 | E21: 2025-01-31 15:10:00 | F21: 08/11/2024-NO_DEFINIDO - Solicitud de Servico Creada desde AMSi, 30/01/2025-Biomedico1 - Se realiza verificación del adaptador de carga del equipo se evidencia que el cargador se encuentra en falla se instala un cargador de backup se realizan pruebas de funcionamiento equipo funcionando correctamente | G21: Correctivo menor | H21: Fotoforo | I21: 18993 | J21: N/A | K21: 1 | L21: 0.33333333 | M21: 3746.6458 | N21: 0.0002669054 | O21: 3746.6458 | P21: 0.0002669054 | Q21: 0.015886776 | R21: 0.091614057 | S21: #N/A
A22: BFT-ELIPT-00015248 | B22: 1957.4167 | C22: 41942 | D22: 2019-10-17 15:00:00 | E22: 2019-10-17 14:00:00 | F22: -NO_DEFINIDO - Se realiza inspección física inicial, verificación de encendido, puesta en marcha en modos de trabajo, inclinación y velocidad, limpieza general externa de display,labels de acción, chasis del equipo, se realiza lubricación de la banda y verificación de voltaje. Equipo funciona correctamente. | G22: Correctivo menor | H22: Eliptica | I22: 15248 | J22: N/A | K22: 8 | L22: 1 | M22: 1813.625 | N22: 0.0044110552 | O22: 226.70312 | P22: 0.0044110552 | Q22: 0.2325357 | R22: 0.79566202 | S22: #N/A
A23: BDG-BASTA-00007156 | B23: 1972.6458 | C23: 41942 | D23: 2019-10-02 08:30:00 | E23: 2019-10-02 08:30:00 | F23: -NO_DEFINIDO - OT generada automáticamente por la solicitud No. 16143&#x0D; &#x0D; Diagnóstico S.S: Indicador de báscula presenta falla y no funciona.&#x0D; &#x0D; Comentario S.S:Se realiza ajuste de indicador de peso de la báscula que se bloqueaba | G23: Correctivo menor | H23: Bascula Con Tallimetro | I23: 19426 | J23: 10000001187681 | K23: 6 | L23: 0 | M23: 1798.4583 | N23: 0.0033361907 | O23: 299.74306 | P23: 0.0033361907 | Q23: 0.1814096 | R23: 0.69911545 | S23: #N/A
A24: BMO-TRMOH-00014155 | B24: 1967.4583 | C24: 41942 | D24: 2019-10-07 13:30:00 | E24: 2019-10-07 13:00:00 | F24: -NO_DEFINIDO - Se realiza revisión de termohigrometro, se ajusta y se realiza limpieza general. Equipo funciona correctamente. | G24: Correctivo menor | H24: Termohigrometro Digital | I24: 14155 | J24: N/A | K24: 3 | L24: 0.5 | M24: 1803.5625 | N24: 0.0016633746 | O24: 601.1875 | P24: 0.0016633746 | Q24: 0.094983836 | R24: 0.45053755 | S24: #N/A
A25: BMO-TRMOH-00014155 | B25: 1965.6458 | C25: 41942 | D25: 2019-10-09 09:00:00 | E25: 2019-10-09 08:30:00 | F25: -NO_DEFINIDO - Se realiza revisión de remohigrometro el cuál está funcionando correctamente, se realiza ajuste de temperatura programada en la nevera. Equipo funcional. | G25: Correctivo menor | H25: Termohigrometro Digital | I25: 14155 | J25: N/A | K25: 3 | L25: 0.5 | M25: 1805.375 | N25: 0.0016617046 | O25: 601.79167 | P25: 0.0016617046 | Q25: 0.094893152 | R25: 0.45020713 | S25: #N/A
A26: BMO-TRMOH-00014157 | B26: 1944.4792 | C26: 41942 | D26: 2019-10-30 13:00:00 | E26: 2019-10-30 12:30:00 | F26: -NO_DEFINIDO - El termohrigrometro evidencia daño en el display por caída, se encuentra una parte de la pantalla rota, se repara y equipo queda funcional. | G26: Correctivo menor | H26: Termohigrometro Digital | I26: 14157 | J26: N/A | K26: 2 | L26: 0.5 | M26: 1826.5417 | N26: 0.0010949654 | O26: 913.27083 | P26: 0.0010949654 | Q26: 0.063586313 | R26: 0.32577241 | S26: #N/A
A27: BMO-TRMOH-00014157 | B27: 1967.6667 | C27: 41942 | D27: 2019-10-07 08:30:00 | E27: 2019-10-07 08:00:00 | F27: -NO_DEFINIDO - Se realiza revisión de termohigrometro se realizan pruebas, equipo patrón: 4.3°C; Equipo: 4.3°C. Equipo funciona correctamente. | G27: Correctivo menor | H27: Termohigrometro Digital | I27: 14157 | J27: N/A | K27: 2 | L27: 0.5 | M27: 1803.3542 | N27: 0.0011090445 | O27: 901.67708 | P27: 0.0011090445 | Q27: 0.064377007 | R27: 0.32918106 | S27: #N/A
A28: BFT-BANTR-00015249 | B28: 1930.5729 | C28: 41942 | D28: 2019-11-14 07:00:00 | E28: 2019-11-13 10:15:00 | F28: -NO_DEFINIDO - Se realiza cambio de interruptor de encendido por daño. Equipo queda funcionando correctamente. | G28: Correctivo menor | H28: Banda Trotadora | I28: 15249 | J28: N/A | K28: 3 | L28: 20.75 | M28: 1841.2917 | N28: 0.001629291 | O28: 613.76389 | P28: 0.001629291 | Q28: 0.093131173 | R28: 0.44375408 | S28: #N/A
A29: BFT-BANTR-00015250 | B29: 1917.6667 | C29: 41942 | D29: 2019-11-26 08:45:00 | E29: 2019-11-26 08:00:00 | F29: -NO_DEFINIDO - Se realiza cambio de interruptor de encendido por daño. Equipo se realizan pruebas y queda funcionando correctamente. | G29: Correctivo menor | H29: Banda Trotadora | I29: 15250 | J29: N/A | K29: 4 | L29: 0.75 | M29: 1853.3646 | N29: 0.002158237 | O29: 463.34115 | P29: 0.002158237 | Q29: 0.12146033 | R29: 0.54020076 | S29: #N/A
A30: BFT-BANTR-00015250 | B30: 1917.5 | C30: 41942 | D30: 2019-11-26 12:45:00 | E30: 2019-11-26 12:00:00 | F30: -NO_DEFINIDO - Se realiza ajuste de banda y lubricación de partes moviles. Equipo funcionando correctamente. | G30: Correctivo menor | H30: Banda Trotadora | I30: 15250 | J30: N/A | K30: 4 | L30: 0.75 | M30: 1853.5312 | N30: 0.0021580429 | O30: 463.38281 | P30: 0.0021580429 | Q30: 0.1214501 | R30: 0.54016863 | S30: #N/A
A31: BDG-TENAT-00012859 | B31: 1928.625 | C31: 41942 | D31: 2019-11-15 10:00:00 | E31: 2019-11-15 09:00:00 | F31: -NO_DEFINIDO - Se realiza revisión de microscopio el cuál se encontraba opaco. Equipo funciona correctamente. | G31: Correctivo menor | H31: Tensiometro De Atril | I31: 12859 | J31: N/A | K31: 4 | L31: 1 | M31: 1842.4167 | N31: 0.0021710616 | O31: 460.60417 | P31: 0.0021710616 | Q31: 0.12213609 | R31: 0.54231869 | S31: #N/A
A32: BQX-SICOR-00007836 | B32: 1804.5417 | C32: 41942 | D32: 2020-03-18 11:45:00 | E32: 2020-03-18 11:00:00 | F32: -NO_DEFINIDO - Se realiza revisión de la sierra, presentaba daño en switch interruptor, se corrige y queda funcionando correctamente. | G32: Correctivo menor | H32: Sierra Corta Yesos | I32: 7836 | J32: N/A | K32: 3 | L32: 0.75 | M32: 1966.4896 | N32: 0.0015255611 | O32: 655.49653 | P32: 0.0015255611 | Q32: 0.087469405 | R32: 0.4225896 | S32: #N/A
A33: BAN-LARIN-00013553 | B33: 1788.6667 | C33: 41942 | D33: 2020-04-03 08:30:00 | E33: 2020-04-03 08:00:00 | F33: -NO_DEFINIDO - Se realiza verificación de laringoscopio, limpieza y ajuste de resorte de contacto. Equipo funciona correctamente. | G33: Correctivo menor | H33: Laringoscopio | I33: 13553 | J33: N/A | K33: 1 | L33: 0.5 | M33: 1982.3542 | N33: 0.00050445073 | O33: 1982.3542 | P33: 0.00050445073 | Q33: 0.029813583 | R33: 0.16606704 | S33: #N/A
A34: BFE-CARTR-00000000 | B34: 1789.6667 | C34: 41578 | D34: 2020-04-02 16:00:00 | E34: 2020-04-02 08:00:00 | F34: -NO_DEFINIDO - Se realiza revisión del carro donde se evidencia que se rompió una rueda, se retiro de la torre al taller de ingeniería para reparación.&#x0D; &#x0D; Se realiza ajuste de rueda, se ajusta rueda en la torre, adicionalmente se ajusta soporte del cilindro, se realiza lubricación y se realiza ajuste de soportes de la base. Carro de transporte queda funcionando correctamente | G34: Correctivo menor | H34: Carro de Trasporte (Torre Artroscopia) | J34: N/A | K34: 1 | L34: 8 | M34: 2345.6667 | N34: 0.00042631803 | O34: 2345.6667 | P34: 0.00042631803 | Q34: 0.025254709 | R34: 0.14227736 | S34: #N/A
A35: BAN-LARIN-00013668 | B35: 1768.7083 | C35: 41942 | D35: 2020-04-23 07:30:00 | E35: 2020-04-23 07:00:00 | F35: -NO_DEFINIDO - Se verifica laringoscopio, se hace limpieza de socket y equipo queda funcionando correctamente. | G35: Correctivo menor | H35: Laringoscopio | I35: 13668 | J35: N/A | K35: 3 | L35: 0.5 | M35: 2002.3125 | N35: 0.0014982676 | O35: 667.4375 | P35: 0.0014982676 | Q35: 0.085973814 | R35: 0.4168882 | S35: #N/A
A36: BDG-EQUIO-00013803 | B36: 1748.6667 | C36: 41942 | D36: 2020-05-13 08:30:00 | E36: 2020-05-13 08:00:00 | F36: -NO_DEFINIDO - Se realiza revisión Eequipo, Se realiza el ajuste y equipo queda funcionando correctamente. | G36: Correctivo menor | H36: Equipo Organos De Los Sentidos | I36: 13803 | J36: N/A | K36: 5 | L36: 0.5 | M36: 2022.3542 | N36: 0.0024723662 | O36: 404.47083 | P36: 0.0024723662 | Q36: 0.13786376 | R36: 0.58936553 | S36: #N/A
A37: BFE-FOTOF-00015060 | B37: 1743.5 | C37: 41942 | D37: 2020-05-18 12:20:00 | E37: 2020-05-18 12:00:00 | F37: -NO_DEFINIDO - Se realiza entrega de fotóforo. Equipo funciona correctamente. | G37: Correctivo menor | H37: Fotoforo | I37: 15060 | J37: N/A | K37: 3 | L37: 0.33333333 | M37: 2027.5139 | N37: 0.0014796446 | O37: 675.83796 | P37: 0.0014796446 | Q37: 0.084951927 | R37: 0.41296572 | S37: #N/A
A38: BDG-EQUIO-00013153 | B38: 1706.4792 | C38: 41942 | D38: 2020-06-24 12:40:00 | E38: 2020-06-24 12:30:00 | F38: -NO_DEFINIDO - Se realiza limpieza, ajuste del equipo y adicionalmente se capacita al servicio acerca del manejo del equipo. Equipo funciona correctamente. | G38: Correctivo menor | H38: Equipo Organos De Los Sentidos | I38: 13153 | J38: N/A | K38: 9 | L38: 0.16666667 | M38: 2064.5278 | N38: 0.0043593504 | O38: 229.39198 | P38: 0.0043593504 | Q38: 0.23015111 | R38: 0.79182291 | S38: #N/A
A39: BDG-EQUIO-00012668 | B39: 1699.6667 | C39: 41942 | D39: 2020-07-01 08:20:00 | E39: 2020-07-01 08:00:00 | F39: -NO_DEFINIDO - Se realiza cambio de rueda del selector de posiciones de luz. Equipo funciona correctamente. | G39: Correctivo menor | H39: Equipo De Organos Portatil | I39: 12668 | J39: N/A | K39: 6 | L39: 0.33333333 | M39: 2071.3472 | N39: 0.0028966655 | O39: 345.22454 | P39: 0.0028966655 | Q39: 0.15953497 | R39: 0.64753346 | S39: #N/A
A40: BAN-LARIN-00013668 | B40: 1691.7083 | C40: 41942 | D40: 2020-07-09 07:30:00 | E40: 2020-07-09 07:00:00 | F40: -NO_DEFINIDO - Se realiza limpieza de laringoscopio ya que no encendía. Equipo se prueba y queda funcionando correctamente | G40: Correctivo menor | H40: Laringoscopio | I40: 13668 | J40: N/A | K40: 3 | L40: 0.5 | M40: 2079.3125 | N40: 0.0014427846 | O40: 693.10417 | P40: 0.0014427846 | Q40: 0.082925966 | R40: 0.40512409 | S40: #N/A
A41: BDG-TENAT-00012867 | B41: 1693.3576 | C41: 41942 | D41: 2020-07-07 15:45:00 | E41: 2020-07-07 15:25:00 | F41: -NO_DEFINIDO - Se realiza entrega de tensiómetro funcionando y en correcto estado | G41: Correctivo menor | H41: Tensiometro De Atril | I41: 12867 | J41: N/A | K41: 4 | L41: 0.33333333 | M41: 2077.6562 | N41: 0.0019252463 | O41: 519.41406 | P41: 0.0019252463 | Q41: 0.10909259 | R41: 0.49997074 | S41: #N/A
A42: BEF-NEVER-00012925 | B42: 1641.4167 | C42: 41942 | D42: 2020-08-28 14:50:00 | E42: 2020-08-28 14:00:00 | F42: -NO_DEFINIDO - Se realiza Revisión general del equipo, se realiza limpieza general del equipo, se realiza limpieza de la unidad, se realizan pruebas de funcionamiento, se entrega equipo al servicio para su respectiva desinfección y en funcionamiento sin novedad | G42: Correctivo menor | H42: Nevera | I42: 12925 | J42: N/A | K42: 7 | L42: 0.83333333 | M42: 2129.6181 | N42: 0.0032869744 | O42: 304.23115 | P42: 0.0032869744 | Q42: 0.17898875 | R42: 0.69373691 | S42: #N/A
A43: BFT-ELIPT-00015248 | B43: 1824.3194 | C43: 41942 | D43: 2020-02-27 16:40:00 | E43: 2020-02-27 16:20:00 | F43: -NO_DEFINIDO - Se realiza revisión general, verificación física y funcional. &#x0D; Equipo funcional. | G43: Correctivo menor | H43: Eliptica | I43: 15248 | J43: N/A | K43: 8 | L43: 0.33333333 | M43: 1946.6944 | N43: 0.0041095304 | O43: 243.33681 | P43: 0.0041095304 | Q43: 0.21852477 | R43: 0.77223274 | S43: #N/A
A44: BFE-FOTOF-00015060 | B44: 1608.5833 | C44: 41942 | D44: 2020-09-30 10:38:00 | E44: 2020-09-30 10:00:00 | F44: -NO_DEFINIDO - Equipo se evidencia roto&#x0D; se realiza revisión de equipo encontrando daño en el brazo lo cual ocasiono exposición de cables se ajusta parte rota se verifica adaptador de AC equipo funcional. | G44: Correctivo menor | H44: Fotoforo | I44: 15060 | J44: N/A | K44: 3 | L44: 0.63333333 | M44: 2162.4431 | N44: 0.0013873198 | O44: 720.81435 | P44: 0.0013873198 | Q44: 0.079868962 | R44: 0.39312662 | S44: #N/A
A45: BDG-BASTA-00005941 | B45: 1417.7292 | C45: 41942 | D45: 2021-04-09 06:58:00 | E45: 2021-04-09 06:30:00 | F45: -NO_DEFINIDO - Se realiza revisión general del equipo, se evidencia resorte interno desajustado. &#x0D; Se realiza ajuste interno y pruebas de funcionamiento satisfactorias. &#x0D; Equipo operativo en el servicio | G45: Correctivo menor | H45: Bascula Con Tallimetro | I45: 5941 | J45: N/A | K45: 5 | L45: 0.46666667 | M45: 2353.2903 | N45: 0.0021246848 | O45: 470.65806 | P45: 0.0021246848 | Q45: 0.11968993 | R45: 0.53461326 | S45: #N/A
A46: OTP-CAMIL-00008925 | B46: 1714.5417 | C46: 41942 | D46: 2020-06-16 12:00:00 | E46: 2020-06-16 11:00:00 | F46: -NO_DEFINIDO - Se realiza reparación, fabricación de puntas de anclaje de baranda derecha, se realiza instalación, ajuste y lubricación de baranda derecha, pruebas de funcionamiento satisfactorias. &#x0D; Se entrega al servicio para su respectiva desinfección, se adjunta reporte de servicio | G46: Correctivo menor | H46: Camilla De Transporte | I46: 8925 | J46: N/A | K46: 2 | L46: 1 | M46: 2056.5 | N46: 0.00097252614 | O46: 1028.25 | P46: 0.00097252614 | Q46: 0.056681752 | R46: 0.29538901 | S46: #N/A
... A79: BDG-EQUIO-00015284 | B79: 1581.6667 | C79: 41942 | D79: 2020-10-27 08:30:00 | E79: 2020-10-27 08:00:00 | F79: -NO_DEFINIDO - Se realiza revisión general del equipo, se realiza limpieza, se realizan pruebas de funcionamiento y se entrega al servicio para su respectiva desinfección. Equipo funciona correctamente.&#x0D; &#x0D; Se adjunta reporte de mantenimiento. | G79: Correctivo menor | H79: Equipo Organos De Los Sentidos | I79: 15284 | J79: N/A | K79: 2 | L79: 0.5 | M79: 2189.3542 | N79: 0.0009135114 | O79: 1094.6771 | P79: 0.0009135114 | Q79: 0.053335651 | R79: 0.28025918 | S79: #N/A
A80: BEF-NEVER-00012925 | B80: 1832.5417 | C80: 41942 | D80: 2020-02-19 12:00:00 | E80: 2020-02-19 11:00:00 | G80: Correctivo menor | H80: Nevera | I80: 12925 | J80: N/A | K80: 7 | L80: 1 | M80: 1938.5 | N80: 0.0036110395 | O80: 276.92857 | P80: 0.0036110395 | Q80: 0.19479821 | R80: 0.72746118 | S80: #N/A
A81: BDG-EQUIO-00006131 | B81: 1265.5417 | C81: 41942 | D81: 2021-09-08 11:30:00 | E81: 2021-09-08 11:00:00 | F81: -NO_DEFINIDO - Se realiza ajuste de mango de otoscopio ya que tenia los cables pelados se recubre con cinta fundente. Equipo ok | G81: Correctivo menor | H81: Equipo Organos De Los Sentidos | I81: 6131 | J81: N/A | K81: 5 | L81: 0.5 | M81: 2505.4792 | N81: 0.0019956263 | O81: 501.09583 | P81: 0.0019956263 | Q81: 0.11284678 | R81: 0.51248073 | S81: #N/A
A82: BAN-LARIN-00000768 | B82: 1265.6806 | C82: 41942 | D82: 2021-09-08 08:00:00 | E82: 2021-09-08 07:40:00 | F82: -NO_DEFINIDO - Se realiza limpieza y ajuste de socket de laringoscopio el cual no enciende, se deja sin novedad | G82: Correctivo menor | H82: Laringoscopio | I82: 768 | J82: N/A | K82: 3 | L82: 0.33333333 | M82: 2505.3333 | N82: 0.0011974454 | O82: 835.11111 | P82: 0.0011974454 | Q82: 0.069326468 | R82: 0.35019331 | S82: #N/A
A83: BDG-BASTA-00005941 | B83: 1559.4028 | C83: 41942 | D83: 2020-11-18 15:10:00 | E83: 2020-11-18 14:20:00 | F83: -NO_DEFINIDO - Se realiza revisión general del equipo, se realiza limpieza, se realizan pruebas de funcionamiento, se realiza verificación de parámetro por comparación y se entrega al servicio para su respectiva desinfección. Equipo funciona correctamente.&#x0D; &#x0D; Se adjunta reporte de mantenimiento. | G83: Correctivo menor | H83: Bascula Con Tallimetro | I83: 5941 | J83: N/A | K83: 5 | L83: 0.83333333 | M83: 2211.6319 | N83: 0.002260774 | O83: 442.32639 | P83: 0.002260774 | Q83: 0.12684871 | R83: 0.55686404 | S83: #N/A
A84: BDG-BASTA-00006111 | B84: 1559.6111 | C84: 41942 | D84: 2020-11-18 10:10:00 | E84: 2020-11-18 09:20:00 | F84: -NO_DEFINIDO - Se realiza revisión general del equipo, se realiza limpieza, se realizan pruebas de funcionamiento, se realiza verificación de parámetro por comparación y se entrega al servicio para su respectiva desinfección. Equipo funciona correctamente.&#x0D; &#x0D; Se adjunta reporte de mantenimiento. | G84: Correctivo menor | H84: Bascula Con Tallimetro | I84: 6111/12760 | J84: N/A | K84: 3 | L84: 0.83333333 | M84: 2211.4236 | N84: 0.0013565922 | O84: 737.1412 | P84: 0.0013565922 | Q84: 0.078170993 | R84: 0.38637617 | S84: 600000
A85: BDG-BASTA-00006143 | B85: 1559.4861 | C85: 41942 | D85: 2020-11-18 13:10:00 | E85: 2020-11-18 12:20:00 | F85: -NO_DEFINIDO - Se realiza revisión general del equipo, se realiza limpieza, se realizan pruebas de funcionamiento, se realiza verificación de parámetro por comparación y se entrega al servicio para su respectiva desinfección. Equipo funciona correctamente.&#x0D; &#x0D; Se adjunta reporte de mantenimiento. | G85: Correctivo menor | H85: Bascula Con Tallimetro | I85: 6143 | J85: N/A | K85: 3 | L85: 0.83333333 | M85: 2211.5486 | N85: 0.0013565155 | O85: 737.18287 | P85: 0.0013565155 | Q85: 0.078166752 | R85: 0.38635923 | S85: #N/A
A86: BDG-BASTA-00007156 | B86: 1559.5694 | C86: 41942 | D86: 2020-11-18 11:10:00 | E86: 2020-11-18 10:20:00 | F86: -NO_DEFINIDO - Se realiza revisión general del equipo, se realiza limpieza, se realizan pruebas de funcionamiento, se realiza verificación de parámetro por comparación y se entrega al servicio para su respectiva desinfección. Equipo funciona correctamente.&#x0D; &#x0D; Se adjunta reporte de mantenimiento. | G86: Correctivo menor | H86: Bascula Con Tallimetro | I86: 19426 | J86: 10000001187681 | K86: 6 | L86: 0.83333333 | M86: 1798.3542 | N86: 0.003336384 | O86: 299.72569 | P86: 0.003336384 | Q86: 0.18141909 | R86: 0.69913639 | S86: #N/A
A87: BDG-BASTA-00001066 | B87: 1565.75 | C87: 41942 | D87: 2020-11-12 06:30:00 | E87: 2020-11-12 06:00:00 | F87: -NO_DEFINIDO - Se realiza revisión general del equipo, se realiza limpieza, se realizan pruebas de funcionamiento, se realiza verificación de parámetro por comparación y se entrega al servicio para su respectiva desinfección. Equipo funciona correctamente.&#x0D; &#x0D; Se adjunta reporte de mantenimiento. | G87: Correctivo menor | H87: Bascula Con Tallimetro | I87: 1066 | J87: N/A | K87: 3 | L87: 0.5 | M87: 2205.2708 | N87: 0.0013603771 | O87: 735.09028 | P87: 0.0013603771 | Q87: 0.078380313 | R87: 0.38721171 | S87: #N/A
A88: BDG-BASME-00005924 | B88: 1567.6562 | C88: 41942 | D88: 2020-11-10 09:10:00 | E88: 2020-11-10 08:15:00 | F88: -NO_DEFINIDO - Se realiza revisión general del equipo, se realiza limpieza, se realizan pruebas de funcionamiento, se realiza verificación de parámetro por comparación y se entrega al servicio para su respectiva desinfección. Equipo funciona correctamente.&#x0D; &#x0D; Se adjunta reporte de mantenimiento. | G88: Correctivo menor | H88: Bascula Mecanica | I88: 5924 | J88: N/A | K88: 2 | L88: 0.91666667 | M88: 2203.3819 | N88: 0.00090769556 | O88: 1101.691 | P88: 0.00090769556 | Q88: 0.053005254 | R88: 0.27875068 | S88: #N/A
A89: BDG-BASME-00012811 | B89: 1567.5 | C89: 41942 | D89: 2020-11-10 12:38:00 | E89: 2020-11-10 12:00:00 | F89: -NO_DEFINIDO - Se realiza revisión general del equipo, se realiza limpieza, se realizan pruebas de funcionamiento, se realiza verificación de parámetro por comparación y se entrega al servicio para su respectiva desinfección. Equipo funciona correctamente.&#x0D; &#x0D; Se adjunta reporte de mantenimiento. | G89: Correctivo menor | H89: Bascula Mecanica | I89: 12811 | J89: N/A | K89: 3 | L89: 0.63333333 | M89: 2203.5264 | N89: 0.0013614541 | O89: 734.5088 | P89: 0.0013614541 | Q89: 0.078439864 | R89: 0.38744924 | S89: #N/A
A90: BDG-GRAME-00008319 | B90: 1564.375 | C90: 41942 | D90: 2020-11-13 15:35:00 | E90: 2020-11-13 15:00:00 | F90: -NO_DEFINIDO - Se realiza revisión general del equipo, se realiza limpieza, se realizan pruebas de funcionamiento, se realiza verificación de parámetro por comparación y se entrega al servicio para su respectiva desinfección. Equipo funciona correctamente.&#x0D; &#x0D; Se adjunta reporte de mantenimiento. | G90: Correctivo menor | H90: Gramera | I90: 8319 | J90: N/A | K90: 4 | L90: 0.58333333 | M90: 2206.6493 | N90: 0.0018127031 | O90: 551.66233 | P90: 0.0018127031 | Q90: 0.1030563 | R90: 0.47929578 | S90: #N/A
A91: BFE-LAMAU-00005914 | B91: 1566.5 | C91: 41942 | D91: 2020-11-11 12:30:00 | E91: 2020-11-11 12:00:00 | F91: -NO_DEFINIDO - Se realiza revisión general del equipo, se realiza limpieza, se realizan pruebas de funcionamiento y se entrega al servicio para su respectiva desinfección. Equipo funciona correctamente.&#x0D; &#x0D; Se adjunta reporte de mantenimiento. | G91: Correctivo menor | H91: Lampara Auxiliar De Procedimientos | I91: 5914 | J91: N/A | K91: 2 | L91: 0.5 | M91: 2204.5208 | N91: 0.00090722663 | O91: 1102.2604 | P91: 0.00090722663 | Q91: 0.052978609 | R91: 0.27862891 | S91: #N/A
A92: BFE-LAMAU-00008078 | B92: 1554.5 | C92: 41942 | D92: 2020-11-23 12:30:00 | E92: 2020-11-23 12:00:00 | F92: -NO_DEFINIDO - Se realiza revisión general del equipo, se realiza limpieza, se realizan pruebas de funcionamiento, se realiza verificación de parámetro por comparación y se entrega al servicio para su respectiva desinfección. Equipo funciona correctamente.&#x0D; &#x0D; Se adjunta reporte de mantenimiento. | G92: Correctivo menor | H92: Lampara Auxiliar De Procedimientos | I92: 8078 | J92: N/A | K92: 3 | L92: 0.5 | M92: 2216.5208 | N92: 0.0013534725 | O92: 738.84028 | P92: 0.0013534725 | Q92: 0.077998428 | R92: 0.38568663 | S92: #N/A
A93: BDG-BASTA-00014094 | B93: 1565.4167 | C93: 41942 | D93: 2020-11-12 14:35:00 | E93: 2020-11-12 14:00:00 | F93: -NO_DEFINIDO - Se realiza revisión general del equipo, se realiza limpieza, se realizan pruebas de funcionamiento, se realiza verificación de parámetro por comparación y se entrega al servicio para su respectiva desinfección. Equipo funciona correctamente.&#x0D; &#x0D; Se adjunta reporte de mantenimiento. | G93: Correctivo menor | H93: Bascula Con Tallimetro | I93: 14094 | J93: N/A | K93: 3 | L93: 0.58333333 | M93: 2205.6076 | N93: 0.0013601694 | O93: 735.20255 | P93: 0.0013601694 | Q93: 0.078368826 | R93: 0.38716588 | S93: #N/A
A94: BDG-BASME-00007880 | B94: 1565.625 | C94: 41942 | D94: 2020-11-12 09:35:00 | E94: 2020-11-12 09:00:00 | F94: -NO_DEFINIDO - Se realiza revisión general del equipo, se realiza limpieza, se realizan pruebas de funcionamiento, se realiza verificación de parámetro por comparación y se entrega al servicio para su respectiva desinfección. Equipo funciona correctamente.&#x0D; &#x0D; Se adjunta reporte de mantenimiento. | G94: Correctivo menor | H94: Bascula Mecanica | I94: 7880 | J94: N/A | K94: 4 | L94: 0.58333333 | M94: 2205.3993 | N94: 0.0018137305 | O94: 551.34983 | P94: 0.0018137305 | Q94: 0.10311159 | R94: 0.47948834 | S94: #N/A
A95: BDG-TENPO-00006323 | B95: 1203.5833 | C95: 41942 | D95: 2021-11-09 10:20:00 | E95: 2021-11-09 10:00:00 | F95: -NO_DEFINIDO - Se realiza ajuste de tensiómetro el cual tenia fuga en la pera, se entrega sin novedad. | G95: Correctivo menor | H95: Tensiometro Portatil | I95: 6323 | J95: N/A | K95: 6 | L95: 0.33333333 | M95: 2567.4306 | N95: 0.0023369668 | O95: 427.90509 | P95: 0.0023369668 | Q95: 0.13083127 | R95: 0.56885381 | S95: #N/A
A96: BMO-TRMOH-00009050 | B96: 1175.6042 | C96: 41942 | D96: 2021-12-07 09:50:00 | E96: 2021-12-07 09:30:00 | F96: -NO_DEFINIDO - Se realiza ajuste de sonda de temperatura de termo higrómetro se realizan pruebas y equipo queda funcionando correctamente&#x0D; | G96: Correctivo menor | H96: Termohigrometro Digital | I96: 9050 | J96: N/A | K96: 1 | L96: 0.33333333 | M96: 2595.4097 | N96: 0.00038529562 | O96: 2595.4097 | P96: 0.00038529562 | Q96: 0.02285257 | R96: 0.12951646 | S96: #N/A
A97: BDG-BASME-00005924 | B97: 1483.5833 | C97: 41942 | D97: 2021-02-02 10:20:00 | E97: 2021-02-02 10:00:00 | F97: -NO_DEFINIDO - El equipo se somete a pruebas de metrología por parte de Celsius, en donde se evidencia un desajuste considerable de la bascula, se realiza el proceso de ajuste y se entrega nuevamente a pruebas de metrología y el resultado sigue siendo negativo en donde la bascula no es apta para su uso.&#x0D; El equipo no da respuesta satisfactorias a pruebas finales de funcionamiento .&#x0D; | G97: Correctivo menor | H97: Bascula Mecanica | I97: 5924 | J97: N/A | K97: 2 | L97: 0.33333333 | M97: 2287.4306 | N97: 0.00087434348 | O97: 1143.7153 | P97: 0.00087434348 | Q97: 0.051108302 | R97: 0.27003862 | S97: #N/A
A98: BFE-FOTOF-00015810 | B98: 1565.4167 | C98: 41942 | D98: 2020-11-12 14:20:00 | E98: 2020-11-12 14:00:00 | F98: -NO_DEFINIDO - Se realiza retiro de fotósforo roto del servicio de consulta externa para realizar revisión. | G98: Correctivo menor | H98: Fotoforo | I98: 15810 | J98: N/A | K98: 1 | L98: 0.33333333 | M98: 2205.5972 | N98: 0.00045339194 | O98: 2205.5972 | P98: 0.00045339194 | Q98: 0.026836833 | R98: 0.15059663 | S98: #N/A
... A119: OTP-CAMIL-00015569 | B119: 1411.375 | C119: 41942 | D119: 2021-04-15 16:30:00 | E119: 2021-04-15 15:00:00 | F119: -NO_DEFINIDO - Verificación de estado físico y funcional, limpieza general y desmanchado de estructura metálica, limpieza de ruedas, plataformas plásticas y barandas, ajustes mecánicos de barandas, ajuste de sistema mecánico de altura, ajuste accionamiento de hidráulico cabecero, graduación de frenos, lubricación de bujes de desplazamiento y partes móviles. &#x0D; Pruebas de funcionamiento satisfactorias&#x0D; Se entrega al servicio para su respectiva desinfección, se adjunta reporte de servicio.&#x0D; &#x0D; RECOMENDACIÓN:&#x0D; Equipo se encuentra sin cinturones de seguridad para paciente, se recomienda instalación | G119: Correctivo menor | H119: Camilla De Transporte | I119: 15569 | J119: N/A | K119: 2 | L119: 1.5 | M119: 2359.6875 | N119: 0.00084756986 | O119: 1179.8438 | P119: 0.00084756986 | Q119: 0.049582761 | R119: 0.26296887 | S119: #N/A
A120: BDG-EQUIO-00016126 | B120: 1412.6667 | C120: 41942 | D120: 2021-04-14 08:40:00 | E120: 2021-04-14 08:00:00 | F120: -NO_DEFINIDO - Se realiza revisión general del equipo, se realiza limpieza, se realizan pruebas de funcionamiento, y se entrega al servicio para su respectiva desinfección. Equipo funciona correctamente.&#x0D; &#x0D; Se adjunta reporte de mantenimiento,&#x0D; | G120: Correctivo menor | H120: Equipo De Organos Portatil | I120: 16126/16127 | J120: N/A | K120: 4 | L120: 0.66666667 | M120: 2358.3611 | N120: 0.0016960931 | O120: 589.59028 | P120: 0.0016960931 | Q120: 0.096758741 | R120: 0.45697152 | S120: 600000
A121: BDG-BASTA-00005941 | B121: 1374.4375 | C121: 41942 | D121: 2021-05-22 14:20:00 | E121: 2021-05-22 13:30:00 | F121: -NO_DEFINIDO - Se realiza revisión general del equipo, se realiza limpieza, se realizan pruebas de funcionamiento, se realiza verificación de parámetro por comparación y se entrega al servicio para su respectiva desinfección. Equipo funciona correctamente.&#x0D; &#x0D; Se adjunta reporte de mantenimiento | G121: Correctivo menor | H121: Bascula Con Tallimetro | I121: 5941 | J121: N/A | K121: 5 | L121: 0.83333333 | M121: 2396.5972 | N121: 0.0020862913 | O121: 479.31944 | P121: 0.0020862913 | Q121: 0.11765971 | R121: 0.52813619 | S121: #N/A
A122: BDG-BASTA-00006111 | B122: 1374.4722 | C122: 41942 | D122: 2021-05-22 13:25:00 | E122: 2021-05-22 12:40:00 | F122: -NO_DEFINIDO - Se realiza revisión general del equipo, se realiza limpieza, se realizan pruebas de funcionamiento, se realiza verificación de parámetro por comparación y se entrega al servicio para su respectiva desinfección. Equipo funciona correctamente.&#x0D; &#x0D; Se adjunta reporte de mantenimiento | G122: Correctivo menor | H122: Bascula Con Tallimetro | I122: 6111/12760 | J122: N/A | K122: 3 | L122: 0.75 | M122: 2396.559 | N122: 0.0012517947 | O122: 798.85301 | P122: 0.0012517947 | Q122: 0.072356412 | R122: 0.36278369 | S122: 600000
A123: BDG-BASTA-00006143 | B123: 1374.5139 | C123: 41942 | D123: 2021-05-22 12:35:00 | E123: 2021-05-22 11:40:00 | F123: -NO_DEFINIDO - Se realiza revisión general del equipo, se realiza limpieza, se realizan pruebas de funcionamiento, se realiza verificación de parámetro por comparación y se entrega al servicio para su respectiva desinfección. Equipo funciona correctamente.&#x0D; &#x0D; Se adjunta reporte de mantenimiento | G123: Correctivo menor | H123: Bascula Con Tallimetro | I123: 6143 | J123: N/A | K123: 3 | L123: 0.91666667 | M123: 2396.5243 | N123: 0.0012518129 | O123: 798.84144 | P123: 0.0012518129 | Q123: 0.072357422 | R123: 0.36278785 | S123: #N/A
A124: BDG-BASTA-00007156 | B124: 1374.7257 | C124: 41942 | D124: 2021-05-22 07:22:00 | E124: 2021-05-22 06:35:00 | F124: -NO_DEFINIDO - Se realiza revisión general del equipo, se realiza limpieza, se realizan pruebas de funcionamiento, se realiza verificación de parámetro por comparación y se entrega al servicio para su respectiva desinfección. Equipo funciona correctamente.&#x0D; &#x0D; Se adjunta reporte de mantenimiento | G124: Correctivo menor | H124: Bascula Con Tallimetro | I124: 19426 | J124: 10000001187681 | K124: 6 | L124: 0.78333333 | M124: 2211.4653 | N124: 0.0027131333 | O124: 368.57755 | P124: 0.0027131333 | Q124: 0.15022868 | R124: 0.62345886 | S124: #N/A
A125: BDG-BASTA-00001066 | B125: 1371.6597 | C125: 41942 | D125: 2021-05-25 09:05:00 | E125: 2021-05-25 08:10:00 | F125: -NO_DEFINIDO - Se realiza revisión general del equipo, se realiza limpieza, se realizan pruebas de funcionamiento, se realiza verificación de parámetro por comparación y se entrega al servicio para su respectiva desinfección. Equipo funciona correctamente.&#x0D; &#x0D; Se adjunta reporte de mantenimiento.&#x0D; | G125: Correctivo menor | H125: Bascula Con Tallimetro | I125: 1066 | J125: N/A | K125: 3 | L125: 0.91666667 | M125: 2399.3785 | N125: 0.0012503238 | O125: 799.79282 | P125: 0.0012503238 | Q125: 0.072274537 | R125: 0.36244617 | S125: #N/A
A126: BDG-BASME-00012811 | B126: 1377.5278 | C126: 41942 | D126: 2021-05-19 12:10:00 | E126: 2021-05-19 11:20:00 | F126: -NO_DEFINIDO - Se realiza revisión general del equipo, se realiza limpieza, se realizan pruebas de funcionamiento, se realiza verificación de parámetro por comparación y se entrega al servicio para su respectiva desinfección. Equipo funciona correctamente.&#x0D; &#x0D; Se adjunta reporte de mantenimiento.&#x0D; | G126: Correctivo menor | H126: Bascula Mecanica | I126: 12811 | J126: N/A | K126: 3 | L126: 0.83333333 | M126: 2393.5069 | N126: 0.001253391 | O126: 797.83565 | P126: 0.001253391 | Q126: 0.072445252 | R126: 0.36314976 | S126: #N/A
A127: BDG-GRAME-00008319 | B127: 1371.4167 | C127: 41942 | D127: 2021-05-25 14:50:00 | E127: 2021-05-25 14:00:00 | F127: -NO_DEFINIDO - Se realiza revisión general del equipo, verificación de funcionamiento, limpieza externa, lubricación de partes internas se realiza verificación de ajuste a cero y estabilidad en la superficie, se entrega equipo al servicio para su respectiva desinfección y en funcionamiento sin novedad. &#x0D; &#x0D; Se entrega al servicio para su respectiva desinfección. Equipo funciona correctamente. | G127: Correctivo menor | H127: Gramera | I127: 8319 | J127: N/A | K127: 4 | L127: 0.83333333 | M127: 2399.6181 | N127: 0.0016669319 | O127: 599.90451 | P127: 0.0016669319 | Q127: 0.095176984 | R127: 0.45124077 | S127: #N/A
A128: BFE-LAMAU-00005914 | B128: 1371.7083 | C128: 41942 | D128: 2021-05-25 07:45:00 | E128: 2021-05-25 07:00:00 | F128: -NO_DEFINIDO - Se realiza revisión general del equipo, se realiza limpieza, se realizan pruebas de funcionamiento, se realiza verificación de parámetro por comparación y se entrega al servicio para su respectiva desinfección. Equipo funciona correctamente.&#x0D; &#x0D; Se adjunta reporte de mantenimiento | G128: Correctivo menor | H128: Lampara Auxiliar De Procedimientos | I128: 5914 | J128: N/A | K128: 2 | L128: 0.75 | M128: 2399.3229 | N128: 0.0008335685 | O128: 1199.6615 | P128: 0.0008335685 | Q128: 0.048783997 | R128: 0.25924449 | S128: #N/A
A129: BFE-LAMAU-00008078 | B129: 1371.7014 | C129: 41942 | D129: 2021-05-25 08:00:00 | E129: 2021-05-25 07:10:00 | F129: -NO_DEFINIDO - Se realiza revisión general del equipo, se realiza limpieza, se realizan pruebas de funcionamiento, y se entrega al servicio para su respectiva desinfección. Equipo funciona correctamente.&#x0D; &#x0D; Se adjunta reporte de mantenimiento,&#x0D; | G129: Correctivo menor | H129: Lampara Auxiliar De Procedimientos | I129: 8078 | J129: N/A | K129: 3 | L129: 0.83333333 | M129: 2399.3333 | N129: 0.0012503473 | O129: 799.77778 | P129: 0.0012503473 | Q129: 0.072275847 | R129: 0.36245157 | S129: #N/A
A130: BDG-BASTA-00014094 | B130: 1371.7014 | C130: 41942 | D130: 2021-05-25 08:05:00 | E130: 2021-05-25 07:10:00 | F130: -NO_DEFINIDO - Se realiza revisión general del equipo, se realiza limpieza, se realizan pruebas de funcionamiento, se realiza verificación de parámetro por comparación y se entrega al servicio para su respectiva desinfección. Equipo funciona correctamente.&#x0D; &#x0D; Se adjunta reporte de mantenimiento.&#x0D; | G130: Correctivo menor | H130: Bascula Con Tallimetro | I130: 14094 | J130: N/A | K130: 3 | L130: 0.91666667 | M130: 2399.3368 | N130: 0.0012503455 | O130: 799.77894 | P130: 0.0012503455 | Q130: 0.072275746 | R130: 0.36245115 | S130: #N/A
A131: BDG-BASME-00007880 | B131: 1372.7014 | C131: 41942 | D131: 2021-05-24 08:05:00 | E131: 2021-05-24 07:10:00 | F131: -NO_DEFINIDO - Se realiza revisión general del equipo, se realiza limpieza, se realizan pruebas de funcionamiento, se realiza verificación de parámetro por comparación y se entrega al servicio para su respectiva desinfección. Equipo funciona correctamente.&#x0D; &#x0D; Se adjunta reporte de mantenimiento.&#x0D; | G131: Correctivo menor | H131: Bascula Mecanica | I131: 7880 | J131: N/A | K131: 4 | L131: 0.91666667 | M131: 2398.3368 | N131: 0.0016678225 | O131: 599.5842 | P131: 0.0016678225 | Q131: 0.095225328 | R131: 0.45141667 | S131: #N/A
A132: BFE-LAMAU-00000237 | B132: 1377.6667 | C132: 41942 | D132: 2021-05-19 09:00:00 | E132: 2021-05-19 08:00:00 | F132: -NO_DEFINIDO - Se realiza revisión general del equipo, se realiza limpieza, se realizan pruebas de funcionamiento, y se entrega al servicio para su respectiva desinfección. Equipo funciona correctamente.&#x0D; &#x0D; Se adjunta reporte de mantenimiento,&#x0D; | G132: Correctivo menor | H132: Lampara Auxiliar De Procedimientos | I132: 237/14680 | J132: N/A | K132: 2 | L132: 1 | M132: 2393.375 | N132: 0.00083564005 | O132: 1196.6875 | P132: 0.00083564005 | Q132: 0.048902219 | R132: 0.25979671 | S132: 600000
A133: BLP-CNSGR-00012975 | B133: 1368.6493 | C133: 41942 | D133: 2021-05-28 09:10:00 | E133: 2021-05-28 08:25:00 | F133: -NO_DEFINIDO - Se realiza revisión general del equipo, se realiza limpieza, se realizan pruebas de funcionamiento, y se entrega al servicio para su respectiva desinfección. Equipo funciona correctamente.&#x0D; &#x0D; Se adjunta reporte de mantenimiento. | G133: Correctivo menor | H133: Consola Grabador | I133: 12975 | J133: N/A | K133: 2 | L133: 0.75 | M133: 2402.3819 | N133: 0.00083250709 | O133: 1201.191 | P133: 0.00083250709 | Q133: 0.048723417 | R133: 0.25896139 | S133: #N/A
A134: BDG-EQUIO-00016128 | B134: 1412.7083 | C134: 41942 | D134: 2021-04-14 07:40:00 | E134: 2021-04-14 07:00:00 | F134: -NO_DEFINIDO - Se realiza revisión general del equipo, se realiza limpieza, se realizan pruebas de funcionamiento, y se entrega al servicio para su respectiva desinfección. Equipo funciona correctamente.&#x0D; Se le informa al servicio que se deben solicitar las baterías de recambio del equipo para mantener el buen funcionamiento&#x0D; Se adjunta reporte de mantenimiento,&#x0D; | G134: Correctivo menor | H134: Equipo De Organos Portatil | I134: 16128/16129 | J134: N/A | K134: 3 | L134: 0.66666667 | M134: 2358.3194 | N134: 0.0012720923 | O134: 786.10648 | P134: 0.0012720923 | Q134: 0.073485458 | R134: 0.36742294 | S134: 600000
A135: BFT-BANTR-00015249 | B135: 1341.3819 | C135: 41942 | D135: 2021-06-24 15:50:00 | E135: 2021-06-24 14:50:00 | F135: -NO_DEFINIDO - Se realiza revisión general del equipo, se realiza limpieza, se realizan pruebas de funcionamiento, y se entrega al servicio para su respectiva desinfección. Equipo funciona correctamente.&#x0D; &#x0D; Se adjunta reporte de mantenimiento,&#x0D; | G135: Correctivo menor | H135: Banda Trotadora | I135: 15249 | J135: N/A | K135: 3 | L135: 1 | M135: 2429.6597 | N135: 0.0012347408 | O135: 809.88657 | P135: 0.0012347408 | Q135: 0.071406728 | R135: 0.35885952 | S135: #N/A
A136: BFT-BANTR-00015250 | B136: 1341.4306 | C136: 41942 | D136: 2021-06-24 14:50:00 | E136: 2021-06-24 13:40:00 | F136: -NO_DEFINIDO - Se realiza revisión general del equipo, se realiza limpieza, se realizan pruebas de funcionamiento, y se entrega al servicio para su respectiva desinfección. Equipo funciona correctamente.&#x0D; &#x0D; Se adjunta reporte de mantenimiento,&#x0D; | G136: Correctivo menor | H136: Banda Trotadora | I136: 15250 | J136: N/A | K136: 4 | L136: 1.1666667 | M136: 2429.6181 | N136: 0.0016463493 | O136: 607.40451 | P136: 0.0016463493 | Q136: 0.094058875 | R136: 0.4471595 | S136: #N/A
A137: BFT-ELIPT-00015248 | B137: 1341.375 | C137: 41942 | D137: 2021-06-24 15:50:00 | E137: 2021-06-24 15:00:00 | F137: -NO_DEFINIDO - Se realiza revisión general del equipo, se realiza limpieza, se realizan pruebas de funcionamiento, y se entrega al servicio para su respectiva desinfección. Equipo funciona correctamente.&#x0D; &#x0D; Se adjunta reporte de mantenimiento,&#x0D; | G137: Correctivo menor | H137: Eliptica | I137: 15248 | J137: N/A | K137: 8 | L137: 0.83333333 | M137: 2429.6597 | N137: 0.0032926421 | O137: 303.70747 | P137: 0.0032926421 | Q137: 0.1792679 | R137: 0.69436117 | S137: #N/A
A138: OTP-CAMIL-00001384 | B138: 1347.625 | C138: 41942 | D138: 2021-06-18 10:30:00 | E138: 2021-06-18 09:00:00 | F138: -NO_DEFINIDO - Se realiza cromado de barandas el cual se encontraban en avanzada deterioro, se realiza instalación de las mismas. &#x0D; Equipo funcionando correctamente | G138: Correctivo menor | H138: Camilla De Transporte | I138: 1384 | J138: N/A | K138: 2 | L138: 1.5 | M138: 2423.4375 | N138: 0.00082527402 | O138: 1211.7188 | P138: 0.00082527402 | Q138: 0.048310489 | R138: 0.25702928 | S138: #N/A
A139: OTP-CAMIL-00007666 | B139: 1309.625 | C139: 41942 | D139: 2021-07-26 10:30:00 | E139: 2021-07-26 09:00:00 | F139: -NO_DEFINIDO - Se realiza verificación del movimiento de cabecero encontrando daño en bisagra, se procede a realizar el cambio por una nueva.&#x0D; Equipo se entrega en buenas condiciones físicas y de funcionamiento | G139: Correctivo menor | H139: Camilla De Transporte | I139: 7666 | J139: N/A | K139: 6 | L139: 1.5 | M139: 2461.4375 | N139: 0.0024376 | O139: 410.23958 | P139: 0.0024376 | Q139: 0.13606349 | R139: 0.5841938 | S139: #N/A
A140: BEF-NEVER-00012925 | B140: 1299.7083 | C140: 41942 | D140: 2021-08-05 07:56:00 | E140: 2021-08-05 07:00:00 | F140: -NO_DEFINIDO - Se realiza revisión general del equipo, se realiza limpieza, se realizan pruebas de funcionamiento, se realiza verificación de parámetro por comparación y se entrega al servicio para su respectiva desinfección. Equipo funciona correctamente.&#x0D; &#x0D; Se adjunta reporte de mantenimiento | G140: Correctivo menor | H140: Nevera | I140: 12925 | J140: N/A | K140: 7 | L140: 0.93333333 | M140: 2471.3306 | N140: 0.0028324823 | O140: 353.04722 | P140: 0.0028324823 | Q140: 0.1562921 | R140: 0.63929456 | S140: #N/A
A141: OTP-CAMIL-00015639 | B141: 1305.7083 | C141: 41942 | D141: 2021-07-30 08:00:00 | E141: 2021-07-30 07:00:00 | F141: -NO_DEFINIDO - Se realiza fabricación e instalación de seguro de baranda. &#x0D; Se realizan pruebas de funcionamiento satisfactorias&#x0D; Equipo operativo | G141: Correctivo menor | H141: Camilla De Transporte | I141: 15639 | J141: N/A | K141: 5 | L141: 1 | M141: 2465.3333 | N141: 0.0020281233 | O141: 493.06667 | P141: 0.0020281233 | Q141: 0.11457489 | R141: 0.51815095 | S141: #N/A
A142: OTP-CAMIL-00008945 | B142: 1305.5417 | C142: 41942 | D142: 2021-07-30 12:00:00 | E142: 2021-07-30 11:00:00 | F142: -NO_DEFINIDO - Se realiza reparación de soporte de baranda&#x0D; Se realizan pruebas de funcionamiento satisfactorias&#x0D; Equipo operativo | G142: Correctivo menor | H142: Camilla De Transporte | I142: 8945 | J142: N/A | K142: 1 | L142: 1 | M142: 2465.5 | N142: 0.00040559724 | O142: 2465.5 | P142: 0.00040559724 | Q142: 0.024042106 | R142: 0.13585527 | S142: #N/A
A143: OTP-CAMIL-00014303 | B143: 1299.625 | C143: 41942 | D143: 2021-08-05 10:00:00 | E143: 2021-08-05 09:00:00 | F143: -NO_DEFINIDO - Se realiza reparación e instalación de palanca de activación de hidráulico y base soporte de cabecero, instalación de 1 hidráulico cabecero nuevo. &#x0D; Pruebas de funcionamiento satisfactorias | G143: Correctivo menor | H143: Camilla De Transporte | I143: 14303 | J143: N/A | K143: 3 | L143: 1 | M143: 2471.4167 | N143: 0.0012138787 | O143: 823.80556 | P143: 0.0012138787 | Q143: 0.070243654 | R143: 0.35402619 | S143: #N/A
A144: BFE-FOTOF-00016943 | B144: 1244.6146 | C144: 41942 | D144: 2021-09-29 10:00:00 | E144: 2021-09-29 09:15:00 | F144: -NO_DEFINIDO - Se realiza revisión general del equipo, se realiza limpieza, se realizan pruebas de funcionamiento y se entrega al servicio para su respectiva desinfección. Equipo funciona correctamente.&#x0D; &#x0D; Se adjunta reporte de mantenimiento.&#x0D; | G144: Correctivo menor | H144: Fotoforo | I144: 16943 | J144: N/A | K144: 2 | L144: 0.75 | M144: 2526.4167 | N144: 0.00079163506 | O144: 1263.2083 | P144: 0.00079163506 | Q144: 0.046387718 | R144: 0.24797719 | S144: #N/A
A145: OTP-CAMIL-00016853 | B145: 1273.5833 | C145: 41942 | D145: 2021-08-31 11:00:00 | E145: 2021-08-31 10:00:00 | F145: -NO_DEFINIDO - Se realiza reparación y ajuste en bisagra del cabecero &#x0D; Pruebas de funcionamiento satisfactorias | G145: Correctivo menor | H145: Camilla De Transporte | I145: 16853 | J145: N/A | K145: 4 | L145: 1 | M145: 2497.4583 | N145: 0.0016016283 | O145: 624.36458 | P145: 0.0016016283 | Q145: 0.091624736 | R145: 0.43818698 | S145: #N/A
A146: OTP-CAMIL-00001269 | B146: 1260.625 | C146: 41942 | D146: 2021-09-13 10:00:00 | E146: 2021-09-13 09:00:00 | F146: -NO_DEFINIDO - Fabricación e instalación de los 2 pasadores de barandas, pruebas de funcionamiento satisfactorias. | G146: Correctivo menor | H146: Camilla De Transporte | I146: 1269 | J146: N/A | K146: 1 | L146: 1 | M146: 2510.4167 | N146: 0.00039834025 | O146: 2510.4167 | P146: 0.00039834025 | Q146: 0.023617062 | R146: 0.13359472 | S146: #N/A
... A164: BDG-TENSI-00015257 | B164: 1221.5208 | C164: 41942 | D164: 2021-10-22 12:20:00 | E164: 2021-10-22 11:30:00 | F164: -NO_DEFINIDO - Se realiza revisión general del equipo, se realiza limpieza, se realizan pruebas de funcionamiento, se realiza verificación de parámetro por comparación y se entrega al servicio para su respectiva desinfección. Equipo funciona correctamente.&#x0D; &#x0D; Se adjunta reporte de mantenimiento.&#x0D; | G164: Correctivo menor | H164: Tensiometro Portatil | I164: 15257 | J164: N/A | K164: 4 | L164: 0.83333333 | M164: 2549.5139 | N164: 0.0015689265 | O164: 637.37847 | P164: 0.0015689265 | Q164: 0.089840657 | R164: 0.43153387 | S164: #N/A
A165: BDG-EQUIO-00016126 | B165: 1231.5972 | C165: 41942 | D165: 2021-10-12 10:20:00 | E165: 2021-10-12 09:40:00 | F165: -NO_DEFINIDO - Se realiza revisión general del equipo, se evidencia que el equipo requiere cambio de batería las cuales deben ser solicitadas al área de compras, se informa novedad al servicio. Se realiza entrega del equipo al servicio para su respectiva desinfección. Equipo funciona correctamente.&#x0D; &#x0D; Se adjunta reporte de mantenimiento | G165: Correctivo menor | H165: Equipo De Organos Portatil | I165: 16126/16127 | J165: N/A | K165: 4 | L165: 0.66666667 | M165: 2539.4306 | N165: 0.0015751563 | O165: 634.85764 | P165: 0.0015751563 | Q165: 0.090180797 | R165: 0.43280735 | S165: 600000
A166: BDG-EQUIO-00016128 | B166: 1231.5556 | C166: 41942 | D166: 2021-10-12 11:20:00 | E166: 2021-10-12 10:40:00 | F166: -NO_DEFINIDO - Se realiza revisión general del equipo, se evidencia que el equipo requiere cambio de baterías las cuales deben ser solicitadas por el servicio al área de compras y se entrega al servicio para su respectiva desinfección. Equipo funciona correctamente.&#x0D; &#x0D; Se adjunta reporte de mantenimiento | G166: Correctivo menor | H166: Equipo De Organos Portatil | I166: 16128/16129 | J166: N/A | K166: 3 | L166: 0.66666667 | M166: 2539.4722 | N166: 0.0011813478 | O166: 846.49074 | P166: 0.0011813478 | Q166: 0.068427136 | R166: 0.34641666 | S166: 600000
A167: BDG-EQUIO-00013153 | B167: 635.3125 | C167: 41942 | D167: 2023-05-31 17:00:00 | E167: 2023-05-31 16:30:00 | F167: 30/05/2023-NO_DEFINIDO - Solicitud de Servico Creada desde AMSi, 02/06/2023-Biomedico2 - Se realiza verificación de cabezal de oftalmoscopio de equipo de órganos de consultorio 7 Se encuentra con cabezal con ruptura de carcasa,se retira para su verificación Se realiza verificación y ajuste de carcasa y mecanismo interno y al realizar pruebas de funcionamiento y no son satisfactorias,filtros internos con fractura y disco interno de dioptrias sueltas Se realiza cambio por uno de BACKUP | G167: Correctivo menor | H167: Equipo Organos De Los Sentidos | I167: 13153 | J167: N/A | K167: 9 | L167: 0.5 | M167: 3135.7083 | N167: 0.0028701649 | O167: 348.41204 | P167: 0.0028701649 | Q167: 0.15819753 | R167: 0.64415476 | S167: #N/A
A168: OTP-CAMIL-00000974 | B168: 1237.1667 | C168: 41942 | D168: 2021-10-06 21:00:00 | E168: 2021-10-06 20:00:00 | F168: -NO_DEFINIDO - Se realiza limpieza general, desmanchado de estructura metálica, limpieza de tapizado. &#x0D; Pruebas de funcionamiento ok | G168: Correctivo menor | H168: Camilla Fija-Divan | I168: 974 | J168: N/A | K168: 1 | L168: 1 | M168: 2533.875 | N168: 0.00039465246 | O168: 2533.875 | P168: 0.00039465246 | Q168: 0.023400996 | R168: 0.13244371 | S168: #N/A
A169: OTP-CAMIL-00000941 | B169: 1237.2083 | C169: 41942 | D169: 2021-10-06 20:00:00 | E169: 2021-10-06 19:00:00 | F169: -NO_DEFINIDO - Se realiza limpieza general, desmanchado de estructura metálica, limpieza de tapizado superior&#x0D; Pruebas de funcionamiento ok&#x0D; RECOMENDACIONES: Se recomienda cambio de tapizado inferior | G169: Correctivo menor | H169: Camilla Fija-Divan | I169: 941 | J169: N/A | K169: 2 | L169: 1 | M169: 2533.8333 | N169: 0.0007893179 | O169: 1266.9167 | P169: 0.0007893179 | Q169: 0.046255129 | R169: 0.24734961 | S169: #N/A
...
